Workbook

Sheet Lauren no longer working
A1: March 2022 Monthly Budget
A2: Income: | B2: 1st half of month | C2: 2nd half of month | F2: what we make 1st half of month | G2: what we owe 1st half of month | H2: money left over
A3: Brian | B3: 3796.66 | C3: 3796.66 | F3: =B3+B4 -> 3796.66 | G3: =C9+C10+C11+C12+C13+C14+C15 -> 3528.31 | H3: =F3-G3 -> 268.35
A4: Lauren
F5: what we make 2nd half of month | G5: what we owe 2nd half of month | H5: money left over
F6: =B3+B4 -> 3796.66 | G6: =C18+C19+C20+C21+C22+C23 -> 1679.22 | H6: =F6-G6 -> 2117.44
A7: Expenses: | B7: Due Date: | C7: Expense Cost:
A8: 1st half of month:
A9: Mortgage Payment (automatic) | B9: 1st of each month | C9: 2271.33
A10: youtube tv (automatic) | B10: 1st of each month | C10: 64.99
A11: Starlink(automatic) | B11: 3rd of each month | C11: 110 | F11: Average for two week span
A12: Mohela Student Interest Loan (automatic) | B12: 6th of each month | C12: 542.02 | F12: =(H3+H6)/2 -> 1192.895
A13: Travlers Insurance | B13: 7th of each month | C13: 165.33
A14: Disney+(automatic) | B14: 13th of each month | C14: 8.55
A15: Toyota Financial Payment (automatic) | B15: 15th of each month | C15: 366.09
A17: 2nd half of month:
A18: Ram Truck Payment (automatic) | B18: 16th of each month | C18: 710.16
A19: Greenbrier Water, trash payment | B19: 18th of each month | C19: 47.1
A20: At&t Payment (automatic) | B20: 22nd of each month | C20: 243.86
A21: Entergy Payment (automatic) | B21: 27th of each month | C21: 313.4
A22: Pool Loan Payment(automatic) | B22: 26th of each month | C22: 342.81
A23: Netflix | B23: 28th of each month | C23: 21.89
A31: Arkansas Protection Services
A32: Spotify USA (automatic)
A33: Lawn Mower
A34: Lowes
A35: Synchrony Bank Payment - Mattress (automatic)

Sheet June 2022
A1: June 2022 Monthly Budget
A2: Income: | B2: 1st half of month | C2: 2nd half of month | F2: what we make 1st half of month | G2: what we owe 1st half of month | H2: money left over
A3: Brian | B3: 3796.66 | C3: 3796.66 | F3: =B3+B4 -> 5319.655 | G3: =C9+C10+C11+C12+C13+C14+C15+C16+C17 -> 3546.16 | H3: =F3-G3 -> 1773.495
A4: Lauren | B4: 1522.995 | C4: 1522.995
F5: what we make 2nd half of month | G5: what we owe 2nd half of month | H5: money left over
F6: =B3+B4 -> 5319.655 | G6: =C20+C21+C22+C23+C24+C25+C26+C27 -> 1775 | H6: =F6-G6 -> 3544.655
A7: Expenses: | B7: Due Date: | C7: Expense Cost:
A8: 1st half of month:
A9: Mortgage Payment (automatic) | B9: 1st of each month | C9: 2271.33
A10: youtube tv (automatic) | B10: 1st of each month | C10: 80.23
A11: Swyft Internet(automatic) | B11: 3rd of each month | C11: 98.39 | F11: Average for two week span
A12: Arkansas Protection Services | B12: Paid Quartly | F12: =(H3+H6)/2 -> 2659.075
A13: Mohela Student Interest Loan (automatic) | B13: 6th of each month | C13: 542.02
A14: Travlers Insurance | B14: 7th of each month | C14: 165.33
A15: Spotify USA (automatic) | B15: 9th of each month | C15: 14.22
A16: Disney+(automatic) | B16: 13th of each month | C16: 8.55
A17: Toyota Financial Payment (automatic) | B17: 15th of each month | C17: 366.09
A19: 2nd half of month:
A20: Ram Truck Payment (automatic) | B20: 16th of each month | C20: 710.16
A21: Greenbrier Water, trash payment | B21: 18th of each month | C21: 62.31
A22: At&t Payment (automatic) | B22: 22nd of each month | C22: 243.86
A23: Lawn Mower | B23: 29th of each month | C23: 120.67
A24: Entergy Payment (automatic) | B24: 27th of each month | C24: 204.3
A25: Pool Loan Payment(automatic) | B25: 26th of each month | C25: 342.81
A26: Synchrony Bank Payment - Mattress (automatic) | B26: 27th of each month | C26: 69
A27: Netflix | B27: 28th of each month | C27: 21.89
A40: Disney Trip Expenses | B40: Amount owed
A41: House | B41: 810
A42: Disney Tickets | B42: 1354.12
A43: Car Rental | B43: 477.36
A44: Universal Tickets | B44: 1398.05
B45: 4039.53

Sheet May 2022
A1: May 2022 Monthly Budget
A2: Income: | B2: 1st half of month | C2: 2nd half of month | F2: what we make 1st half of month | G2: what we owe 1st half of month | H2: money left over
A3: Brian | B3: 3796.66 | C3: 3796.66 | F3: =B3+B4 -> 5319.655 | G3: =C9+C10+C11+C12+C13+C14+C15+C16+C17 -> 3546.16 | H3: =F3-G3 -> 1773.495
A4: Lauren | B4: 1522.995 | C4: 1522.995
F5: what we make 2nd half of month | G5: what we owe 2nd half of month | H5: money left over
F6: =B3+B4 -> 5319.655 | G6: =C20+C21+C22+C23+C24+C25+C26+C27 -> 1782.68 | H6: =F6-G6 -> 3536.975
A7: Expenses: | B7: Due Date: | C7: Expense Cost:
A8: 1st half of month:
A9: Mortgage Payment (automatic) | B9: 1st of each month | C9: 2271.33
A10: youtube tv (automatic) | B10: 1st of each month | C10: 80.23
A11: Swyft Internet(automatic) | B11: 3rd of each month | C11: 98.39 | F11: Average for two week span
A12: Arkansas Protection Services | B12: Paid Quartly | F12: =(H3+H6)/2 -> 2655.235
A13: Mohela Student Interest Loan (automatic) | B13: 6th of each month | C13: 542.02
A14: Travlers Insurance | B14: 7th of each month | C14: 165.33
A15: Spotify USA (automatic) | B15: 9th of each month | C15: 14.22
A16: Disney+(automatic) | B16: 13th of each month | C16: 8.55
A17: Toyota Financial Payment (automatic) | B17: 15th of each month | C17: 366.09
A19: 2nd half of month:
A20: Ram Truck Payment (automatic) | B20: 16th of each month | C20: 710.16
A21: Greenbrier Water, trash payment | B21: 18th of each month | C21: 62.31
A22: At&t Payment (automatic) | B22: 22nd of each month | C22: 243.86
A23: Lawn Mower | B23: 29th of each month | C23: 120.67
A24: Entergy Payment (automatic) | B24: 27th of each month | C24: 211.98
A25: Pool Loan Payment(automatic) | B25: 26th of each month | C25: 342.81
A26: Synchrony Bank Payment - Mattress (automatic) | B26: 27th of each month | C26: 69
A27: Netflix | B27: 28th of each month | C27: 21.89
A40: Disney Trip Expenses | B40: Amount owed
A41: House | B41: 810
A42: Disney Tickets | B42: 1354.12
A43: Car Rental | B43: 477.36
A44: Universal Tickets | B44: 1398.05
B45: 4039.53

Sheet April 2022
A1: April 2022 Monthly Budget
A2: Income: | B2: 1st half of month | C2: 2nd half of month | F2: what we make 1st half of month | G2: what we owe 1st half of month | H2: money left over
A3: Brian | B3: 3796.66 | C3: 3796.66 | F3: =B3+B4 -> 5319.655 | G3: =C9+C10+C11+C12+C13+C14+C15+C16+C17 -> 3546.16 | H3: =F3-G3 -> 1773.495
A4: Lauren | B4: 1522.995 | C4: 1522.995
F5: what we make 2nd half of month | G5: what we owe 2nd half of month | H5: money left over
F6: =B3+B4 -> 5319.655 | G6: =C20+C21+C22+C23+C24+C25+C26+C27+C28 -> 2032.46 | H6: =F6-G6 -> 3287.195
A7: Expenses: | B7: Due Date: | C7: Expense Cost:
A8: 1st half of month:
A9: Mortgage Payment (automatic) | B9: 1st of each month | C9: 2271.33
A10: youtube tv (automatic) | B10: 1st of each month | C10: 80.23
A11: Swyft Internet(automatic) | B11: 3rd of each month | C11: 98.39 | F11: Average for two week span
A12: Arkansas Protection Services | B12: Paid Quartly | F12: =(H3+H6)/2 -> 2530.345
A13: Mohela Student Interest Loan (automatic) | B13: 6th of each month | C13: 542.02
A14: Travlers Insurance | B14: 7th of each month | C14: 165.33
A15: Spotify USA (automatic) | B15: 9th of each month | C15: 14.22
A16: Disney+(automatic) | B16: 13th of each month | C16: 8.55
A17: Toyota Financial Payment (automatic) | B17: 15th of each month | C17: 366.09
A19: 2nd half of month:
A20: Ram Truck Payment (automatic) | B20: 16th of each month | C20: 710.16
A21: Greenbrier Water, trash payment | B21: 18th of each month | C21: 47.1
A22: At&t Payment (automatic) | B22: 22nd of each month | C22: 243.86
A23: Lawn Mower | B23: 29th of each month | C23: 120.67
A24: Entergy Payment (automatic) | B24: 27th of each month | C24: 226.97
A25: Lowes | B25: 2nd half of the month | C25: 250
A26: Pool Loan Payment(automatic) | B26: 26th of each month | C26: 342.81
A27: Synchrony Bank Payment - Mattress (automatic) | B27: 27th of each month | C27: 69
A28: Netflix | B28: 28th of each month | C28: 21.89
A32: Credit cards: | B32: Amount owed | F32: Combined amount:
A33: Citi Card payment | B33: 0 | F33: 17144.66
A34: Lawn Mower | B34: 3378.53
A35: Lowes | B35: 0 | C35: pay 2567.19 on 4/18 | F35: Combined - normal pay
A36: Payment - Mattress (automatic) | B36: 2438 | F36: =F33-B3 -> 13348
A37: Amex | B37: 0
A38: Sams club Mastercard | B38: 0 | C38: pay 1727.18 on 4/18 | F38: Bonus - 2 week spending
A39: Amazon | B39: 0 | F39: =F36-800 -> 12548
A41: Disney Trip Expenses | B41: Amount owed
A42: House | B42: 810
A43: Disney Tickets | B43: 1354.12
A44: Car Rental | B44: 477.36
A45: Universal Tickets | B45: 1398.05
B46: 4039.53

Sheet March 2022
A1: March 2022 Monthly Budget
A2: Income: | B2: 1st half of month | C2: 2nd half of month | F2: what we make 1st half of month | G2: what we owe 1st half of month | H2: money left over
A3: Brian | B3: 3796.66 | C3: 3796.66 | F3: =B3+B4 -> 5273.95 | G3: =C9+C10+C11+C12+C13+C14+C15+C16+C17 -> 3546.16 | H3: =F3-G3 -> 1727.79
A4: Lauren | B4: 1477.29 | C4: 1477.29
F5: what we make 2nd half of month | G5: what we owe 2nd half of month | H5: money left over
F6: =B3+B4 -> 5273.95 | G6: =C20+C21+C22+C23+C24+C25+C26+C27+C28 -> 2101.81 | H6: =F6-G6 -> 3172.14
A7: Expenses: | B7: Due Date: | C7: Expense Cost:
A8: 1st half of month:
A9: Mortgage Payment (automatic) | B9: 1st of each month | C9: 2271.33
A10: youtube tv (automatic) | B10: 1st of each month | C10: 80.23
A11: Swyft Internet(automatic) | B11: 3rd of each month | C11: 98.39 | F11: Average for two week span
A12: Arkansas Protection Services | B12: Paid Quartly | F12: =(H3+H6)/2 -> 2449.965
A13: Mohela Student Interest Loan (automatic) | B13: 6th of each month | C13: 542.02
A14: Travlers Insurance | B14: 7th of each month | C14: 165.33
A15: Spotify USA (automatic) | B15: 9th of each month | C15: 14.22
A16: Disney+(automatic) | B16: 13th of each month | C16: 8.55
A17: Toyota Financial Payment (automatic) | B17: 15th of each month | C17: 366.09
A19: 2nd half of month:
A20: Ram Truck Payment (automatic) | B20: 16th of each month | C20: 710.16
A21: Greenbrier Water, trash payment | B21: 18th of each month | C21: 47.1
A22: At&t Payment (automatic) | B22: 22nd of each month | C22: 243.86
A23: Lawn Mower | B23: 29th of each month | C23: 120.67
A24: Entergy Payment (automatic) | B24: 27th of each month | C24: 296.32
A25: Lowes | B25: 2nd half of the month | C25: 250
A26: Pool Loan Payment(automatic) | B26: 26th of each month | C26: 342.81
A27: Synchrony Bank Payment - Mattress (automatic) | B27: 27th of each month | C27: 69
A28: Netflix | B28: 28th of each month | C28: 21.89

Sheet February 2022
A1: January 2022 Monthly Budget
A2: Income: | B2: 1st half of month | C2: 2nd half of month | F2: what we make 1st half of month | G2: what we owe 1st half of month | H2: money left over
A3: Brian | B3: 3916.75 | C3: 3916.75 | F3: =B3+B4 -> 5391.46 | G3: =C9+C10+C11+C12+C13+C14+C15+C16+C17 -> 3546.16 | H3: =F3-G3 -> 1845.3
A4: Lauren | B4: 1474.71 | C4: 1474.71
F5: what we make 2nd half of month | G5: what we owe 2nd half of month | H5: money left over
F6: =B3+B4 -> 5391.46 | G6: =C20+C21+C22+C23+C24+C25+C26+C27+C28 -> 2116.7 | H6: =F6-G6 -> 3274.76
A7: Expenses: | B7: Due Date: | C7: Expense Cost:
A8: 1st half of month:
A9: Mortgage Payment (automatic) | B9: 1st of each month | C9: 2271.33
A10: youtube tv (automatic) | B10: 1st of each month | C10: 80.23
A11: Swyft Internet(automatic) | B11: 3rd of each month | C11: 98.39 | F11: Average for two week span
A12: Arkansas Protection Services | B12: Paid Quartly | F12: =(H3+H6)/2 -> 2560.03
A13: Mohela Student Interest Loan (automatic) | B13: 6th of each month | C13: 542.02
A14: Travlers Insurance | B14: 7th of each month | C14: 165.33
A15: Spotify USA (automatic) | B15: 9th of each month | C15: 14.22
A16: Disney+(automatic) | B16: 13th of each month | C16: 8.55
A17: Toyota Financial Payment (automatic) | B17: 15th of each month | C17: 366.09
A19: 2nd half of month:
A20: Ram Truck Payment (automatic) | B20: 16th of each month | C20: 710.16
A21: Greenbrier Water, trash payment | B21: 18th of each month | C21: 47.1
A22: At&t Payment (automatic) | B22: 22nd of each month | C22: 243.86
A23: Lawn Mower | B23: 29th of each month | C23: 120.67
A24: Entergy Payment (automatic) | B24: 27th of each month | C24: 313.4
A25: Lowes | B25: 2nd half of the month | C25: 250
A26: Pool Loan Payment(automatic) | B26: 26th of each month | C26: 342.81
A27: Synchrony Bank Payment - Mattress (automatic) | B27: 27th of each month | C27: 69
A28: Netflix | B28: 28th of each month | C28: 19.7

Sheet January 2022
A1: January 2022 Monthly Budget
A2: Income: | B2: 1st half of month | C2: 2nd half of month | F2: what we make 1st half of month | G2: what we owe 1st half of month | H2: money left over
A3: Brian | B3: 3879.35 | C3: 3879.35 | F3: =B3+B4 -> 5354.06 | G3: =C9+C10+C11+C12+C13+C14+C15+C16+C17+C18 -> 3809.16 | H3: =F3-G3 -> 1544.9
A4: Lauren | B4: 1474.71 | C4: 1474.71
F5: what we make 2nd half of month | G5: what we owe 2nd half of month | H5: money left over
F6: =B3+B4 -> 5354.06 | G6: =C21+C22+C23+C24+C25+C26+C27+C28+C29+C30 -> 2142.86 | H6: =F6-G6 -> 3211.2
A7: Expenses: | B7: Due Date: | C7: Expense Cost:
A8: 1st half of month:
A9: Mortgage Payment (automatic) | B9: 1st of each month | C9: 2271.33
A10: youtube tv (automatic) | B10: 1st of each month | C10: 80.23
A11: Swyft Internet(automatic) | B11: 3rd of each month | C11: 98.39 | F11: Average for two week span
A12: Arkansas Protection Services | B12: Paid Quartly | C12: 113 | F12: =(H3+H6)/2 -> 2378.05
A13: Mohela Student Interest Loan (automatic) | B13: 6th of each month | C13: 542.02
A14: Travlers Insurance | B14: 7th of each month | C14: 165.33
A15: Spotify USA (automatic) | B15: 9th of each month | C15: 14.22
A16: Disney+(automatic) | B16: 13th of each month | C16: 8.55
A17: Citi card payment | B17: 1st half of the month | C17: 150
A18: Toyota Financial Payment (automatic) | B18: 15th of each month | C18: 366.09
A20: 2nd half of month:
A21: Ram Truck Payment (automatic) | B21: 16th of each month | C21: 710.16
A22: Greenbrier Water, trash payment | B22: 18th of each month | C22: 62.5
A23: At&t Payment (automatic) | B23: 22nd of each month | C23: 243.86
A24: Lawn Mower | B24: 29th of each month | C24: 120.67
A25: Entergy Payment (automatic) | B25: 27th of each month | C25: 174.16
A26: Citi card payment | B26: 2nd half of the month | C26: 150
A27: Lowes | B27: 2nd half of the month | C27: 250
A28: Pool Loan Payment(automatic) | B28: 26th of each month | C28: 342.81
A29: Synchrony Bank Payment - Mattress (automatic) | B29: 27th of each month | C29: 69
A30: Netflix | B30: 28th of each month | C30: 19.7

Sheet December 2021
A1: December 2021 Monthly Budget
A2: Income: | B2: 1st half of month | C2: 2nd half of month | F2: what we make 1st half of month | G2: what we owe 1st half of month | H2: money left over
A3: Brian | B3: 3879.35 | C3: 3879.35 | F3: =B3+B4 -> 5354.06 | G3: =C9+C10+C11+C12+C13+C14+C15+C16+C17+C18 -> 3665.25 | H3: =F3-G3 -> 1688.81
A4: Lauren | B4: 1474.71 | C4: 1474.71
F5: what we make 2nd half of month | G5: what we owe 2nd half of month | H5: money left over
F6: =B3+B4 -> 5354.06 | G6: =C21+C22+C23+C24+C25+C26+C27+C28+C29+C30 -> 2149.52 | H6: =F6-G6 -> 3204.54
A7: Expenses: | B7: Due Date: | C7: Expense Cost:
A8: 1st half of month:
A9: Mortgage Payment (automatic) | B9: 1st of each month | C9: 2271.33
A10: youtube tv (automatic) | B10: 1st of each month | C10: 80.23
A11: Swyft Internet(automatic) | B11: 3rd of each month | C11: 98.39 | F11: Average for two week span
A12: Arkansas Protection Services | B12: Paid Quartly | F12: =(H3+H6)/2 -> 2446.675
A13: Mohela Student Interest Loan (automatic) | B13: 6th of each month | C13: 542.02
A14: Travlers Insurance | B14: 7th of each month | C14: 134.42
A15: Spotify USA (automatic) | B15: 9th of each month | C15: 14.22
A16: Disney+(automatic) | B16: 13th of each month | C16: 8.55
A17: Citi card payment | B17: 1st half of the month | C17: 150
A18: Toyota Financial Payment (automatic) | B18: 15th of each month | C18: 366.09
A20: 2nd half of month:
A21: Ram Truck Payment (automatic) | B21: 16th of each month | C21: 710.16
A22: Greenbrier Water, trash payment | B22: 18th of each month | C22: 57
A23: At&t Payment (automatic) | B23: 22nd of each month | C23: 243.86
A24: Lawn Mower | B24: 29th of each month | C24: 120.67
A25: Entergy Payment (automatic) | B25: 27th of each month | C25: 186.32
A26: Citi card payment | B26: 2nd half of the month | C26: 150
A27: Lowes | B27: 2nd half of the month | C27: 250
A28: Pool Loan Payment(automatic) | B28: 26th of each month | C28: 342.81
A29: Synchrony Bank Payment - Mattress (automatic) | B29: 27th of each month | C29: 69
A30: Netflix | B30: 28th of each month | C30: 19.7

Sheet November 2021
A1: November 2021 Monthly Budget
A2: Income: | B2: 1st half of month | C2: 2nd half of month | F2: what we make 1st half of month | G2: what we owe 1st half of month | H2: money left over
A3: Brian | B3: 3879.35 | C3: 3879.35 | F3: =B3+B4 -> 5354.06 | G3: =C9+C10+C11+C12+C13+C14+C15+C16+C17+C18 -> 3665.25 | H3: =F3-G3 -> 1688.81
A4: Lauren | B4: 1474.71 | C4: 1474.71
F5: what we make 2nd half of month | G5: what we owe 2nd half of month | H5: money left over
F6: =B3+B4 -> 5354.06 | G6: =C21+C22+C23+C24+C25+C26+C27+C28+C29+C30 -> 2145.26 | H6: =F6-G6 -> 3208.8
A7: Expenses: | B7: Due Date: | C7: Expense Cost:
A8: 1st half of month:
A9: Mortgage Payment (automatic) | B9: 1st of each month | C9: 2271.33
A10: youtube tv (automatic) | B10: 1st of each month | C10: 80.23
A11: Swyft Internet(automatic) | B11: 3rd of each month | C11: 98.39 | F11: Average for two week span
A12: Arkansas Protection Services | B12: Paid Quartly | F12: =(H3+H6)/2 -> 2448.805
A13: Mohela Student Interest Loan (automatic) | B13: 6th of each month | C13: 542.02
A14: Travlers Insurance | B14: 7th of each month | C14: 134.42
A15: Spotify USA (automatic) | B15: 9th of each month | C15: 14.22
A16: Disney+(automatic) | B16: 13th of each month | C16: 8.55
A17: Citi card payment | B17: 1st half of the month | C17: 150
A18: Toyota Financial Payment (automatic) | B18: 15th of each month | C18: 366.09
A20: 2nd half of month:
A21: Ram Truck Payment (automatic) | B21: 16th of each month | C21: 710.16
A22: Greenbrier Water, trash payment | B22: 18th of each month | C22: 62.63
A23: At&t Payment (automatic) | B23: 22nd of each month | C23: 210.75
A24: Lawn Mower | B24: 29th of each month | C24: 120.67
A25: Entergy Payment (automatic) | B25: 27th of each month | C25: 209.54
A26: Citi card payment | B26: 2nd half of the month | C26: 150
A27: Lowes | B27: 2nd half of the month | C27: 250
A28: Pool Loan Payment(automatic) | B28: 26th of each month | C28: 342.81
A29: Synchrony Bank Payment - Mattress (automatic) | B29: 27th of each month | C29: 69
A30: Netflix | B30: 28th of each month | C30: 19.7
F33: Citi Card payment | G33: 6166.33
F34: Lawn Mower | G34: 4102.55
F35: Lowes | G35: 397
F36: Payment - Mattress (automatic) | G36: 2852
F37: Amex | G37: 0

Sheet October 2021
A1: October 2021 Monthly Budget
A2: Income: | B2: 1st half of month | C2: 2nd half of month | F2: what we make 1st half of month | G2: what we owe 1st half of month | H2: money left over
A3: Brian | B3: 3879.35 | C3: 3879.35 | F3: =B3+B4 -> 5354.06 | G3: =C9+C10+C11+C12+C13+C14+C15+C16+C17+C18 -> 3705.25 | H3: =F3-G3 -> 1648.81
A4: Lauren | B4: 1474.71 | C4: 1474.71
F5: what we make 2nd half of month | G5: what we owe 2nd half of month | H5: money left over
F6: =B3+B4 -> 5354.06 | G6: =C21+C22+C23+C24+C25+C26+C27+C28+C29+C30 -> 2320.27 | H6: =F6-G6 -> 3033.79
A7: Expenses: | B7: Due Date: | C7: Expense Cost:
A8: 1st half of month:
A9: Mortgage Payment (automatic) | B9: 1st of each month | C9: 2271.33
A10: youtube tv (automatic) | B10: 1st of each month | C10: 80.23
A11: Swyft Internet(automatic) | B11: 3rd of each month | C11: 98.39 | F11: Average for two week span
A12: Arkansas Protection Services | B12: Paid Quartly | C12: 40 | F12: =(H3+H6)/2 -> 2341.3
A13: Mohela Student Interest Loan (automatic) | B13: 6th of each month | C13: 542.02
A14: Travlers Insurance | B14: 7th of each month | C14: 134.42
A15: Spotify USA (automatic) | B15: 9th of each month | C15: 14.22
A16: Disney+(automatic) | B16: 13th of each month | C16: 8.55
A17: Citi card payment | B17: 1st half of the month | C17: 150
A18: Toyota Financial Payment (automatic) | B18: 15th of each month | C18: 366.09
A20: 2nd half of month:
A21: Ram Truck Payment (automatic) | B21: 16th of each month | C21: 710.16
A22: Greenbrier Water, trash payment | B22: 18th of each month | C22: 62.63
A23: At&t Payment (automatic) | B23: 22nd of each month | C23: 210.75
A24: Lawn Mower | B24: 29th of each month | C24: 120.67
A25: Entergy Payment (automatic) | B25: 27th of each month | C25: 384.55
A26: Citi card payment | B26: 2nd half of the month | C26: 150
A27: Lowes | B27: 2nd half of the month | C27: 250
A28: Pool Loan Payment(automatic) | B28: 26th of each month | C28: 342.81
A29: Synchrony Bank Payment - Mattress (automatic) | B29: 27th of each month | C29: 69
A30: Netflix | B30: 28th of each month | C30: 19.7
F33: Citi Card payment | G33: 6166.33
F34: Lawn Mower | G34: 4102.55
F35: Lowes | G35: 0
F36: Payment - Mattress (automatic) | G36: 2852
F37: Amex | G37: 0
B39: 13120.88 % 739.67
B40: 17.7 months to save this much up

Sheet September 2021
A1: September 2021 Monthly Budget
A2: Income: | B2: 1st half of month | C2: 2nd half of month | F2: what we make 1st half of month | G2: what we owe 1st half of month | H2: money left over
A3: Brian | B3: 3879.35 | C3: 3879.35 | F3: =B3+B4 -> 5354.06 | G3: =C9+C10+C11+C12+C13+C14+C15+C16+C17+C18 -> 3694.4 | H3: =F3-G3 -> 1659.66
A4: Lauren | B4: 1474.71 | C4: 1474.71
F5: what we make 2nd half of month | G5: what we owe 2nd half of month | H5: money left over
F6: =B3+B4 -> 5354.06 | G6: =C21+C22+C23+C24+C25+C26+C27+C28+C29+C30 -> 2351.28 | H6: =F6-G6 -> 3002.78
A7: Expenses: | B7: Due Date: | C7: Expense Cost:
A8: 1st half of month:
A9: Mortgage Payment (automatic) | B9: 1st of each month | C9: 2271.33
A10: youtube tv (automatic) | B10: 1st of each month | C10: 69.59
A11: Swyft Internet(automatic) | B11: 3rd of each month | C11: 98.74 | F11: Average for two week span
A12: Arkansas Protection Services | B12: Paid Quartly | C12: 40 | F12: =(H3+H6)/2 -> 2331.22
A13: Mohela Student Interest Loan (automatic) | B13: 6th of each month | C13: 542.02
A14: Travlers Insurance | B14: 7th of each month | C14: 134.42
A15: Spotify USA (automatic) | B15: 9th of each month | C15: 14.22
A16: Disney+(automatic) | B16: 13th of each month | C16: 7.99
A17: Citi card payment | B17: 1st half of the month | C17: 150
A18: Toyota Financial Payment (automatic) | B18: 15th of each month | C18: 366.09
A20: 2nd half of month:
A21: Ram Truck Payment (automatic) | B21: 16th of each month | C21: 710.16
A22: Greenbrier Water, trash payment | B22: 18th of each month | C22: 88.93
A23: At&t Payment (automatic) | B23: 22nd of each month | C23: 210.75
A24: Lawn Mower | B24: 29th of each month | C24: 120.67
A25: Entergy Payment (automatic) | B25: 27th of each month | C25: 389.26
A26: Citi card payment | B26: 2nd half of the month | C26: 150
A27: Lowes | B27: 2nd half of the month | C27: 250
A28: Pool Loan Payment(automatic) | B28: 26th of each month | C28: 342.81
A29: Synchrony Bank Payment - Mattress (automatic) | B29: 27th of each month | C29: 69
A30: Netflix | B30: 28th of each month | C30: 19.7

Sheet August 2021
A1: August 2021 Monthly Budget
A2: Income: | B2: 1st half of month | C2: 2nd half of month | F2: what we make 1st half of month | G2: what we owe 1st half of month | H2: money left over
A3: Brian | B3: 3439.14 | C3: 3439.14 | F3: =B3+B4 -> 4913.85 | G3: =C9+C10+C11+C12+C13+C14+C15+C16+C17+C18 -> 3648.68 | H3: =F3-G3 -> 1265.17
A4: Lauren | B4: 1474.71 | C4: 1474.71
F5: what we make 2nd half of month | G5: what we owe 2nd half of month | H5: money left over
F6: =B3+B4 -> 4913.85 | G6: =C21+C22+C23+C24+C25+C26+C27+C28+C29+C30 -> 2337.94 | H6: =F6-G6 -> 2575.91
A7: Expenses: | B7: Due Date: | C7: Expense Cost:
A8: 1st half of month:
A9: Mortgage Payment (automatic) | B9: 1st of each month | C9: 2225.61
A10: youtube tv (automatic) | B10: 1st of each month | C10: 69.59
A11: Swyft Internet(automatic) | B11: 3rd of each month | C11: 98.74 | F11: Average for two week span
A12: Arkansas Protection Services | B12: Paid Quartly | C12: 40 | F12: =(H3+H6)/2 -> 1920.54
A13: Mohela Student Interest Loan (automatic) | B13: 6th of each month | C13: 542.02
A14: Travlers Insurance | B14: 7th of each month | C14: 134.42
A15: Spotify USA (automatic) | B15: 9th of each month | C15: 14.22
A16: Disney+(automatic) | B16: 13th of each month | C16: 7.99
A17: Citi card payment | B17: 1st half of the month | C17: 150
A18: Toyota Financial Payment (automatic) | B18: 15th of each month | C18: 366.09
A20: 2nd half of month:
A21: Ram Truck Payment (automatic) | B21: 16th of each month | C21: 710.16
A22: Greenbrier Water, trash payment | B22: 18th of each month | C22: 88.93
A23: At&t Payment (automatic) | B23: 22nd of each month | C23: 210.75
A24: Lawn Mower | B24: 29th of each month | C24: 120.67
A25: Entergy Payment (automatic) | B25: 27th of each month | C25: 376.45
A26: Citi card payment | B26: 2nd half of the month | C26: 150
A27: Lowes | B27: 2nd half of the month | C27: 250
A28: Pool Loan Payment(automatic) | B28: 26th of each month | C28: 342.81
A29: Synchrony Bank Payment - Mattress (automatic) | B29: 27th of each month | C29: 69
A30: Netflix | B30: 28th of each month | C30: 19.17

Sheet July 2021
A1: July 2021 Monthly Budget
A2: Income: | B2: 1st half of month | C2: 2nd half of month | F2: what we make 1st half of month | G2: what we owe 1st half of month | H2: money left over
A3: Brian | B3: 3439.14 | C3: 3439.14 | F3: =B3+B4 -> 4880.67 | G3: =C9+C10+C11+C12+C13+C14+C15+C16+C17+C18 -> 3670.68 | H3: =F3-G3 -> 1209.99
A4: Lauren | B4: 1441.53 | C4: 1441.53
F5: what we make 2nd half of month | G5: what we owe 2nd half of month | H5: money left over
F6: =B3+B4 -> 4880.67 | G6: =C21+C22+C23+C24+C25+C26+C27+C28+C29+C30 -> 2041 | H6: =F6-G6 -> 2839.67
A7: Expenses: | B7: Due Date: | C7: Expense Cost:
A8: 1st half of month:
A9: Mortgage Payment (automatic) | B9: 1st of each month | C9: 2256.87
A10: youtube tv (automatic) | B10: 1st of each month | C10: 69.59
A11: Swyft Internet(automatic) | B11: 3rd of each month | C11: 98.74 | F11: Average for two week span
A12: Arkansas Protection Services | B12: Paid Quartly | C12: 40 | F12: =(H3+H6)/2 -> 2024.83
A13: Mohela Student Interest Loan (automatic) | B13: 6th of each month | C13: 542.02
A14: Travlers Insurance | B14: 7th of each month | C14: 125.16
A15: Spotify USA (automatic) | B15: 9th of each month | C15: 14.22
A16: Disney+(automatic) | B16: 13th of each month | C16: 7.99
A17: Citi card payment | B17: 1st half of the month | C17: 150
A18: Toyota Financial Payment (automatic) | B18: 15th of each month | C18: 366.09
A20: 2nd half of month:
A21: Tahoe Payment (automatic) | B21: 16th of each month | C21: 483.15
A22: Greenbrier Water, trash payment | B22: 18th of each month | C22: 55
A23: At&t Payment (automatic) | B23: 22nd of each month | C23: 210.75
A24: Lawn Mower | B24: 29th of each month | C24: 120.67
A25: Entergy Payment (automatic) | B25: 27th of each month | C25: 340.45
A26: Citi card payment | B26: 2nd half of the month | C26: 150
A27: Lowes | B27: 2nd half of the month | C27: 250
A28: Pool Loan Payment(automatic) | B28: 26th of each month | C28: 342.81
A29: Synchrony Bank Payment - Mattress (automatic) | B29: 27th of each month | C29: 69
A30: Netflix | B30: 28th of each month | C30: 19.17

Sheet June 2021
A1: June 2021 Monthly Budget
A2: Income: | B2: 1st half of month | C2: 2nd half of month | F2: what we make 1st half of month | G2: what we owe 1st half of month | H2: money left over
A3: Brian | B3: 3439.14 | C3: 3439.14 | F3: =B3+B4 -> 4880.67 | G3: =C9+C10+C11+C12+C13+C14+C15+C16+C17+C18 -> 3618.2 | H3: =F3-G3 -> 1262.47
A4: Lauren | B4: 1441.53 | C4: 1441.53
F5: what we make 2nd half of month | G5: what we owe 2nd half of month | H5: money left over
F6: =B3+B4 -> 4880.67 | G6: =C21+C22+C23+C24+C25+C26+C27+C28+C29 -> 1762.55 | H6: =F6-G6 -> 3118.12
A7: Expenses: | B7: Due Date: | C7: Expense Cost:
A8: 1st half of month:
A9: Mortgage Payment (automatic) | B9: 1st of each month | C9: 2256.87
A10: youtube tv (automatic) | B10: 1st of each month | C10: 69.59
A11: Swyft Internet(automatic) | B11: 3rd of each month | C11: 98.74 | F11: Average for two week span
A12: Arkansas Protection Services | B12: Paid Quartly | C12: 40 | F12: =(H3+H6)/2 -> 2190.295
A13: Mohela Student Interest Loan (automatic) | B13: 6th of each month | C13: 542.02
A14: Travlers Insurance | B14: 7th of each month | C14: 72.68
A15: Spotify USA (automatic) | B15: 9th of each month | C15: 14.22
A16: Disney+(automatic) | B16: 13th of each month | C16: 7.99
A17: Citi card payment | B17: 1st half of the month | C17: 150
A18: Toyota Financial Payment (automatic) | B18: 15th of each month | C18: 366.09
A20: 2nd half of month: | F20: 11373.01
A21: Tahoe Payment (automatic) | B21: 16th of each month | C21: 483.15
A22: Greenbrier Water, trash payment | B22: 18th of each month | C22: 55
A23: At&t Payment (automatic) | B23: 22nd of each month | C23: 210.75
A24: Lawn Mower | B24: 29th of each month | C24: 120.67
A25: Pool Loan Payment(automatic) | B25: 26th of each month | C25: 342.81
A26: Entergy Payment (automatic) | B26: 27th of each month | C26: 131
A27: Citi card payment | B27: 2nd half of the month | C27: 150
A28: Lowes | B28: 2nd half of the month | C28: 250
A29: Netflix | B29: 28th of each month | C29: 19.17
B33: What we owe | C33: Amount we pay a month
A34: Synchrony Bank Payment - Mattress (automatic) | B34: 4025 | C34: 69

Sheet May 2021
A1: May 2021 Monthly Budget
A2: Income: | B2: 1st half of month | C2: 2nd half of month | F2: what we make 1st half of month | G2: what we owe 1st half of month | H2: money left over
A3: Brian | B3: 3439.14 | C3: 3439.14 | F3: =B3+B4 -> 4880.67 | G3: =C9+C10+C11+C12+C13+C14+C15+C16+C17 -> 3101.11 | H3: =F3-G3 -> 1779.56
A4: Lauren | B4: 1441.53 | C4: 1441.53
F5: what we make 2nd half of month | G5: what we owe 2nd half of month | H5: money left over
F6: =B3+B4 -> 4880.67 | G6: =C20+C21+C22+C23+C24+C25+C26 -> 1381.24 | H6: =F6-G6 -> 3499.43
A7: Expenses: | B7: Due Date: | C7: Expense Cost:
A8: 1st half of month:
A9: Mortgage Payment (automatic) | B9: 1st of each month | C9: 2256.87
A10: youtube tv (automatic) | B10: 1st of each month | C10: 69.59
A11: Swyft Internet(automatic) | B11: 3rd of each month | C11: 98.74 | F11: Average for two week span
A12: Arkansas Protection Services | B12: Paid Quartly | C12: 40 | F12: =(H3+H6)/2 -> 2639.495
A13: Mohela Student Interest Loan (automatic) | B13: 6th of each month | C13: 542.02
A14: Travlers Insurance | B14: 7th of each month | C14: 72.68
A15: Spotify USA (automatic) | B15: 9th of each month | C15: 14.22
A17: Disney+(automatic) | B17: 13th of each month | C17: 6.99
A19: 2nd half of month:
A20: Tahoe Payment (automatic) | B20: 16th of each month | C20: 483.15
A21: Greenbrier Water, trash payment | B21: 18th of each month | C21: 73.69
A22: At&t Payment (automatic) | B22: 22nd of each month | C22: 210.75
A23: Lawn Mower | B23: 29th of each month | C23: 120.67
A24: Pool Loan Payment(automatic) | B24: 26th of each month | C24: 342.81
A25: Entergy Payment (automatic) | B25: 27th of each month | C25: 131
A26: Netflix | B26: 28th of each month | C26: 19.17
B30: What we owe | C30: Amount we pay a month
A31: Synchrony Bank Payment - Mattress (automatic) | B31: 4025 | C31: 69

Sheet April 2021
A1: April 2021 Monthly Budget
A2: Income: | B2: 1st half of month | C2: 2nd half of month | F2: what we make 1st half of month | G2: what we owe 1st half of month | H2: money left over
A3: Brian | B3: 3439.14 | C3: 3439.14 | F3: =B3+B4 -> 4880.67 | G3: =C9+C10+C11+C12+C13+C14+C15+C16+C17 -> 3617.06 | H3: =F3-G3 -> 1263.61
A4: Lauren | B4: 1441.53 | C4: 1441.53
F5: what we make 2nd half of month | G5: what we owe 2nd half of month | H5: money left over
F6: =B3+B4 -> 4880.67 | G6: =C20+C21+C22+C23+C24+C25+C26 -> 1367.16 | H6: =F6-G6 -> 3513.51
A7: Expenses: | B7: Due Date: | C7: Expense Cost:
A8: 1st half of month:
A9: Mortgage Payment (automatic) | B9: 1st of each month | C9: 2256.87
A10: youtube tv (automatic) | B10: 1st of each month | C10: 69.59
A11: Swyft Internet(automatic) | B11: 3rd of each month | C11: 98.74 | F11: Average for two week span
A12: Arkansas Protection Services | B12: Paid Quartly | C12: 40 | F12: =(H3+H6)/2 -> 2388.56
A13: Mohela Student Interest Loan (automatic) | B13: 6th of each month | C13: 542.02
A14: Travlers Insurance | B14: 7th of each month | C14: 154.66
A15: Spotify USA (automatic) | B15: 9th of each month | C15: 14.18
A16: BBVA Finance (automatic) | B16: 12th of each month | C16: 434.01
A17: Disney+(automatic) | B17: 13th of each month | C17: 6.99
A19: 2nd half of month:
A20: Tahoe Payment (automatic) | B20: 16th of each month | C20: 483.15
A21: Greenbrier Water, trash payment | B21: 18th of each month | C21: 52
A22: At&t Payment (automatic) | B22: 22nd of each month | C22: 210.75
A23: Lawn Mower | B23: 29th of each month | C23: 120.67
A24: Pool Loan Payment(automatic) | B24: 26th of each month | C24: 342.81
A25: Entergy Payment (automatic) | B25: 27th of each month | C25: 138.61
A26: Netflix | B26: 28th of each month | C26: 19.17
B30: What we owe | C30: Amount we pay a month
A31: Synchrony Bank Payment - Mattress (automatic) | B31: 4025 | C31: 69

Sheet March 2021
A1: March 2021 Monthly Budget
A2: Income: | B2: 1st half of month | C2: 2nd half of month | F2: what we make 1st half of month | G2: what we owe 1st half of month | H2: money left over
A3: Brian | B3: 3337.25 | C3: 3337.25 | F3: =B3+B4 -> 4778.78 | G3: =C9+C10+C11+C12+C13+C14+C15+C16+C17 -> 3617.06 | H3: =F3-G3 -> 1161.72
A4: Lauren | B4: 1441.53 | C4: 1441.53
F5: what we make 2nd half of month | G5: what we owe 2nd half of month | H5: money left over
F6: =B3+B4 -> 4778.78 | G6: =C20+C21+C22+C23+C24+C25+C26 -> 1484.15 | H6: =F6-G6 -> 3294.63
A7: Expenses: | B7: Due Date: | C7: Expense Cost:
A8: 1st half of month:
A9: Mortgage Payment (automatic) | B9: 1st of each month | C9: 2256.87
A10: youtube tv (automatic) | B10: 1st of each month | C10: 69.59
A11: Swyft Internet(automatic) | B11: 3rd of each month | C11: 98.74 | F11: Average for two week span
A12: Arkansas Protection Services | B12: Paid Quartly | C12: 40 | F12: =(H3+H6)/2 -> 2228.175
A13: Mohela Student Interest Loan (automatic) | B13: 6th of each month | C13: 542.02
A14: Travlers Insurance | B14: 7th of each month | C14: 154.66
A15: Spotify USA (automatic) | B15: 9th of each month | C15: 14.18
A16: BBVA Finance (automatic) | B16: 12th of each month | C16: 434.01
A17: Disney+(automatic) | B17: 13th of each month | C17: 6.99
A19: 2nd half of month:
A20: Tahoe Payment (automatic) | B20: 16th of each month | C20: 483.15
A21: Greenbrier Water, trash payment | B21: 18th of each month | C21: 52
A22: At&t Payment (automatic) | B22: 22nd of each month | C22: 210.75
A23: Lawn Mower | B23: 29th of each month | C23: 120.67
A24: Pool Loan Payment(automatic) | B24: 26th of each month | C24: 342.81
A25: Entergy Payment (automatic) | B25: 27th of each month | C25: 255.6
A26: Netflix | B26: 28th of each month | C26: 19.17
B30: What we owe | C30: Amount we pay a month
A31: Synchrony Bank Payment - Mattress (automatic) | B31: 4025 | C31: 69

Sheet February 2021
A1: February 2021 Monthly Budget
A2: Income: | B2: 1st half of month | C2: 2nd half of month | F2: what we make 1st half of month | G2: what we owe 1st half of month | H2: money left over
A3: Brian | B3: 3337.25 | C3: 3337.25 | F3: =B3+B4 -> 4778.78 | G3: =C9+C10+C11+C12+C13+C14+C15+C16+C17 -> 3617.06 | H3: =F3-G3 -> 1161.72
A4: Lauren | B4: 1441.53 | C4: 1441.53
F5: what we make 2nd half of month | G5: what we owe 2nd half of month | H5: money left over
F6: =B3+B4 -> 4778.78 | G6: =C20+C21+C22+C23+C24+C25+C26 -> 1501.18 | H6: =F6-G6 -> 3277.6
A7: Expenses: | B7: Due Date: | C7: Expense Cost:
A8: 1st half of month:
A9: Mortgage Payment (automatic) | B9: 1st of each month | C9: 2256.87
A10: youtube tv (automatic) | B10: 1st of each month | C10: 69.59
A11: Swyft Internet(automatic) | B11: 3rd of each month | C11: 98.74 | F11: Average for two week span
A12: Arkansas Protection Services | B12: Paid Quartly | C12: 40 | F12: =(H3+H6)/2 -> 2219.66
A13: Mohela Student Interest Loan (automatic) | B13: 6th of each month | C13: 542.02
A14: Travlers Insurance | B14: 7th of each month | C14: 154.66
A15: Spotify USA (automatic) | B15: 9th of each month | C15: 14.18
A16: BBVA Finance (automatic) | B16: 12th of each month | C16: 434.01
A17: Disney+(automatic) | B17: 13th of each month | C17: 6.99
A19: 2nd half of month:
A20: Tahoe Payment (automatic) | B20: 16th of each month | C20: 483.15
A21: Greenbrier Water, trash payment | B21: 18th of each month | C21: 52
A22: At&t Payment (automatic) | B22: 22nd of each month | C22: 210.75
A23: Lawn Mower | B23: 29th of each month | C23: 120.67
A24: Pool Loan Payment(automatic) | B24: 26th of each month | C24: 342.81
A25: Entergy Payment (automatic) | B25: 27th of each month | C25: 272.63
A26: Netflix | B26: 28th of each month | C26: 19.17
B30: What we owe | C30: Amount we pay a month
A31: Synchrony Bank Payment - Mattress (automatic) | B31: 4025 | C31: 69

Sheet January 2021
A1: January 2021 Monthly Budget
A2: Income: | B2: 1st half of month | C2: 2nd half of month | F2: what we make 1st half of month | G2: what we owe 1st half of month | H2: money left over
A3: Brian | B3: 3337.25 | C3: 3337.25 | F3: =B3+B4 -> 4778.78 | G3: =C9+C10+C11+C12+C13+C14+C15+C16+C17 -> 3595.84 | H3: =F3-G3 -> 1182.94
A4: Lauren | B4: 1441.53 | C4: 1441.53
F5: what we make 2nd half of month | G5: what we owe 2nd half of month | H5: money left over
F6: =B3+B4 -> 4778.78 | G6: =C20+C21+C22+C23+C24+C25+C26 -> 1398.99 | H6: =F6-G6 -> 3379.79
A7: Expenses: | B7: Due Date: | C7: Expense Cost:
A8: 1st half of month:
A9: Mortgage Payment (automatic) | B9: 1st of each month | C9: 2256.87
A10: direct tv payment (automatic) | B10: 1st of each month | C10: 55
A11: Swyft Internet(automatic) | B11: 3rd of each month | C11: 98.74 | F11: Average for two week span
A12: Arkansas Protection Services | B12: Paid Quartly | C12: 40 | F12: =(H3+H6)/2 -> 2281.365
A13: Mohela Student Interest Loan (automatic) | B13: 6th of each month | C13: 542.02
A14: Travlers Insurance | B14: 7th of each month | C14: 148.03
A15: Spotify USA (automatic) | B15: 9th of each month | C15: 14.18
A16: BBVA Finance (automatic) | B16: 12th of each month | C16: 434.01
A17: Disney+(automatic) | B17: 13th of each month | C17: 6.99
A19: 2nd half of month:
A20: Tahoe Payment (automatic) | B20: 16th of each month | C20: 483.15
A21: Greenbrier Water, trash payment | B21: 18th of each month | C21: 52
A22: At&t Payment (automatic) | B22: 22nd of each month | C22: 210.75
A23: Pool Loan Payment(automatic) | B23: 26th of each month | C23: 342.81
A24: Entergy Payment (automatic) | B24: 27th of each month | C24: 170.44
A25: Netflix | B25: 28th of each month | C25: 19.17
A26: Lawn Mower | B26: 29th of each month | C26: 120.67
B30: What we owe | C30: Amount we pay a month | G30: 5185.11 + 1635.06 = 6,820.17
A31: Synchrony Bank Payment - Mattress (automatic) | B31: 4025 | C31: 69 | G31: ((6674.5 + 2883.06) - 1600 ) - 740 = 7,217.56
G32: after christmas spending payments = 397.39

Sheet December 2020
A1: December 2020 Monthly Budget
A2: Income: | B2: 1st half of month | C2: 2nd half of month | F2: what we make 1st half of month | G2: what we owe 1st half of month | H2: money left over
A3: Brian | B3: 3337.25 | C3: 3337.25 | F3: =B3+B4 -> 4778.78 | G3: =C9+C10+C11+C12+C13+C14+C15+C16+C17 -> 3595.84 | H3: =F3-G3 -> 1182.94
A4: Lauren | B4: 1441.53 | C4: 1441.53
F5: what we make 2nd half of month | G5: what we owe 2nd half of month | H5: money left over
F6: =B3+B4 -> 4778.78 | G6: =C20+C21+C22+C23+C24+C25+C26 -> 1349.83 | H6: =F6-G6 -> 3428.95
A7: Expenses: | B7: Due Date: | C7: Expense Cost:
A8: 1st half of month:
A9: Mortgage Payment (automatic) | B9: 1st of each month | C9: 2256.87
A10: direct tv payment (automatic) | B10: 1st of each month | C10: 55
A11: Swyft Internet(automatic) | B11: 3rd of each month | C11: 98.74 | F11: Average for two week span
A12: Arkansas Protection Services | B12: Paid Quartly | C12: 40 | F12: =(H3+H6)/2 -> 2305.945
A13: Mohela Student Interest Loan (automatic) | B13: 6th of each month | C13: 542.02
A14: Travlers Insurance | B14: 7th of each month | C14: 148.03
A15: Spotify USA (automatic) | B15: 9th of each month | C15: 14.18
A16: BBVA Finance (automatic) | B16: 12th of each month | C16: 434.01
A17: Disney+(automatic) | B17: 13th of each month | C17: 6.99
A19: 2nd half of month:
A20: Tahoe Payment (automatic) | B20: 16th of each month | C20: 483.15
A21: Greenbrier Water, trash payment | B21: 18th of each month | C21: 52
A22: At&t Payment (automatic) | B22: 22nd of each month | C22: 212.75
A23: Pool Loan Payment(automatic) | B23: 26th of each month | C23: 342.81
A24: Entergy Payment (automatic) | B24: 27th of each month | C24: 120.94
A25: Netflix | B25: 28th of each month | C25: 17.51
A26: Lawn Mower | B26: 29th of each month | C26: 120.67
B30: What we owe | C30: Amount we pay a month
A31: Synchrony Bank Payment - Mattress (automatic) | B31: 4025 | C31: 69

Sheet November 2020
A1: November 2020 Monthly Budget
A2: Income: | B2: 1st half of month | C2: 2nd half of month | F2: what we make 1st half of month | G2: what we owe 1st half of month | H2: money left over
A3: Brian | B3: 3337.25 | C3: 3337.25 | F3: =B3+B4 -> 4778.78 | G3: =C9+C10+C11+C12+C13+C14+C15 -> 3442.1 | H3: =F3-G3 -> 1336.68
A4: Lauren | B4: 1441.53 | C4: 1441.53
F5: what we make 2nd half of month | G5: what we owe 2nd half of month | H5: money left over
F6: =B3+B4 -> 4778.78 | G6: =C18+C19+C20+C21+C22+C23+C24+C25+C26 -> 1781.58 | H6: =F6-G6 -> 2997.2
A7: Expenses: | B7: Due Date: | C7: Expense Cost:
A8: 1st half of month:
A9: Mortgage Payment (automatic) | B9: 1st of each month | C9: 2256.87
A10: Arkansas Protection Services | B10: Paid Quartly | C10: 40
A11: Mohela Student Interest Loan (automatic) | B11: 6th of each month | C11: 542.02 | F11: Average for two week span
A12: Travlers Insurance | B12: 7th of each month | C12: 148.03 | F12: =(H3+H6)/2 -> 2166.94
A13: Spotify USA (automatic) | B13: 9th of each month | C13: 14.18
A14: BBVA Finance (automatic) | B14: 12th of each month | C14: 434.01
A15: Disney+(automatic) | B15: 13th of each month | C15: 6.99
A17: 2nd half of month:
A18: Swyft Internet(automatic) | B18: 15th of each month | C18: 98.74
A19: Tahoe Payment (automatic) | B19: 16th of each month | C19: 483.15
A20: Greenbrier Water, trash payment | B20: 18th of each month | C20: 80
A21: At&t Payment (automatic) | B21: 22nd of each month | C21: 212.75
A22: youtube tv (automatic) | B22: 23rd of each month | C22: 69.54 | G22: 6924.36
A23: Pool Loan Payment(automatic) | B23: 26th of each month | C23: 342.81 | G23: 1119.69
A24: Entergy Payment (automatic) | B24: 27th of each month | C24: 356.41 | G24: 5804.67
A25: Netflix | B25: 28th of each month | C25: 17.51
A26: Lawn Mower | B26: 29th of each month | C26: 120.67 | G26: 5804.67
G27: 3442.1
G28: 2362.57
B30: What we owe | C30: Amount we pay a month | G30: 2362.57
A31: Synchrony Bank Payment - Mattress (automatic) | B31: 4025 | C31: 69 | G31: 2930.11
G32: 2883.06
G33: 8175.74
G35: 8175.74
G36: 1716
G37: 6459.74

Sheet October 2020
A1: October 2020 Monthly Budget
A2: Income: | B2: 1st half of month | C2: 2nd half of month | F2: what we make 1st half of month | G2: what we owe 1st half of month | H2: money left over
A3: Brian | B3: 3277.24 | C3: 3277.24 | F3: =B3+B4 -> 4718.77 | G3: =C9+C10+C11+C12+C13+C14+C15+C16 -> 3565.2 | H3: =F3-G3 -> 1153.57
A4: Lauren | B4: 1441.53 | C4: 1441.53
F5: what we make 2nd half of month | G5: what we owe 2nd half of month | H5: money left over
F6: =B3+B4 -> 4718.77 | G6: =C19+C20+C21+C22+C23+C24+C25+C26 -> 1709.82 | H6: =F6-G6 -> 3008.95
A7: Expenses: | B7: Due Date: | C7: Expense Cost:
A8: 1st half of month:
A9: Mortgage Payment (automatic) | B9: 1st of each month | C9: 2256.87
A10: Direct TV (automatic) | B10: 2nd of each month | C10: 123.1
A11: Arkansas Protection Services | B11: Paid Quartly | C11: 40 | F11: Average for two week span
A12: Mohela Student Interest Loan (automatic) | B12: 6th of each month | C12: 542.02 | F12: =(H3+H6)/2 -> 2081.26
A13: Travlers Insurance | B13: 7th of each month | C13: 148.03
A14: Spotify USA (automatic) | B14: 9th of each month | C14: 14.18
A15: BBVA Finance (automatic) | B15: 12th of each month | C15: 434.01
A16: Disney+(automatic) | B16: 13th of each month | C16: 6.99
A18: 2nd half of month:
A19: Swyft Internet(automatic) | B19: 15th of each month | C19: 98.74
A20: Tahoe Payment (automatic) | B20: 16th of each month | C20: 483.15
A21: Greenbrier Water, trash payment | B21: 18th of each month | C21: 80
A22: At&t Payment (automatic) | B22: 22nd of each month | C22: 210.53
A23: Entergy Payment (automatic) | B23: 27th of each month | C23: 356.41
A24: Netflix | B24: 28th of each month | C24: 17.51
A25: Pool Loan Payment(automatic) | B25: 29th of each month | C25: 342.81
A26: Lawn Mower | B26: 29th of each month | C26: 120.67
B30: What we owe | C30: Amount we pay a month
A31: Synchrony Bank Payment - Mattress (automatic) | B31: 4025 | C31: 69

Sheet September 2020
A1: September 2020 Monthly Budget
A2: Income: | B2: 1st half of month | C2: 2nd half of month | F2: what we make 1st half of month | G2: what we owe 1st half of month | H2: money left over
A3: Brian | B3: 3277.24 | C3: 3277.24 | F3: =B3+B4 -> 4718.77 | G3: =C9+C10+C11+C12+C13+C14+C15+C16 -> 3538.22 | H3: =F3-G3 -> 1180.55
A4: Lauren | B4: 1441.53 | C4: 1441.53
F5: what we make 2nd half of month | G5: what we owe 2nd half of month | H5: money left over
F6: =B3+B4 -> 4718.77 | G6: =C19+C20+C21+C22+C23+C24+C25+C26 -> 1633.17 | H6: =F6-G6 -> 3085.6
A7: Expenses: | B7: Due Date: | C7: Expense Cost:
A8: 1st half of month:
A9: Mortgage Payment (automatic) | B9: 1st of each month | C9: 2256.87
A10: Direct TV (automatic) | B10: 2nd of each month | C10: 96.12
A11: Arkansas Protection Services | B11: Paid Quartly | C11: 40 | F11: Average for two week span
A12: Mohela Student Interest Loan (automatic) | B12: 6th of each month | C12: 542.02 | F12: =(H3+H6)/2 -> 2133.075
A13: Travlers Insurance | B13: 7th of each month | C13: 148.03
A14: Spotify USA (automatic) | B14: 9th of each month | C14: 14.18
A15: BBVA Finance (automatic) | B15: 12th of each month | C15: 434.01
A16: Disney+(automatic) | B16: 13th of each month | C16: 6.99
A18: 2nd half of month:
A19: Swyft Internet(automatic) | B19: 15th of each month | C19: 98.74
A20: Tahoe Payment (automatic) | B20: 16th of each month | C20: 483.15
A21: Greenbrier Water, trash payment | B21: 18th of each month | C21: 80
A22: At&t Payment (automatic) | B22: 22nd of each month | C22: 212.75
A23: Entergy Payment (automatic) | B23: 27th of each month | C23: 277.54
A24: Netflix | B24: 28th of each month | C24: 17.51
A25: Pool Loan Payment(automatic) | B25: 29th of each month | C25: 342.81
A26: Lawn Mower | B26: 29th of each month | C26: 120.67
B30: What we owe | C30: Amount we pay a month
A31: Synchrony Bank Payment - Mattress (automatic) | B31: 4025 | C31: 69

Sheet August 2020
A1: August 2020 Monthly Budget
A2: Income: | B2: 1st half of month | C2: 2nd half of month | F2: what we make 1st half of month | G2: what we owe 1st half of month | H2: money left over
A3: Brian | B3: 3277.24 | C3: 3277.24 | F3: =B3+B4 -> 4759.74 | G3: =C9+C10+C11+C12+C13+C14+C15+C16 -> 3538.22 | H3: =F3-G3 -> 1221.52
A4: Lauren | B4: 1482.5 | C4: 1482.5
F5: what we make 2nd half of month | G5: what we owe 2nd half of month | H5: money left over
F6: =B3+B4 -> 4759.74 | G6: =C19+C20+C21+C22+C23+C24+C25 -> 1605.59 | H6: =F6-G6 -> 3154.15
A7: Expenses: | B7: Due Date: | C7: Expense Cost:
A8: 1st half of month:
A9: Mortgage Payment (automatic) | B9: 1st of each month | C9: 2256.87
A10: Direct TV (automatic) | B10: 2nd of each month | C10: 96.12
A11: Arkansas Protection Services | B11: Paid Quartly | C11: 40 | F11: Average for two week span
A12: Mohela Student Interest Loan (automatic) | B12: 6th of each month | C12: 542.02 | F12: =(H3+H6)/2 -> 2187.835
A13: Travlers Insurance | B13: 7th of each month | C13: 148.03
A14: Spotify USA (automatic) | B14: 9th of each month | C14: 14.18
A15: BBVA Finance (automatic) | B15: 12th of each month | C15: 434.01
A16: Disney+(automatic) | B16: 13th of each month | C16: 6.99
A18: 2nd half of month:
A19: Swyft Internet(automatic) | B19: 15th of each month | C19: 98.74
A20: Tahoe Payment (automatic) | B20: 16th of each month | C20: 483.15
A21: Greenbrier Water, trash payment | B21: 18th of each month | C21: 194.24
A22: At&t Payment (automatic) | B22: 22nd of each month | C22: 212.75
A23: Entergy Payment (automatic) | B23: 27th of each month | C23: 256.39
A24: Netflix | B24: 28th of each month | C24: 17.51
A25: Pool Loan Payment(automatic) | B25: 29th of each month | C25: 342.81
B29: What we owe | C29: Amount we pay a month
A30: Synchrony Bank Payment - Mattress (automatic) | B30: 4025 | C30: 69
A34: Pool Loan: Pay 70$ to principle a month(I think) | C34: Savings account: 740 a month | F34: 740 plus 342 how long to catch back up
A35: 43500 | C35: 2821.98 | F35: 631.98
A36: =A35-70 -> 43430 | C36: =C35+740 -> 3561.98 | F36: =F35+740+342 -> 1713.98
A37: =A36-70 -> 43360 | C37: =C36+740 -> 4301.98 | F37: =F36+740+342 -> 2795.98
A38: =A37-70 -> 43290 | C38: =C37+740 -> 5041.98 | F38: =F37+740+342 -> 3877.98
A39: =A38-70 -> 43220 | C39: =C38+740 -> 5781.98 | F39: =F38+740+342 -> 4959.98
A40: =A39-70 -> 43150 | C40: =C39+740 -> 6521.98 | F40: =F39+740+342 -> 6041.98
A41: =A40-70 -> 43080 | C41: =C40+740 -> 7261.98 | F41: =F40+740+342 -> 7123.98
A42: =A41-70 -> 43010 | C42: =C41+740 -> 8001.98 | F42: =F41+740+342 -> 8205.98
A43: =A42-70 -> 42940 | C43: =C42+740 -> 8741.98 | F43: =F42+740+342 -> 9287.98
A44: =A43-70 -> 42870 | C44: =C43+740 -> 9481.98 | F44: =F43+740+342 -> 10369.98
A45: =A44-70 -> 42800 | C45: =C44+740 -> 10221.98 | F45: =F44+740+342 -> 11451.98
A46: =A45-70 -> 42730 | C46: =C45+740 -> 10961.98 | F46: =F45+740+342 -> 12533.98
A47: =A46-70 -> 42660 | C47: =C46+740 -> 11701.98 | F47: =F46+740+342 -> 13615.98
... A71: =A70-70 -> 40980 | C71: =C70+740 -> 29461.98 | F71: =F70+740+342 -> 39583.98
A72: =A71-70 -> 40910 | C72: =C71+740 -> 30201.98 | F72: =F71+740+342 -> 40665.98 | G72: 38 months to catch back up
A73: =A72-70 -> 40840 | C73: =C72+740 -> 30941.98 | F73: =F72+740+342 -> 41747.98
A74: =A73-70 -> 40770 | C74: =C73+740 -> 31681.98 | F74: =F73+740+342 -> 42829.98
A75: =A74-70 -> 40700 | C75: =C74+740 -> 32421.98 | F75: =F74+740+342 -> 43911.98
A76: =A75-70 -> 40630 | C76: =C75+740 -> 33161.98 | F76: =F75+740+342 -> 44993.98
A77: =A76-70 -> 40560 | C77: =C76+740 -> 33901.98 | F77: =F76+740+342 -> 46075.98
A78: =A77-70 -> 40490 | C78: =C77+740 -> 34641.98 | F78: =F77+740+342 -> 47157.98
A79: =A78-70 -> 40420 | C79: =C78+740 -> 35381.98 | F79: =F78+740+342 -> 48239.98
A80: =A79-70 -> 40350 | C80: =C79+740 -> 36121.98 | F80: =F79+740+342 -> 49321.98
A81: =A80-70 -> 40280 | C81: =C80+740 -> 36861.98 | F81: =F80+740+342 -> 50403.98
A82: =A81-70 -> 40210 | C82: =C81+740 -> 37601.98 | F82: =F81+740+342 -> 51485.98
A83: =A82-70 -> 40140 | C83: =C82+740 -> 38341.98 | F83: =F82+740+342 -> 52567.98
A84: =A83-70 -> 40070 | C84: =C83+740 -> 39081.98 | F84: =F83+740+342 -> 53649.98
A85: =A84-70 -> 40000 | C85: =C84+740 -> 39821.98 | F85: =F84+740+342 -> 54731.98
A86: =A85-70 -> 39930 | C86: =C85+740 -> 40561.98 | F86: =F85+740+342 -> 55813.98 | G86: same amount of months what we have now
A87: 52 months till we have more savings than what we owe.

Sheet July 2020
A1: July 2020 Monthly Budget
A2: Income: | B2: 1st half of month | C2: 2nd half of month | F2: what we make 1st half of month | G2: what we owe 1st half of month | H2: money left over
A3: Brian | B3: 3277.24 | C3: 3277.24 | F3: =B3+B4 -> 4574.72 | G3: =C9+C10+C11+C12+C13+C14+C15+C16 -> 3534.94 | H3: =F3-G3 -> 1039.78
A4: Lauren | B4: 1297.48 | C4: 1297.48
F5: what we make 2nd half of month | G5: what we owe 2nd half of month | H5: money left over
F6: =B3+B4 -> 4574.72 | G6: =C19+C20+C21+C22+C23+C24+C25 -> 1613.59 | H6: =F6-G6 -> 2961.13
A7: Expenses: | B7: Due Date: | C7: Expense Cost:
A8: 1st half of month:
A9: Mortgage Payment (automatic) | B9: 1st of each month | C9: 2256.87
A10: Direct TV (automatic) | B10: 2nd of each month | C10: 96.12
A11: Arkansas Protection Services | B11: Paid Quartly | C11: 40 | F11: Average for two week span
A12: Mohela Student Interest Loan (automatic) | B12: 6th of each month | C12: 542.02 | F12: =(H3+H6)/2 -> 2000.455
A13: Travlers Insurance | B13: 7th of each month | C13: 148.03
A14: Spotify USA (automatic) | B14: 9th of each month | C14: 10.9
A15: BBVA Finance (automatic) | B15: 12th of each month | C15: 434.01
A16: Disney+(automatic) | B16: 13th of each month | C16: 6.99
A18: 2nd half of month:
A19: Swyft Internet(automatic) | B19: 15th of each month | C19: 98.74
A20: Tahoe Payment (automatic) | B20: 16th of each month | C20: 483.15
A21: Greenbrier Water, trash payment | B21: 18th of each month | C21: 40
A22: At&t Payment (automatic) | B22: 22nd of each month | C22: 157.84
A23: Entergy Payment (automatic) | B23: 27th of each month | C23: 473.54
A24: Netflix | B24: 28th of each month | C24: 17.51
A25: Pool Loan Payment(automatic) | B25: 25th of each month | C25: 342.81
B29: What we owe | C29: Amount we pay a month
A30: Synchrony Bank Payment - Mattress (automatic) | B30: 4025 | C30: 69

Sheet June 2020
A1: June 2020 Monthly Budget
A2: Income: | B2: 1st half of month | C2: 2nd half of month | F2: what we make 1st half of month | G2: what we owe 1st half of month | H2: money left over
A3: Brian | B3: 3277.24 | C3: 3277.24 | F3: =B3+B4 -> 4574.72 | G3: =C9+C10+C11+C12+C13+C14+C15+C16 -> 3502.85 | H3: =F3-G3 -> 1071.87
A4: Lauren | B4: 1297.48 | C4: 1297.48
F5: what we make 2nd half of month | G5: what we owe 2nd half of month | H5: money left over
F6: =B3+B4 -> 4574.72 | G6: =C19+C20+C21+C22+C23+C24+C25 -> 1385.83 | H6: =F6-G6 -> 3188.89
A7: Expenses: | B7: Due Date: | C7: Expense Cost:
A8: 1st half of month:
A9: Mortgage Payment (automatic) | B9: 1st of each month | C9: 2256.87
A10: Direct TV (automatic) | B10: 2nd of each month | C10: 96.12
A11: Arkansas Protection Services | B11: Paid Quartly | C11: 40 | F11: Average for two week span
A12: Mohela Student Interest Loan (automatic) | B12: 6th of each month | C12: 542.02 | F12: =(H3+H6)/2 -> 2130.38
A13: Travlers Insurance | B13: 7th of each month | C13: 115.94
A14: Spotify USA (automatic) | B14: 9th of each month | C14: 10.9
A15: BBVA Finance (automatic) | B15: 12th of each month | C15: 434.01
A16: Disney+(automatic) | B16: 13th of each month | C16: 6.99
A18: 2nd half of month:
A19: Swyft Internet(automatic) | B19: 15th of each month | C19: 97.47
A20: Tahoe Payment (automatic) | B20: 16th of each month | C20: 483.15
A21: Greenbrier Water, trash payment | B21: 18th of each month
A22: At&t Payment (automatic) | B22: 22nd of each month | C22: 157.84
A23: Pool Loan Payment(automatic) | B23: 25th of each month | C23: 354.43
A24: Entergy Payment (automatic) | B24: 27th of each month | C24: 275.43
A25: Netflix | B25: 28th of each month | C25: 17.51
B29: What we owe | C29: Amount we pay a month
A30: Synchrony Bank Payment - Mattress (automatic) | B30: 4025 | C30: 69
A31: Amex CC(will be 0$ soon) | B31: 6140.59 | C31: 65

Sheet May 2020
A1: May 2020 Monthly Budget
A2: Income: | B2: 1st half of month | C2: 2nd half of month | F2: what we make 1st half of month | G2: what we owe 1st half of month | H2: money left over
A3: Brian | B3: 3277.24 | C3: 3277.24 | F3: =B3+B4 -> 4574.72 | G3: =C9+C10+C11+C12+C13+C14+C15+C16+C17+C18+C19 -> 3802.75 | H3: =F3-G3 -> 771.97
A4: Lauren | B4: 1297.48 | C4: 1297.48
F5: what we make 2nd half of month | G5: what we owe 2nd half of month | H5: money left over
F6: =B3+B4 -> 4574.72 | G6: =C22+C23+C24+C25+C26 -> 992.67 | H6: =F6-G6 -> 3582.05
A7: Expenses: | B7: Due Date: | C7: Expense Cost:
A8: 1st half of month:
A9: Mortgage Payment (automatic) | B9: 1st of each month | C9: 2558.18
A10: Direct TV (automatic) | B10: 2nd of each month | C10: 72.71
A11: Arkansas Protection Services | C11: 40 | F11: Average for two week span
A12: Mohela Student Interest Loan (automatic) | B12: 6th of each month | C12: 542.02 | F12: =(H3+H6)/2 -> 2177.01
A13: Travlers Insurance | B13: 7th of each month | C13: 137.94
A15: Nelnet Loan #1(automatic) | B15: 9th of each month
A16: Spotify USA (automatic) | B16: 9th of each month | C16: 10.9
A17: BBVA Finance (automatic) | B17: 12th of each month | C17: 434.01
A18: Disney+(automatic) | B18: 13th of each month | C18: 6.99
A19: NelNet loan #2(automatic)(Gov't defer till 9/20/20) | B19: 15th of each month
A21: 2nd half of month:
A22: Tahoe Payment (automatic) | B22: 16th of each month | C22: 483.15
A23: Greenbrier Water, trash payment | B23: 18th of each month | C23: 33.4
A24: At&t Payment (automatic) | B24: 22nd of each month | C24: 196.61
A25: Entergy Payment (automatic) | B25: 27th of each month | C25: 262
A26: Netflix | B26: 28th of each month | C26: 17.51
B30: What we owe | C30: Amount we pay a month | F30: Lauren Student Loan | G30: 4629.58
A31: Citi Black Card payment (automatic) | B31: 9721.73 | C31: 183 | F31: Monthly payment | G31: 474.31
A32: US Bank loan payment (automatic) | B32: 12766.06 | C32: 411.14
A33: Synchrony Bank Payment - Mattress (automatic) | B33: 4025 | C33: 69
A34: Amex CC(will be 0$ soon) | B34: 6140.59 | C34: 65
A35: Lowes CC | B35: 0
A36: Sam's Club CC | B36: 0
A37: Amazon CC (4272.00 available) (will be 0$ soon) | B37: 0

Sheet April 2020
A1: April 2020 Monthly Budget
A2: Income: | B2: 1st half of month | C2: 2nd half of month | F2: what we make 1st half of month | G2: what we owe 1st half of month | H2: money left over
A3: Brian | B3: 3277.24 | C3: 3277.24 | F3: =B3+B4 -> 4574.72 | G3: =C9+C10+C11+C12+C13+C14+C15+C16+C17 -> 3342.33 | H3: =F3-G3 -> 1232.39
A4: Lauren | B4: 1297.48 | C4: 1297.48
F5: what we make 2nd half of month | G5: what we owe 2nd half of month | H5: money left over
F6: =B3+B4 -> 4574.72 | G6: =C20+C21+C22+C23+C24 -> 961.52 | H6: =F6-G6 -> 3613.2
A7: Expenses: | B7: Due Date: | C7: Expense Cost:
A8: 1st half of month:
A9: New House Payment #1 (automatic) | B9: 1st of each month | C9: 1568.84
A10: Direct TV (automatic) | B10: 2nd of each month | C10: 72.71
A11: Vivint Payment(automatic) | B11: 3rd of each month | C11: 33.69 | F11: Average for two week span
A12: Mohela Student Interest Loan (automatic) | B12: 6th of each month | C12: 542.02 | F12: =(H3+H6)/2 -> 2422.795
A13: Travlers Insurance | B13: 7th of each month | C13: 148.82
A14: Windstream Internet Payment (automatic) | B14: 7th of each month | C14: 67.93
A15: Nelnet Loan #1(automatic) | B15: 9th of each month | C15: 184.4
A16: BBVA Finance (automatic) | B16: 12th of each month | C16: 434.01
A17: NelNet loan #2(automatic)(Gov't defer till 9/20/20) | B17: 15th of each month | C17: 289.91
A19: 2nd half of month:
A20: Tahoe Payment (automatic) | B20: 16th of each month | C20: 484
A21: Greenbrier Water, trash payment | B21: 18th of each month | C21: 33.4
A22: At&t Payment (automatic) | B22: 22nd of each month | C22: 196.61
A23: Entergy Payment (automatic) | B23: 27th of each month | C23: 230
A24: Netflix | B24: 28th of each month | C24: 17.51
B28: What we owe | C28: Amount we pay a month | F28: 279900
A29: Citi Black Card payment (automatic) | B29: 9871.73 | C29: 183 | F29: 11196 | G29: 4% Realtor Fee
A30: US Bank loan payment (automatic) | B30: 12489.9 | C30: 411.14 | F30: 268704
A31: Synchrony Bank Payment - Mattress (automatic) | B31: 4094 | C31: 69
A32: Amex CC(will be 0$ soon) | B32: 1913.44 | C32: 65 | F32: 266704 | G32: (minus 2,000 for painting house)
A33: Lowes CC (will be 0$ soon) | B33: 590.81 | F33: 29654 | G33: (CC debt)
A34: Sam's Club CC (will be 0$ soon) | B34: 0 | F34: 237,050‬
A35: Amazon CC (4272.00 available) (will be 0$ soon) | B35: 694.27
F36: 237050
F37: 21495 | G37: 5% down payment
F38: 215,555‬
F40: 215555
F41: 205638.6 | G41: (what we owe on the house)
F42: 9,916.4‬ | G42: Potential profit after all things!

Sheet March 2020
A1: March 2020 Monthly Budget
A2: Income: | B2: 1st half of month | C2: 2nd half of month | F2: what we make 1st half of month | G2: what we owe 1st half of month | H2: money left over
A3: Brian | B3: 3277.24 | C3: 3277.24 | F3: =B3+B4 -> 4574.72 | G3: =C9+C10+C11+C12+C13+C14+C15+C16+C17 -> 3323.74 | H3: =F3-G3 -> 1250.98
A4: Lauren | B4: 1297.48 | C4: 1297.48
F5: what we make 2nd half of month | G5: what we owe 2nd half of month | H5: money left over
F6: =B3+B4 -> 4574.72 | G6: =C20+C21+C22+C23+C24 -> 948.75 | H6: =F6-G6 -> 3625.97
A7: Expenses: | B7: Due Date: | C7: Expense Cost:
A8: 1st half of month:
A9: New House Payment #1 (automatic) | B9: 1st of each month | C9: 1568.84
A10: Direct TV (automatic) | B10: 2nd of each month | C10: 72.71
A11: Vivint Payment(automatic) | B11: 3rd of each month | C11: 32.1 | F11: Average for two week span
A12: Mohela Student Interest Loan (automatic) | B12: 6th of each month | C12: 542.02 | F12: =(H3+H6)/2 -> 2438.475
A13: Travlers Insurance | B13: 7th of each month | C13: 148.82
A14: Windstream Internet Payment (automatic) | B14: 7th of each month | C14: 50.93
A15: Nelnet Loan #1(automatic) | B15: 9th of each month | C15: 184.4
A16: BBVA Finance (automatic) | B16: 12th of each month | C16: 434.01
A17: NelNet loan #2(automatic) | B17: 15th of each month | C17: 289.91
A19: 2nd half of month:
A20: Tahoe Payment (automatic) | B20: 16th of each month | C20: 484
A21: Greenbrier Water, trash payment | B21: 18th of each month | C21: 33.4
A22: At&t Payment (automatic) | B22: 22nd of each month | C22: 183.84
A23: Entergy Payment (automatic) | B23: 27th of each month | C23: 230
A24: Netflix | B24: 28th of each month | C24: 17.51
B28: What we owe | C28: Amount we pay a month
A29: Citi Black Card payment (automatic) | B29: 10021.73 | C29: 183
A30: US Bank loan payment (automatic) | B30: 12766.06 | C30: 411.14
A31: Synchrony Bank Payment - Mattress (automatic) | B31: 4163 | C31: 69
A32: Amex CC(will be 0$ soon) | B32: 1652.87 | C32: 65
A33: Lowes CC (will be 0$ soon) | B33: 329
A34: Sam's Club CC (will be 0$ soon) | B34: 0
A35: Amazon CC (4272.00 available) (will be 0$ soon) | B35: 1194.27

Sheet February 2020
A1: February 2020 Monthly Budget
A2: Income: | B2: 1st half of month | C2: 2nd half of month | F2: what we make 1st half of month | G2: what we owe 1st half of month | H2: money left over
A3: Brian | B3: 3277.24 | C3: 3277.24 | F3: =B3+B4 -> 4574.72 | G3: =C9+C10+C11+C12+C13+C14+C15+C16+C17+C18+C19+C20+C21+C22 -> 4631.23 | H3: =F3-G3 -> -56.51
A4: Lauren | B4: 1297.48 | C4: 1297.48
F5: what we make 2nd half of month | G5: what we owe 2nd half of month | H5: money left over
F6: =B3+B4 -> 4574.72 | G6: =C25+C26+C27+C28+C29+C30+C31 -> 793.75 | H6: =F6-G6 -> 3780.97
A7: Expenses: | B7: Due Date: | C7: Expense Cost:
A8: 1st half of month:
A9: New House Payment #1 (automatic) | B9: 1st of each month | C9: 1568.84
A10: Citi Black Card payment (automatic) | B10: 1st of each month | C10: 183
A11: Rep daycare payment (automatic) | B11: Each Week | C11: 130 | F11: Average for two week span
A12: Vivint Payment(automatic) | B12: 3rd of each month | C12: 32.1 | F12: =(H3+H6)/2 -> 1862.23
A13: Tahoe Payment (automatic) | B13: 4th of each month | C13: 470
A14: US Bank loan payment (automatic) | B14: 5th of each month | C14: 411.14
A15: Mohela Student Interest Loan (automatic) | B15: 6th of each month | C15: 542.02
A16: Travlers Insurance | B16: 7th of each month | C16: 180
A17: Windstream Internet Payment (automatic) | B17: 7th of each month | C17: 70
A18: Rep daycare payment (automatic) | B18: Each Week | C18: 130
A19: Nelnet Loan #1(automatic) | B19: 9th of each month | C19: 184.4
A20: Direct TV (automatic) | B20: 11th of each month | C20: 72.71
A21: BBVA Finance (automatic) | B21: 15th of each month | C21: 434.01
A22: NelNet loan #2(automatic) | B22: 15th of each month | C22: 223.01
A24: 2nd half of month:
A25: Greenbrier Water, trash payment | B25: 18th of each month | C25: 33.4
A26: Rep daycare payment (automatic) | B26: Each Week | C26: 130
A27: At&t Payment (automatic) | B27: 22nd of each month | C27: 183.84
A28: Synchrony Bank Payment - Mattress (automatic) | B28: 27th of each month | C28: 69
A29: Rep daycare payment (automatic) | B29: Each Week | C29: 130
A30: Entergy Payment (automatic) | B30: 27th of each month | C30: 230
A31: Netflix | B31: 28th of each month | C31: 17.51

Sheet January 2020
A1: January 2020 Monthly Budget
A2: Income: | B2: 1st half of month | C2: 2nd half of month | F2: what we make 1st half of month | G2: what we owe 1st half of month | H2: money left over
A3: Brian | B3: 3277.24 | C3: 3277.24 | F3: =B3+B4 -> 4574.72 | G3: =C9+C10+C11+C12+C13+C14+C15+C16+C17+C18+C19+C20+C21 -> 4430.83 | H3: =F3-G3 -> 143.89
A4: Lauren | B4: 1297.48 | C4: 1297.48
F5: what we make 2nd half of month | G5: what we owe 2nd half of month | H5: money left over
F6: =B3+B4 -> 4574.72 | G6: =C24+C25+C26+C27+C28+C29+C30+C31 -> 945.58 | H6: =F6-G6 -> 3629.14
A7: Expenses: | B7: Due Date: | C7: Expense Cost:
A8: 1st half of month:
A9: New House Payment #1 (automatic) | B9: 1st of each month | C9: 1568.84
A10: Citi Black Card payment (automatic) | B10: 1st of each month | C10: 183
A11: Rep daycare payment (automatic) | B11: Each Week | C11: 130 | F11: Average for two week span
A12: Vivint Payment(automatic) | B12: 3rd of each month | C12: 32.1 | F12: =(H3+H6)/2 -> 1886.515
A13: Tahoe Payment (automatic) | B13: 4th of each month | C13: 470
A14: US Bank loan payment (automatic) | B14: 5th of each month | C14: 411.14
A15: Mohela Loan (automatic) | B15: 6th of each month | C15: 542.02
A16: Windstream Internet Payment (automatic) | B16: 7th of each month | C16: 49.6
A17: Rep daycare payment (automatic) | B17: Each Week | C17: 130
A18: Nelnet Loan #1(automatic) | B18: 9th of each month | C18: 184.4
A19: Direct TV (automatic) | B19: 11th of each month | C19: 72.71
A20: Nissan Finance (automatic) | B20: 15th of each month | C20: 434.01
A21: NelNet loan #2(automatic) | B21: 15th of each month | C21: 223.01
A23: 2nd half of month:
A24: Greenbrier Water, trash payment | B24: 18th of each month | C24: 33.4
A25: Rep daycare payment (automatic) | B25: Each Week | C25: 130
A26: At&t Payment (automatic) | B26: 22nd of each month | C26: 183.84
A27: Synchrony Bank Payment - Mattress (automatic) | B27: 27th of each month | C27: 69
A28: Rep daycare payment (automatic) | B28: Each Week | C28: 130
A29: Entergy Payment (automatic) | B29: 27th of each month | C29: 235
A30: Netflix | B30: 28th of each month | C30: 17.51
A31: Travlers Insurance | B31: 28th of each month | C31: 146.83

Sheet December 2019
A1: December 2019 Monthly Budget
A2: Income: | B2: 1st half of month | C2: 2nd half of month | F2: what we make 1st half of month | G2: what we owe 1st half of month | H2: money left over
A3: Brian | B3: 3277.24 | C3: 3277.24 | F3: =B3+B4 -> 4574.72 | G3: =C9+C10+C11+C12+C13+C14+C15+C16+C17+C18+C19+C20+C21 -> 5286.98 | H3: =F3-G3 -> -712.26
A4: Lauren | B4: 1297.48 | C4: 1297.48
F5: what we make 2nd half of month | G5: what we owe 2nd half of month | H5: money left over
F6: =B3+B4 -> 4574.72 | G6: =C24+C25+C26+C27+C28+C29+C30+C31+C19 -> 998.94 | H6: =F6-G6 -> 3575.78
A7: Expenses: | B7: Due Date: | C7: Expense Cost:
A8: 1st half of month:
A9: New House Payment #1 (automatic) | B9: 1st of each month | C9: 2868
A10: Citi Black Card payment (automatic) | B10: 1st of each month
A11: Rep daycare payment (automatic) | B11: Each Week | F11: Average for two week span
A12: Vivint Payment(automatic) | B12: 3rd of each month | C12: 32.1 | F12: =(H3+H6)/2 -> 1431.76
A13: Tahoe Payment (automatic) | B13: 4th of each month | C13: 470
A14: US Bank loan payment (automatic) | B14: 5th of each month | C14: 411.14
A15: Mohela Loan (automatic) | B15: 6th of each month | C15: 542.02
A16: Windstream Internet Payment (automatic) | B16: 7th of each month | C16: 49.6
A17: Rep daycare payment (automatic) | B17: Each Week
A18: Nelnet Loan #1(automatic) | B18: 9th of each month | C18: 184.4
A19: Direct TV (automatic) | B19: 11th of each month | C19: 72.71
A20: Nissan Finance (automatic) | B20: 15th of each month | C20: 434
A21: NelNet loan #2(automatic) | B21: 15th of each month | C21: 223.01
A23: 2nd half of month:
A24: Greenbrier Water, trash payment | B24: 18th of each month | C24: 33.4
A25: Rep daycare payment (automatic) | B25: Each Week
A26: At&t Payment (automatic) | B26: 22nd of each month | C26: 195.32
A27: Synchrony Bank Payment - Mattress (automatic) | B27: 27th of each month
A28: Rep daycare payment (automatic) | B28: Each Week
A29: Entergy Payment (automatic) | B29: 27th of each month | C29: 500
A30: Netflix | B30: 28th of each month | C30: 17.51
A31: Allstate Payment (automatic) | B31: 28th of each month | C31: 180
A38: US Bank Credit Card (8,000 available) | B38: 0
A39: Citi Bank Credit Card (8,691.27 available) | B39: 10808.73
A40: Mattress Firm CC (3992.00 available) | B40: 4508
A41: Lowes CC (8859.00 available) | B41: 0
A42: Sam's Club MasterCard (7799.00 available) | B42: 1735.54
A43: Amazon CC (4272.00 available) | B43: 842.58 | C43: (paying off on 11/22/19)
A44: American Express CC(19,509.00 available) | B44: 0
A46: US Bank Personal Loan | B46: 14223.99

Sheet November 2019
A1: November 2019 Monthly Budget
A2: Income: | B2: 1st half of month | C2: 2nd half of month | F2: what we make 1st half of month | G2: what we owe 1st half of month | H2: money left over
A3: Brian | B3: 3277.24 | C3: 3277.24 | F3: =B3+B4 -> 4574.72 | G3: =C9+C10+C11+C12+C13+C14+C15+C16+C17+C18+C19+C20+C21 -> 4397.35 | H3: =F3-G3 -> 177.37
A4: Lauren | B4: 1297.48 | C4: 1297.48
F5: what we make 2nd half of month | G5: what we owe 2nd half of month | H5: money left over
F6: =B3+B4 -> 4574.72 | G6: =C24+C25+C26+C27+C28+C29+C30+C31+C19 -> 1117.15 | H6: =F6-G6 -> 3457.57
A7: Expenses: | B7: Due Date: | C7: Expense Cost:
A8: 1st half of month:
A9: New House Payment #1 (automatic) | B9: 1st of each month | C9: 1568.84
A10: Citi Black Card payment (automatic) | B10: 1st of each month | C10: 183
A11: Rep daycare payment (automatic) | B11: Each Week | C11: 130 | F11: Average for two week span
A12: Vivint Payment(automatic) | B12: 3rd of each month | C12: 32.1 | F12: =(H3+H6)/2 -> 1817.47
A13: Tahoe Payment (automatic) | B13: 4th of each month | C13: 570.92
A14: US Bank loan payment (automatic) | B14: 5th of each month | C14: 411.14
A15: Mohela Loan (automatic) | B15: 6th of each month | C15: 542.02
A16: Windstream Internet Payment (automatic) | B16: 7th of each month | C16: 49.6
A17: Rep daycare payment (automatic) | B17: Each Week | C17: 130
A18: Nelnet Loan #1(automatic) | B18: 9th of each month | C18: 184.4
A19: Direct TV (automatic) | B19: 11th of each month | C19: 72.71
A20: Nissan Finance (automatic) | B20: 15th of each month | C20: 299.61
A21: NelNet loan #2(automatic) | B21: 15th of each month | C21: 223.01
A23: 2nd half of month:
A24: Greenbrier Water, trash payment | B24: 18th of each month | C24: 33.4
A25: Rep daycare payment (automatic) | B25: Each Week | C25: 130
A26: At&t Payment (automatic) | B26: 22nd of each month | C26: 195.32
A27: Synchrony Bank Payment - Mattress (automatic) | B27: 27th of each month | C27: 69
A28: Rep daycare payment (automatic) | B28: Each Week | C28: 130
A29: Entergy Payment (automatic) | B29: 27th of each month | C29: 250
A30: Netflix | B30: 28th of each month | C30: 17.51
A31: Allstate Payment (automatic) | B31: 28th of each month | C31: 219.21
A38: US Bank Credit Card (8,000 available) | B38: 0
A39: Citi Bank Credit Card (8,691.27 available) | B39: 10808.73
A40: Mattress Firm CC (3992.00 available) | B40: 4508
A41: Lowes CC (8859.00 available) | B41: 0
A42: Sam's Club MasterCard (7799.00 available) | B42: 2200.74
A43: Amazon CC (4272.00 available) | B43: 436.85 | C43: (paying off on 11/22/19)
A44: American Express CC(19,509.00 available) | B44: 0
A46: US Bank Personal Loan | B46: 14223.99

Sheet October 2019
A1: October 2019 Monthly Budget
A2: Income: | B2: 1st half of month | C2: 2nd half of month | F2: what we make 1st half of month | G2: what we owe 1st half of month | H2: money left over
A3: Brian | B3: 3277.24 | C3: 3277.24 | F3: =B3+B4 -> 4574.72 | G3: =C9+C10+C11+C12+C13+C14+C15+C16+C17+C18+C31+C19+C20 -> 4366.61 | H3: =F3-G3 -> 208.11
A4: Lauren | B4: 1297.48 | C4: 1297.48
F5: what we make 2nd half of month | G5: what we owe 2nd half of month | H5: money left over
F6: =B3+B4 -> 4574.72 | G6: =C23+C24+C25+C26+C27+C28+C29+C30+C31 -> 1126.94 | H6: =F6-G6 -> 3447.78
A7: Expenses: | B7: Due Date: | C7: Expense Cost:
A8: 1st half of month:
A9: New House Payment #1 (automatic) | B9: 1st of each month | C9: 1568.84
A10: Citi Black Card payment (automatic) | B10: 1st of each month | C10: 183
A11: Rep daycare payment (automatic) | B11: Each Week | C11: 130 | F11: Average for two week span
A12: Vivint Payment(automatic) | B12: 3rd of each month | C12: 32.1 | F12: =(H3+H6)/2 -> 1827.945
A13: Tahoe Payment (automatic) | B13: 4th of each month | C13: 570.92
A14: US Bank loan payment (automatic) | B14: 5th of each month | C14: 411.14
A15: Mohela Loan (automatic) | B15: 6th of each month | C15: 542.02
A16: Windstream Internet Payment (automatic) | B16: 7th of each month | C16: 49.6
A17: Rep daycare payment (automatic) | B17: Each Week | C17: 130
A18: Nelnet Loan #1(automatic) | B18: 9th of each month | C18: 153.66
A19: Nissan Finance (automatic) | B19: 15th of each month | C19: 299.61
A20: NelNet loan #2(automatic) | B20: 15th of each month | C20: 223.01
A22: 2nd half of month:
A23: Greenbrier Water, trash payment | B23: 18th of each month | C23: 33.4
A24: Rep daycare payment (automatic) | B24: Each Week | C24: 130
A25: At&t Payment (automatic) | B25: 22nd of each month | C25: 195.32
A26: Synchrony Bank Payment - Mattress (automatic) | B26: 27th of each month | C26: 69
A27: Rep daycare payment (automatic) | B27: Each Week | C27: 130
A28: Entergy Payment (automatic) | B28: 27th of each month | C28: 258
A29: Netflix | B29: 28th of each month | C29: 17.51
A30: Allstate Payment (automatic) | B30: 28th of each month | C30: 221
A31: Direct TV (automatic) | B31: 11th of each month | C31: 72.71
A38: US Bank Credit Card (8,000 available) | B38: 0
A39: Citi Bank Credit Card (8,691.27 available) | B39: 10808.73
A40: Mattress Firm CC (3992.00 available) | B40: 4508
A41: Lowes CC (8859.00 available) | B41: 0
A42: Sam's Club MasterCard (7799.00 available) | B42: 2200.74
A43: Amazon CC (4272.00 available) | B43: 436.85 | C43: (paying off on 11/22/19)
A44: American Express CC(19,509.00 available) | B44: 0
A46: US Bank Personal Loan | B46: 14223.99

Sheet September 2019
A1: September 2019 Monthly Budget
A2: Income: | B2: 1st half of month | C2: 2nd half of month | F2: what we make 1st half of month | G2: what we owe 1st half of month | H2: money left over
A3: Brian | B3: 3277.24 | C3: 3277.24 | F3: =B3+B4 -> 4574.72 | G3: =C9+C10+C11+C12+C13+C14+C15+C16+C17+C18+C31+C19+C20 -> 4366.61 | H3: =F3-G3 -> 208.11
A4: Lauren | B4: 1297.48 | C4: 1297.48
F5: what we make 2nd half of month | G5: what we owe 2nd half of month | H5: money left over
F6: =B3+B4 -> 4574.72 | G6: =C23+C24+C25+C26+C27+C28+C29+C30+C31 -> 1092.94 | H6: =F6-G6 -> 3481.78
A7: Expenses: | B7: Due Date: | C7: Expense Cost:
A8: 1st half of month:
A9: New House Payment #1 (automatic) | B9: 1st of each month | C9: 1568.84
A10: Citi Black Card payment (automatic) | B10: 1st of each month | C10: 183
A11: Rep daycare payment (automatic) | B11: Each Week | C11: 130 | F11: Average for two week span
A12: Vivint Payment(automatic) | B12: 3rd of each month | C12: 32.1 | F12: =(H3+H6)/2 -> 1844.945
A13: Tahoe Payment (automatic) | B13: 4th of each month | C13: 570.92
A14: US Bank loan payment (automatic) | B14: 5th of each month | C14: 411.14
A15: Mohela Loan (automatic) | B15: 6th of each month | C15: 542.02
A16: Windstream Internet Payment (automatic) | B16: 7th of each month | C16: 49.6
A17: Rep daycare payment (automatic) | B17: Each Week | C17: 130
A18: Nelnet Loan #1(automatic) | B18: 9th of each month | C18: 153.66
A19: Nissan Finance (automatic) | B19: 15th of each month | C19: 299.61
A20: NelNet loan #2(automatic) | B20: 15th of each month | C20: 223.01
A22: 2nd half of month:
A23: Greenbrier Water, trash payment | B23: 18th of each month | C23: 33.4
A24: Rep daycare payment (automatic) | B24: Each Week | C24: 130
A25: At&t Payment (automatic) | B25: 22nd of each month | C25: 195.32
A26: Synchrony Bank Payment - Mattress (automatic) | B26: 27th of each month | C26: 69
A27: Rep daycare payment (automatic) | B27: Each Week | C27: 130
A28: Entergy Payment (automatic) | B28: 27th of each month | C28: 224
A29: Netflix | B29: 28th of each month | C29: 17.51
A30: Allstate Payment (automatic) | B30: 28th of each month | C30: 221
A31: Direct TV (automatic) | B31: 11th of each month | C31: 72.71
A35: Deposit into savings account: $2341.18

Sheet August 2019
A1: August 2019 Monthly Budget
A2: Income: | B2: 1st half of month | C2: 2nd half of month | F2: what we make 1st half of month | G2: what we owe 1st half of month | H2: money left over
A3: Brian | B3: 3277.24 | C3: 3277.24 | F3: =B3+B4 -> 4553.33 | G3: =C9+C10+C11+C12+C13+C14+C15+C16+C17+C18+C31+C19+C20 -> 4376.15 | H3: =F3-G3 -> 177.18
A4: Lauren | B4: 1276.09 | C4: 1276.09
F5: what we make 2nd half of month | G5: what we owe 2nd half of month | H5: money left over
F6: =B3+B4 -> 4553.33 | G6: =C23+C24+C25+C26+C27+C28+C29+C30+C31 -> 1092.94 | H6: =F6-G6 -> 3460.39
A7: Expenses: | B7: Due Date: | C7: Expense Cost:
A8: 1st half of month:
A9: New House Payment #1 (automatic) | B9: 1st of each month | C9: 1578.38
A10: Citi Black Card payment (automatic) | B10: 1st of each month | C10: 183
A11: Rep daycare payment (automatic) | B11: Each Week | C11: 130 | F11: Average for two week span
A12: Vivint Payment(automatic) | B12: 3rd of each month | C12: 32.1 | F12: =(H3+H6)/2 -> 1818.785
A13: Tahoe Payment (automatic) | B13: 4th of each month | C13: 570.92
A14: US Bank loan payment (automatic) | B14: 5th of each month | C14: 411.14
A15: Mohela Loan (automatic) | B15: 6th of each month | C15: 542.02
A16: Windstream Internet Payment (automatic) | B16: 7th of each month | C16: 49.6
A17: Rep daycare payment (automatic) | B17: Each Week | C17: 130
A18: Nelnet Loan #1(automatic) | B18: 9th of each month | C18: 153.66
A19: Nissan Finance (automatic) | B19: 15th of each month | C19: 299.61
A20: NelNet loan #2(automatic) | B20: 15th of each month | C20: 223.01
A22: 2nd half of month:
A23: Greenbrier Water, trash payment | B23: 18th of each month | C23: 33.4
A24: Rep daycare payment (automatic) | B24: Each Week | C24: 130
A25: At&t Payment (automatic) | B25: 22nd of each month | C25: 195.32
A26: Synchrony Bank Payment - Mattress (automatic) | B26: 27th of each month | C26: 69
A27: Rep daycare payment (automatic) | B27: Each Week | C27: 130
A28: Entergy Payment (automatic) | B28: 27th of each month | C28: 224
A29: Netflix | B29: 28th of each month | C29: 17.51
A30: Allstate Payment (automatic) | B30: 28th of each month | C30: 221
A31: Direct TV (automatic) | B31: 31st of each month | C31: 72.71
A35: Deposit into savings account: $2341.18

Sheet July 2019
A1: July 2019 Monthly Budget
A2: Income: | B2: 1st half of month | C2: 2nd half of month | F2: what we make 1st half of month | G2: what we owe 1st half of month | H2: money left over
A3: Brian | B3: 3277.24 | C3: 3277.24 | F3: =B3+B4 -> 4553.33 | G3: =C9+C10+C11+C12+C13+C14+C15+C16+C17+C18+C19+C20+C21 -> 4455.24 | H3: =F3-G3 -> 98.09
A4: Lauren | B4: 1276.09 | C4: 1276.09
F5: what we make 2nd half of month | G5: what we owe 2nd half of month | H5: money left over
F6: =B3+B4 -> 4553.33 | G6: =C24+C25+C26+C27+C28+C29 -> 766.27 | H6: =F6-G6 -> 3787.06
A7: Expenses: | B7: Due Date: | C7: Expense Cost:
A8: 1st half of month:
A9: New House Payment #1 (automatic) | B9: 1st of each month | C9: 1578.38
A10: Lowes Credit Card payment | B10: 3rd of each month | C10: 250
A11: Vivint Payment(automatic) | B11: 3rd of each month | C11: 32.1 | F11: Average for two week span
A12: Tahoe Payment (automatic) | B12: 4th of each month | C12: 570.92 | F12: =(H3+H6)/2 -> 1942.575
A13: US Bank loan payment (automatic) | B13: 5th of each month | C13: 411.14
A14: Blizzard Payment (automatic) | B14: 5th of each month | C14: 14.99
A15: Mohela Loan (automatic) | B15: 6th of each month | C15: 542.02
A16: Windstream Internet Payment (automatic) | B16: 7th of each month | C16: 49.6
A17: Nelnet Loan #1(automatic) | B17: 9th of each month | C17: 153.66
A18: Direct TV (automatic) | B18: 11th of each month | C18: 111.81
A19: American Express (automatic) | B19: 21st of each month | C19: 218
A20: Nissan Finance (automatic) | B20: 15th of each month | C20: 299.61
A21: NelNet loan #2(automatic) | B21: 15th of each month | C21: 223.01
A23: 2nd half of month:
A24: Greenbrier Water, trash payment | B24: 18th of each month | C24: 33.4
A25: At&t Payment (automatic) | B25: 22nd of each month | C25: 195.32
A26: Synchrony Bank Payment - Mattress (automatic) | B26: 27th of each month | C26: 69
A27: Entergy Payment (automatic) | B27: 27th of each month | C27: 224
A28: Netflix | B28: 28th of each month | C28: 17.51
A29: Allstate Payment (automatic) | B29: 28th of each month | C29: 227.04

Sheet June 2019
A1: June 2019 Monthly Budget
A2: Income: | B2: 1st half of month | C2: 2nd half of month | F2: what we make 1st half of month | G2: what we owe 1st half of month | H2: money left over
A3: Brian | B3: 3277.24 | C3: 3277.24 | F3: =B3+B4 -> 4553.33 | G3: =C9+C10+C11+C12+C13+C14+C15+C16+C17+C18+C19+C20+C21 -> 4455.24 | H3: =F3-G3 -> 98.09
A4: Lauren | B4: 1276.09 | C4: 1276.09
F5: what we make 2nd half of month | G5: what we owe 2nd half of month | H5: money left over
F6: =B3+B4 -> 4553.33 | G6: =C24+C25+C26+C27+C28+C29 -> 803.95 | H6: =F6-G6 -> 3749.38
A7: Expenses: | B7: Due Date: | C7: Expense Cost:
A8: 1st half of month:
A9: New House Payment #1 (automatic) | B9: 1st of each month | C9: 1578.38
A10: Lowes Credit Card payment | B10: 3rd of each month | C10: 250
A11: Vivint Payment(automatic) | B11: 3rd of each month | C11: 32.1 | F11: Average for two week span
A12: Tahoe Payment (automatic) | B12: 4th of each month | C12: 570.92 | F12: =(H3+H6)/2 -> 1923.735
A13: US Bank loan payment (automatic) | B13: 5th of each month | C13: 411.14
A14: Blizzard Payment (automatic) | B14: 5th of each month | C14: 14.99
A15: Mohela Loan (automatic) | B15: 6th of each month | C15: 542.02
A16: Windstream Internet Payment (automatic) | B16: 7th of each month | C16: 49.6
A17: Nelnet Loan #1(automatic) | B17: 9th of each month | C17: 153.66
A18: Direct TV (automatic) | B18: 11th of each month | C18: 111.81
A19: American Express (automatic) | B19: 21st of each month | C19: 218
A20: Nissan Finance (automatic) | B20: 15th of each month | C20: 299.61
A21: NelNet loan #2(automatic) | B21: 15th of each month | C21: 223.01
A23: 2nd half of month:
A24: Greenbrier Water, trash payment | B24: 18th of each month | C24: 33.4
A25: Synchrony Bank Payment - Mattress (automatic) | B25: 27th of each month | C25: 69
A26: At&t Payment (automatic) | B26: 22nd of each month | C26: 227
A27: Entergy Payment (automatic) | B27: 27th of each month | C27: 230
A28: Netflix | B28: 28th of each month | C28: 17.51
A29: Allstate Payment (automatic) | B29: 28th of each month | C29: 227.04

Sheet May 2019
A1: May 2019 Monthly Budget
A2: Income: | B2: 1st half of month | C2: 2nd half of month
A3: Brian | B3: 3277.24 | C3: 3277.24
A4: Lauren | B4: 1276.09 | C4: 1276.09
A7: Expenses: | B7: Due Date: | C7: Expense Cost: | F7: what we make 1st half of month | G7: what we owe 1st half of month | H7: money left over
A8: 1st half of month: | F8: =B3+B4 -> 4553.33 | G8: =C9+C10+C11+C12+C13+C14+C15+C16+C17+C18+C19+C20+C21 -> 4237.24 | H8: =F8-G8 -> 316.09
A9: New House Payment #1 (automatic) | B9: 1st of each month | C9: 1578.38
A10: Tahoe Payment (automatic) | B10: 4th of each month | C10: 570.92 | F10: what we make 2nd half of month | G10: what we owe 2nd half of month | H10: money left over
A11: Vivint Payment(automatic) | B11: 3rd of each month | C11: 32.1 | F11: =B3+B4 -> 4553.33 | G11: =C24+C25+C26+C27+C28+C29 -> 791.44 | H11: =F11-G11 -> 3761.89
A12: US Bank loan payment (automatic) | B12: 5th of each month | C12: 411.14
A13: Citi Black Card | B13: 4th of each month | C13: 150
A14: Blizzard Payment (automatic) | B14: 5th of each month | C14: 14.99
A15: Mohela Loan (automatic) | B15: 6th of each month | C15: 542.02
A16: Windstream Internet Payment (automatic) | B16: 7th of each month | C16: 49.6
A17: Rep Daycare payment #1 | B17: 9th of each month | C17: 100
A18: Great Lakes Student Loan(automatic) | B18: 9th of each month | C18: 153.66
A19: Direct TV (automatic) | B19: 11th of each month | C19: 111.81
A20: Nissan Finance (automatic) | B20: 15th of each month | C20: 299.61
A21: NelNet loan(automatic) | B21: 15th of each month | C21: 223.01
A23: 2nd half of month:
A24: Greenbrier Water, trash payment | B24: 18th of each month | C24: 33.4
A25: American Express (automatic) | B25: 21st of each month | C25: 68
A27: At&t Payment (automatic) | B27: 22nd of each month | C27: 227
A28: Entergy Payment (automatic) | B28: 27th of each month | C28: 236
A29: Allstate Payment (automatic) | B29: 28th of each month | C29: 227.04
F35: Average for two week span
F36: =(H8+H11)/2 -> 2038.99
A40: American Express Payoff Schedule: | B40: 5933.76
A41: 43574 | B41: 5239.92
A42: 43604 | B42: 3121.92
A43: 43635 | B43: 1003.92
A44: 43665 | B44: (overage of 1114.08)
A46: US Bank Loan Payoff Schedule: | B46: 11293.76
A47: 43665 | B47: 10179.68
A48: 43696 | B48: 7650.54
A49: 43727 | B49: 5121.4
A50: 43757 | B50: 2592.26
A51: 43788 | B51: 63.12
A52: 43818 | B52: (overage of 2466.02)
A57: Nelnet Student Loan(lauren) | B57: 11395.23
A58: 43831 | B58: 8489.42
A59: 43862 | B59: 5583.61
A60: 43891 | B60: 2677.8
A61: 43922 | B61: (overage of 228.01)
A63: Sofi Mohela Student Loan(Brian) | B63: 58185.21
A64: 43952 | B64: 54737.38
A65: 43983 | B65: 51289.55
A66: 44013 | B66: 47841.72
A67: 44044 | B67: 44393.89
A68: 44075 | B68: 40946.06
A69: 44105 | B69: 37498.23
A70: 44136 | B70: =B69-'January 2019'!G38 -> 37498.23
A71: 44166 | B71: 30602.57
A72: 44197 | B72: 27154.74
A73: 44228 | B73: 23706.91
A74: 44256 | B74: 20259.08
A75: 44287 | B75: 16811.25
A76: 44317 | B76: 13363.42
A77: 44348 | B77: 9915.59
A78: 44378 | B78: 6467.76
A79: 44409 | B79: 3019.93
A80: 44440 | B80: (overage of 427.90)

Sheet April 2019
A1: April 2019 Monthly Budget
A2: Income: | B2: 1st half of month | C2: 2nd half of month
A3: Brian | B3: 3277.24 | C3: 3277.24
A4: Lauren | B4: 1276.09 | C4: 1276.09
A7: Expenses: | B7: Due Date: | C7: Expense Cost: | F7: what we make 1st half of month | G7: what we owe 1st half of month | H7: money left over
A8: 1st half of month: | F8: =B3+B4 -> 4553.33 | G8: =C9+C10+C11+C12+C13+C14+C15+C16+C17+C18+C19+C20 -> 4187.64 | H8: =F8-G8 -> 365.69
A9: New House Payment #1 (automatic) | B9: 1st of each month | C9: 1578.38
A10: Tahoe Payment | B10: 4th of each month | C10: 570.92 | F10: what we make 2nd half of month | G10: what we owe 2nd half of month | H10: money left over
A11: Vivint Payment(automatic) | B11: 3rd of each month | C11: 32.1 | F11: =B3+B4 -> 4553.33 | G11: =C23+C24+C25+C26+C27+C28+C29 -> 887.44 | H11: =F11-G11 -> 3665.89
A12: US Bank loan payment | B12: 5th of each month | C12: 411.14
A13: Citi Black Card | B13: 4th of each month | C13: 150
A14: Blizzard Payment (automatic) | B14: 5th of each month | C14: 14.99
A15: Mohela Loan (automatic) | B15: 6th of each month | C15: 542.02
A16: Rep Daycare payment #1 | B16: 9th of each month | C16: 100
A17: Great Lakes Student Loan(automatic) - Lauren | B17: 9th of each month | C17: 153.66
A18: Direct TV | B18: 11th of each month | C18: 111.81
A19: Nissan Finance | B19: 15th of each month | C19: 299.61
A20: NelNet loan(automatic) - Lauren | B20: 15th of each month | C20: 223.01
A22: 2nd half of month:
A23: Greenbrier Water, trash payment | B23: 18th of each month | C23: 33.4
A25: American Express | B25: 21st of each month | C25: 68
A26: Rep Daycare Payment #2 | B26: 21st of each month | C26: 100
A27: At&t Payment (automatic) | B27: 22nd of each month | C27: 227
A28: Entergy Payment (automatic) | B28: 27th of each month | C28: 232
A29: Allstate Payment (automatic) | B29: 28th of each month | C29: 227.04
A34: Citi Card Payoff Schedule: | B34: 10721.16
A35: 43469 | B35: 6471.16 | F35: Average for two week span
A36: 43515 | B36: 4421.16 | F36: =(H8+H11)/2 -> 2015.79
A37: 43543 | B37: 2371.16
A38: 43574 | B38: 321.16
A40: American Express Payoff Schedule: | B40: 5933.76
A41: 43574 | B41: 5239.92
A42: 43604 | B42: 3121.92
A43: 43635 | B43: 1003.92
A44: 43665 | B44: (overage of 1114.08)
A46: US Bank Loan Payoff Schedule: | B46: 11293.76
A47: 43665 | B47: 10179.68
A48: 43696 | B48: 7650.54
A49: 43727 | B49: 5121.4
A50: 43757 | B50: 2592.26
A51: 43788 | B51: 63.12
A52: 43818 | B52: (overage of 2466.02)
A57: Nelnet Student Loan(lauren) | B57: 11395.23
A58: 43831 | B58: 8489.42
A59: 43862 | B59: 5583.61
A60: 43891 | B60: 2677.8
A61: 43922 | B61: (overage of 228.01)
A63: Sofi Mohela Student Loan(Brian) | B63: 58185.21
A64: 43952 | B64: 54737.38
A65: 43983 | B65: 51289.55
A66: 44013 | B66: 47841.72
A67: 44044 | B67: 44393.89
A68: 44075 | B68: 40946.06
A69: 44105 | B69: 37498.23
A70: 44136 | B70: =B69-'January 2019'!G38 -> 37498.23
A71: 44166 | B71: 30602.57
A72: 44197 | B72: 27154.74
A73: 44228 | B73: 23706.91
A74: 44256 | B74: 20259.08
A75: 44287 | B75: 16811.25
A76: 44317 | B76: 13363.42
A77: 44348 | B77: 9915.59
A78: 44378 | B78: 6467.76
A79: 44409 | B79: 3019.93
A80: 44440 | B80: (overage of 427.90)

Sheet March 2019
A1: March 2019 Monthly Budget
A2: Income: | B2: 1st half of month | C2: 2nd half of month
A3: Brian | B3: 3277.24 | C3: 3277.24
A4: Lauren | B4: 1276.09 | C4: 1276.09 | I4: March 29th = 9304.08
I5: 958.94
I6: 800
A7: Expenses: | B7: Due Date: | C7: Expense Cost: | F7: what we make 1st half of month | G7: what we owe 1st half of month | H7: money left over | I7: 800
A8: 1st half of month: | F8: =B3+B4 -> 4553.33 | G8: =C9+C10+C11+C12+C13+C14+C15+C16+C17+C18+C19+C20+C21 -> 4225.69 | H8: =F8-G8 -> 327.64 | I8: 950
A9: New House Payment #1 (automatic) | B9: 1st of each month | C9: 1578.38 | I9: 950
A10: Anytime Fitness Payment | B10: 1st of each month | C10: 38.05 | F10: what we make 2nd half of month | G10: what we owe 2nd half of month | H10: money left over | I10: 4945.14
A11: Tahoe Payment | B11: 4th of each month | C11: 570.92 | F11: =B3+B4 -> 4553.33 | G11: =C24+C25+C26+C27+C28+C29+C30 -> 958.94 | H11: =F11-G11 -> 3594.39
A12: Vivint Payment(automatic) | B12: 3rd of each month | C12: 32.1
A13: US Bank loan payment | B13: 5th of each month | C13: 411.14
A14: Citi Black Card | B14: 4th of each month | C14: 150
A15: Blizzard Payment (automatic) | B15: 5th of each month | C15: 14.99
A16: Mohela Loan (automatic) | B16: 6th of each month | C16: 542.02
A17: Rep Daycare payment #1 | B17: 9th of each month | C17: 100
A18: Great Lakes Student Loan(automatic) - Lauren | B18: 9th of each month | C18: 153.66
A19: Direct TV | B19: 11th of each month | C19: 111.81
A20: Nissan Finance | B20: 15th of each month | C20: 299.61
A21: NelNet loan(automatic) - Lauren | B21: 15th of each month | C21: 223.01
A23: 2nd half of month:
A24: Greenbrier Water, trash payment | B24: 18th of each month | C24: 33.4
A25: My Media3 internet | B25: 20th of each month | C25: 86.5
A26: American Express | B26: 21st of each month | C26: 68
A27: Rep Daycare Payment #2 | B27: 21st of each month | C27: 100
A28: At&t Payment (automatic) | B28: 22nd of each month | C28: 227
A29: Entergy Payment (automatic) | B29: 27th of each month | C29: 217
A30: Allstate Payment (automatic) | B30: 28th of each month | C30: 227.04
A35: Citi Card Payoff Schedule: | B35: 10721.16 | F35: Average for two week span
A36: 43469 | B36: 6471.16 | F36: =(H8+H11)/2 -> 1961.015
A37: 43515 | B37: 4421.16
A38: 43543 | B38: 2371.16
A39: 43574 | B39: 321.16
A41: American Express Payoff Schedule: | B41: 5933.76
A42: 43574 | B42: 5239.92
A43: 43604 | B43: 3121.92
A44: 43635 | B44: 1003.92
A45: 43665 | B45: (overage of 1114.08)
A47: US Bank Loan Payoff Schedule: | B47: 11293.76
A48: 43665 | B48: 10179.68
A49: 43696 | B49: 7650.54
A50: 43727 | B50: 5121.4
A51: 43757 | B51: 2592.26
A52: 43788 | B52: 63.12
A53: 43818 | B53: (overage of 2466.02)
A58: Nelnet Student Loan(lauren) | B58: 11395.23
A59: 43831 | B59: 8489.42
A60: 43862 | B60: 5583.61
A61: 43891 | B61: 2677.8
A62: 43922 | B62: (overage of 228.01)
A64: Sofi Mohela Student Loan(Brian) | B64: 58185.21
A65: 43952 | B65: 54737.38
A66: 43983 | B66: 51289.55
A67: 44013 | B67: 47841.72
A68: 44044 | B68: 44393.89
A69: 44075 | B69: 40946.06
A70: 44105 | B70: 37498.23
A71: 44136 | B71: =B70-'January 2019'!G38 -> 37498.23
A72: 44166 | B72: 30602.57
A73: 44197 | B73: 27154.74
A74: 44228 | B74: 23706.91
A75: 44256 | B75: 20259.08
A76: 44287 | B76: 16811.25
A77: 44317 | B77: 13363.42
A78: 44348 | B78: 9915.59
A79: 44378 | B79: 6467.76
A80: 44409 | B80: 3019.93
A81: 44440 | B81: (overage of 427.90)

Sheet February 2019
A1: February 2019 Monthly Budget
A2: Income: | B2: 1st half of month | C2: 2nd half of month
A3: Brian | B3: 3277.24 | C3: 3277.24
A4: Lauren | B4: 1276.09 | C4: 1276.09
A7: Expenses: | B7: Due Date: | C7: Expense Cost: | F7: what we make 1st half of month | G7: what we owe 1st half of month | H7: money left over
A8: 1st half of month: | F8: =B3+B4 -> 4553.33 | G8: =C9+C10+C11+C12+C13+C14+C15+C16+C17+C18+C19+C20+C21 -> 4225.69 | H8: =F8-G8 -> 327.64
A9: New House Payment #1 (automatic) | B9: 1st of each month | C9: 1578.38
A10: Anytime Fitness Payment | B10: 1st of each month | C10: 38.05 | F10: what we make 2nd half of month | G10: what we owe 2nd half of month | H10: money left over
A11: Tahoe Payment | B11: 4th of each month | C11: 570.92 | F11: =B3+B4 -> 4553.33 | G11: =C24+C25+C26+C27+C28+C29+C30 -> 949.94 | H11: =F11-G11 -> 3603.39
A12: Vivint Payment(automatic) | B12: 3rd of each month | C12: 32.1
A13: US Bank loan payment | B13: 5th of each month | C13: 411.14
A14: Citi Black Card | B14: 4th of each month | C14: 150
A15: Blizzard Payment (automatic) | B15: 5th of each month | C15: 14.99
A16: Mohela Loan (automatic) | B16: 6th of each month | C16: 542.02
A17: Rep Daycare payment #1 | B17: 9th of each month | C17: 100
A18: Great Lakes Student Loan(automatic) - Lauren | B18: 9th of each month | C18: 153.66
A19: Direct TV | B19: 11th of each month | C19: 111.81
A20: Nissan Finance | B20: 15th of each month | C20: 299.61
A21: NelNet loan(automatic) - Lauren | B21: 15th of each month | C21: 223.01
A23: 2nd half of month:
A24: Greenbrier Water, trash payment | B24: 18th of each month | C24: 33.4
A25: My Media3 internet | B25: 20th of each month | C25: 86.5
A26: American Express | B26: 21st of each month | C26: 68
A27: Rep Daycare Payment #2 | B27: 21st of each month | C27: 100
A28: At&t Payment (automatic) | B28: 22nd of each month | C28: 227
A29: Entergy Payment (automatic) | B29: 27th of each month | C29: 208
A30: Allstate Payment (automatic) | B30: 28th of each month | C30: 227.04
A35: Citi Card Payoff Schedule: | B35: 10721.16 | F35: Average for two week span
A36: 43469 | B36: 6471.16 | F36: =(H8+H11)/2 -> 1965.515
A37: 43515 | B37: 4421.16
A38: 43543 | B38: 2371.16
A39: 43574 | B39: 321.16
A41: American Express Payoff Schedule: | B41: 5933.76
A42: 43574 | B42: 5239.92
A43: 43604 | B43: 3121.92
A44: 43635 | B44: 1003.92
A45: 43665 | B45: (overage of 1114.08)
A47: US Bank Loan Payoff Schedule: | B47: 11293.76
A48: 43665 | B48: 10179.68
A49: 43696 | B49: 7650.54
A50: 43727 | B50: 5121.4
A51: 43757 | B51: 2592.26
A52: 43788 | B52: 63.12
A53: 43818 | B53: (overage of 2466.02)
A58: Nelnet Student Loan(lauren) | B58: 11395.23
A59: 43831 | B59: 8489.42
A60: 43862 | B60: 5583.61
A61: 43891 | B61: 2677.8
A62: 43922 | B62: (overage of 228.01)
A64: Sofi Mohela Student Loan(Brian) | B64: 58185.21
A65: 43952 | B65: 54737.38
A66: 43983 | B66: 51289.55
A67: 44013 | B67: 47841.72
A68: 44044 | B68: 44393.89
A69: 44075 | B69: 40946.06
A70: 44105 | B70: 37498.23
A71: 44136 | B71: =B70-'January 2019'!G38 -> 37498.23
A72: 44166 | B72: 30602.57
A73: 44197 | B73: 27154.74
A74: 44228 | B74: 23706.91
A75: 44256 | B75: 20259.08
A76: 44287 | B76: 16811.25
A77: 44317 | B77: 13363.42
A78: 44348 | B78: 9915.59
A79: 44378 | B79: 6467.76
A80: 44409 | B80: 3019.93
A81: 44440 | B81: (overage of 427.90)

Sheet January 2019
A1: January 2019 Monthly Budget
A2: Income: | B2: 1st half of month | C2: 2nd half of month
A3: Brian | B3: 3277.24 | C3: 3277.24
A4: Lauren | B4: 1276.09 | C4: 1276.09
A7: Expenses: | B7: Due Date: | C7: Expense Cost: | F7: what we make 1st half of month | G7: what we owe 1st half of month | H7: money left over
A8: 1st half of month: | F8: =B3+B4 -> 4553.33 | G8: =C9+C10+C11+C12+C13+C14+C15+C16+C17+C18+C19+C20+C21 -> 4225.69 | H8: =F8-G8 -> 327.64
A9: New House Payment #1 (automatic) | B9: 1st of each month | C9: 1578.38
A10: Anytime Fitness Payment | B10: 1st of each month | C10: 38.05 | F10: what we make 2nd half of month | G10: what we owe 2nd half of month | H10: money left over
A11: Tahoe Payment | B11: 4th of each month | C11: 570.92 | F11: =B3+B4 -> 4553.33 | G11: =C24+C25+C26+C27+C28+C29+C30 -> 957.94 | H11: =F11-G11 -> 3595.39
A12: Vivint Payment(automatic) | B12: 3rd of each month | C12: 32.1
A13: US Bank loan payment | B13: 5th of each month | C13: 411.14
A14: Citi Black Card | B14: 4th of each month | C14: 150
A15: Blizzard Payment (automatic) | B15: 5th of each month | C15: 14.99
A16: Mohela Loan (automatic) | B16: 6th of each month | C16: 542.02
A17: Rep Daycare payment #1 | B17: 9th of each month | C17: 100
A18: Great Lakes Student Loan(automatic) - Lauren | B18: 9th of each month | C18: 153.66
A19: Direct TV | B19: 11th of each month | C19: 111.81
A20: Nissan Finance | B20: 15th of each month | C20: 299.61
A21: NelNet loan(automatic) - Lauren | B21: 15th of each month | C21: 223.01
A23: 2nd half of month:
A24: Greenbrier Water, trash payment | B24: 18th of each month | C24: 33.4
A25: My Media3 internet | B25: 20th of each month | C25: 86.5
A26: American Express | B26: 21st of each month | C26: 68
A27: Rep Daycare Payment #2 | B27: 21st of each month | C27: 100
A28: At&t Payment (automatic) | B28: 22nd of each month | C28: 227
A29: Entergy Payment (automatic) | B29: 27th of each month | C29: 216
A30: Allstate Payment (automatic) | B30: 28th of each month | C30: 227.04
A35: Citi Card Payoff Schedule: | B35: 10721.16 | F35: Average for two week span
A36: 43469 | B36: 6471.16 | F36: =(H8+H11)/2 -> 1961.515
A37: 43515 | B37: 4421.16
A38: 43543 | B38: 2371.16
A39: 43574 | B39: 321.16
A41: American Express Payoff Schedule: | B41: 5933.76
A42: 43574 | B42: 5239.92
A43: 43604 | B43: 3121.92
A44: 43635 | B44: 1003.92
A45: 43665 | B45: (overage of 1114.08)
A47: US Bank Loan Payoff Schedule: | B47: 11293.76
A48: 43665 | B48: 10179.68
A49: 43696 | B49: 7650.54
A50: 43727 | B50: 5121.4
A51: 43757 | B51: 2592.26
A52: 43788 | B52: 63.12
A53: 43818 | B53: (overage of 2466.02)
A58: Nelnet Student Loan(lauren) | B58: 11395.23
A59: 43831 | B59: 8489.42
A60: 43862 | B60: 5583.61
A61: 43891 | B61: 2677.8
A62: 43922 | B62: (overage of 228.01)
A64: Sofi Mohela Student Loan(Brian) | B64: 58185.21
A65: 43952 | B65: 54737.38
A66: 43983 | B66: 51289.55
A67: 44013 | B67: 47841.72
A68: 44044 | B68: 44393.89
A69: 44075 | B69: 40946.06
A70: 44105 | B70: 37498.23
A71: 44136 | B71: =B70-'January 2019'!G38 -> 37498.23
A72: 44166 | B72: 30602.57
A73: 44197 | B73: 27154.74
A74: 44228 | B74: 23706.91
A75: 44256 | B75: 20259.08
A76: 44287 | B76: 16811.25
A77: 44317 | B77: 13363.42
A78: 44348 | B78: 9915.59
A79: 44378 | B79: 6467.76
A80: 44409 | B80: 3019.93
A81: 44440 | B81: (overage of 427.90)

Sheet December 2018
A1: December 2018 Monthly Budget
A2: Income: | B2: 1st half of month | C2: 2nd half of month
A3: Brian | B3: 3268.89 | C3: 3268.89
A4: Lauren | B4: 1306.22 | C4: 1306.22
A7: Expenses: | B7: Due Date: | C7: Expense Cost: | F7: what we make 1st half of month | G7: what we owe 1st half of month | H7: money left over
A8: 1st half of month: | F8: =B3+B4 -> 4575.11 | G8: =C9+C10+C11+C12+C13+C14+C15+C16+C17+C18+C19+C20+C21 -> 4225.69 | H8: =F8-G8 -> 349.42
A9: New House Payment #1 (automatic) | B9: 1st of each month | C9: 1578.38
A10: Anytime Fitness Payment | B10: 1st of each month | C10: 38.05 | F10: what we make 2nd half of month | G10: what we owe 2nd half of month | H10: money left over
A11: Tahoe Payment | B11: 4th of each month | C11: 570.92 | F11: =B3+B4 -> 4575.11 | G11: =C24+C25+C26+C27+C28+C29+C30 -> 958.94 | H11: =F11-G11 -> 3616.17
A12: Vivint Payment(automatic) | B12: 3rd of each month | C12: 32.1
A13: US Bank loan payment | B13: 5th of each month | C13: 411.14
A14: Citi Black Card | B14: 4th of each month | C14: 150
A15: Blizzard Payment (automatic) | B15: 5th of each month | C15: 14.99
A16: Mohela Loan (automatic) | B16: 6th of each month | C16: 542.02
A17: Rep Daycare payment #1 | B17: 9th of each month | C17: 100
A18: Great Lakes Student Loan(automatic) - Lauren | B18: 9th of each month | C18: 153.66
A19: Direct TV | B19: 11th of each month | C19: 111.81
A20: Nissan Finance | B20: 15th of each month | C20: 299.61
A21: NelNet loan(automatic) - Lauren | B21: 15th of each month | C21: 223.01
A23: 2nd half of month:
A24: Greenbrier Water, trash payment | B24: 18th of each month | C24: 33.4
A25: My Media3 internet | B25: 20th of each month | C25: 86.5
A26: American Express | B26: 21st of each month | C26: 68
A27: Rep Daycare Payment #2 | B27: 21st of each month | C27: 100
A28: At&t Payment (automatic) | B28: 22nd of each month | C28: 227
A29: Entergy Payment (automatic) | B29: 27th of each month | C29: 217
A30: Allstate Payment (automatic) | B30: 28th of each month | C30: 227.04
A33: Citi Card Payoff Schedule: | B33: 10721.16 | C33: 10721.17
A34: 43371 | B34: 9621.16 | C34: Paid
A35: 43385 | B35: 8671.16 | C35: Paid | F35: Average for two week span
F36: =(H8+H11)/2 -> 1982.795
A37: 43413 | B37: 7721.16 | C37: Paid
A38: 43441 | B38: 6621.16
A39: 43455 | B39: 5671.16
A40: 43469 | B40: 4571.16
A41: 43483 | B41: 3621.16
A42: 43497 | B42: 2521.16
A43: 43511 | B43: 1571.16
A44: 43525 | B44: 471.16
A46: American Express Payoff Schedule: | B46: 5933.76
A47: 43525 | B47: 5304.92
A48: 43539 | B48: 4136.92
A49: 43553 | B49: 2968.92
A50: 43567 | B50: 1800.92
A51: 43581 | B51: 632.92
A52: 43595 | B52: -535.08
A54: US Bank Loan Payoff Schedule: | B54: 11293.76
A55: 43609 | B55: 10129.68
A56: 43623 | B56: 8550.68
A57: 43637 | B57: 6971.68
A58: 43651 | B58: 5392.68
A59: 43665 | B59: 3813.68
A60: 43679 | B60: 2234.69
A61: 43693 | B61: 655.68
A62: 43707 | B62: -923.32
A64: Paid
A65: Paid In Full
A67: Nelnet Student Loan(lauren) | B67: 11395.23
A68: 43721 | B68: 9538.82
A69: 43735 | B69: 7564.51
A70: 43749 | B70: 5590.2
A71: 43763 | B71: 3615.89
A72: 43777 | B72: 1641.58
A73: 43791 | B73: -332.73
A75: Sofi Mohela Student Loan(Brian) | B75: 58185.21
A76: 43805 | B76: 55668.88
A77: 43819 | B77: 53152.55
A78: 43833 | B78: 50636.22
A79: 43847 | B79: 48119.89
A80: 43861 | B80: 45603.56
A81: 43875 | B81: 43087.23
A82: 43889 | B82: 40570.9
A83: 43903 | B83: 38054.57
A84: 43917 | B84: 35538.24
A85: 43931 | B85: 33021.91
A86: 43945 | B86: 30505.58
A87: 43959 | B87: 27989.25
... A99: 44127 | B99: -2206.71

Sheet November 2018
A1: November 2018 Monthly Budget
A2: Income: | B2: 1st half of month | C2: 2nd half of month
A3: Brian | B3: 3268.89 | C3: 3268.89
A4: Lauren | B4: 1306.22 | C4: 1306.22
A7: Expenses: | B7: Due Date: | C7: Expense Cost: | F7: what we make 1st half of month | G7: what we owe 1st half of month | H7: money left over
A8: 1st half of month: | F8: =B3+B4 -> 4575.11 | G8: =C9+C10+C11+C12+C13+C14+C15+C16+C17+C18+C19+C20+C21 -> 4158.15 | H8: =F8-G8 -> 416.96
A9: New House Payment #1 (automatic) | B9: 1st of each month | C9: 1578.38
A10: Anytime Fitness Payment | B10: 1st of each month | C10: 38.05 | F10: what we make 2nd half of month | G10: what we owe 2nd half of month | H10: money left over
A11: Tahoe Payment | B11: 4th of each month | C11: 570.92 | F11: =B3+B4 -> 4575.11 | G11: =C24+C25+C26+C27+C28+C29+C30 -> 965.94 | H11: =F11-G11 -> 3609.17
A12: Vivint Payment(automatic) | B12: 3rd of each month | C12: 32.1
A13: US Bank loan payment | B13: 5th of each month | C13: 411.14
A14: Citi Black Card | B14: 4th of each month | C14: 150
A15: Blizzard Payment (automatic) | B15: 5th of each month | C15: 14.99
A16: Mohela Loan (automatic) | B16: 6th of each month | C16: 542.02
A17: Rep Daycare payment #1 | B17: 9th of each month | C17: 100
A18: Great Lakes Student Loan(automatic) - Lauren | B18: 9th of each month | C18: 153.66
A19: Direct TV | B19: 11th of each month | C19: 44.27
A20: Nissan Finance | B20: 15th of each month | C20: 299.61
A21: NelNet loan(automatic) - Lauren | B21: 15th of each month | C21: 223.01
A23: 2nd half of month:
A24: Greenbrier Water, trash payment | B24: 18th of each month | C24: 33.4
A25: My Media3 internet | B25: 20th of each month | C25: 86.5
A26: American Express | B26: 21st of each month | C26: 68
A27: Rep Daycare Payment #2 | B27: 21st of each month | C27: 100
A28: At&t Payment (automatic) | B28: 22nd of each month | C28: 227
A29: Entergy Payment (automatic) | B29: 27th of each month | C29: 224
A30: Allstate Payment (automatic) | B30: 28th of each month | C30: 227.04
A33: Citi Card Payoff Schedule: | B33: 10721.16 | C33: 10721.17
A34: 43371 | B34: 9621.16 | C34: Paid
A35: 43385 | B35: 8671.16 | C35: Paid | F35: Average for two week span
F36: =(H8+H11)/2 -> 2013.065
A37: 43413 | B37: 7721.16 | C37: Paid
A38: 43427 | B38: 6771.16
A39: 43441 | B39: 5821.16
A40: 43455 | B40: 4871.16
A41: 43469 | B41: 3921.16
A42: 43483 | B42: 2971.16
A43: 43497 | B43: 2021.16
A44: 43511 | B44: 1071.16
A45: 43525 | B45: 121.16
A47: American Express Payoff Schedule: | B47: 5933.76
A48: 43525 | B48: 5304.92
A49: 43539 | B49: 4136.92
A50: 43553 | B50: 2968.92
A51: 43567 | B51: 1800.92
A52: 43581 | B52: 632.92
A53: 43595 | B53: -535.08
A55: US Bank Loan Payoff Schedule: | B55: 11293.76
A56: 43609 | B56: 10129.68
A57: 43623 | B57: 8550.68
A58: 43637 | B58: 6971.68
A59: 43651 | B59: 5392.68
A60: 43665 | B60: 3813.68
A61: 43679 | B61: 2234.69
A62: 43693 | B62: 655.68
A63: 43707 | B63: -923.32
A65: Paid
A66: Paid In Full
A68: Nelnet Student Loan(lauren) | B68: 11395.23
A69: 43721 | B69: 9538.82
A70: 43735 | B70: 7564.51
A71: 43749 | B71: 5590.2
A72: 43763 | B72: 3615.89
A73: 43777 | B73: 1641.58
A74: 43791 | B74: -332.73
A76: Sofi Mohela Student Loan(Brian) | B76: 58185.21
A77: 43805 | B77: 55668.88
A78: 43819 | B78: 53152.55
A79: 43833 | B79: 50636.22
A80: 43847 | B80: 48119.89
A81: 43861 | B81: 45603.56
A82: 43875 | B82: 43087.23
A83: 43889 | B83: 40570.9
A84: 43903 | B84: 38054.57
A85: 43917 | B85: 35538.24
A86: 43931 | B86: 33021.91
A87: 43945 | B87: 30505.58
A88: 43959 | B88: 27989.25
... A100: 44127 | B100: -2206.71

Sheet October 2018
A1: October 2018 Monthly Budget
A2: Income: | B2: 1st half of month | C2: 2nd half of month
A3: Brian | B3: 3268.87 | C3: 3268.87
A4: Lauren | B4: 1300.72 | C4: 1300.72
A7: Expenses: | B7: Due Date: | C7: Expense Cost: | F7: what we make 1st half of month | G7: what we owe 1st half of month | H7: money left over
A8: 1st half of month: | F8: =B3+B4 -> 4569.59 | G8: =C9+C10+C11+C12+C13+C14+C15+C16+C17+C18+C19+C20 -> 4058.15 | H8: =F8-G8 -> 511.44
A9: New House Payment #1 (automatic) | B9: 1st of each month | C9: 1578.38
A10: Anytime Fitness Payment | B10: 1st of each month | C10: 38.05 | F10: what we make 2nd half of month | G10: what we owe 2nd half of month | H10: money left over
A11: Tahoe Payment | B11: 4th of each month | C11: 570.92 | F11: =B3+B4 -> 4569.59 | G11: =C23+C24+C25+C26+C27+C28 -> 873.94 | H11: =F11-G11 -> 3695.65
A12: Vivint Payment(automatic) | B12: 3rd of each month | C12: 32.1
A13: US Bank loan payment | B13: 5th of each month | C13: 411.14
A14: Citi Black Card | B14: 4th of each month | C14: 150
A15: Blizzard Payment (automatic) | B15: 5th of each month | C15: 14.99
A16: Mohela Loan (automatic) | B16: 6th of each month | C16: 542.02
A17: Great Lakes Student Loan(automatic) - Lauren | B17: 9th of each month | C17: 153.66
A18: Direct TV | B18: 11th of each month | C18: 44.27
A19: Nissan Finance | B19: 15th of each month | C19: 299.61
A20: NelNet loan(automatic) - Lauren | B20: 15th of each month | C20: 223.01
A22: 2nd half of month:
A23: Greenbrier Water, trash payment | B23: 18th of each month | C23: 33.4
A24: My Media3 internet | B24: 20th of each month | C24: 86.5
A25: American Express | B25: 21st of each month | C25: 68
A26: At&t Payment (automatic) | B26: 22nd of each month | C26: 227
A27: Entergy Payment (automatic) | B27: 27th of each month | C27: 232
A28: Allstate Payment (automatic) | B28: 28th of each month | C28: 227.04
A31: Citi Card Payoff Schedule: | B31: 10721.16 | C31: 10721.17
A32: 43371 | B32: 9621.16 | C32: Paid
A33: 43385 | B33: 8671.16 | C33: Paid | F33: Average for two week span
A34: 43399 | B34: 7721.16 | F34: =(H8+H11)/2 -> 2103.545
A35: 43413 | B35: 6771.16
A36: 43427 | B36: 5821.16
A37: 43441 | B37: 4871.16
A38: 43455 | B38: 3921.16
A39: 43469 | B39: 2971.16
A40: 43483 | B40: 2021.16
A41: 43497 | B41: 1071.16
A42: 43511 | B42: 121.16
A43: 43525 | B43: -828.84
A45: American Express Payoff Schedule: | B45: 5933.76
A46: 43525 | B46: 5304.92
A47: 43539 | B47: 4136.92
A48: 43553 | B48: 2968.92
A49: 43567 | B49: 1800.92
A50: 43581 | B50: 632.92
A51: 43595 | B51: -535.08
A53: US Bank Loan Payoff Schedule: | B53: 11293.76
A54: 43609 | B54: 10129.68
A55: 43623 | B55: 8550.68
A56: 43637 | B56: 6971.68
A57: 43651 | B57: 5392.68
A58: 43665 | B58: 3813.68
A59: 43679 | B59: 2234.69
A60: 43693 | B60: 655.68
A61: 43707 | B61: -923.32
A63: Paid
A64: Paid In Full
A66: Nelnet Student Loan(lauren) | B66: 11395.23
A67: 43721 | B67: 9538.82
A68: 43735 | B68: 7564.51
A69: 43749 | B69: 5590.2
A70: 43763 | B70: 3615.89
A71: 43777 | B71: 1641.58
A72: 43791 | B72: -332.73
A74: Sofi Mohela Student Loan(Brian) | B74: 58185.21
A75: 43805 | B75: 55668.88
A76: 43819 | B76: 53152.55
A77: 43833 | B77: 50636.22
A78: 43847 | B78: 48119.89
A79: 43861 | B79: 45603.56
A80: 43875 | B80: 43087.23
A81: 43889 | B81: 40570.9
A82: 43903 | B82: 38054.57
A83: 43917 | B83: 35538.24
A84: 43931 | B84: 33021.91
A85: 43945 | B85: 30505.58
A86: 43959 | B86: 27989.25
... A98: 44127 | B98: -2206.71

Sheet September 2018
A1: September 2018 Monthly Budget
A2: Income: | B2: 1st half of month | C2: 2nd half of month
A3: Brian | B3: 3188.56 | C3: 3188.56
A4: Lauren | B4: 1300.72 | C4: 1300.72
A7: Expenses: | B7: Due Date: | C7: Expense Cost: | F7: what we make 1st half of month | G7: what we owe 1st half of month | H7: money left over
A8: 1st half of month: | F8: =B3+B4 -> 4489.28 | G8: =C9+C10+C11+C12+C13+C14+C15+C16+C17+C18+C19+C20 -> 4056.05 | H8: =F8-G8 -> 433.23
A9: New House Payment #1 (automatic) | B9: 1st of each month | C9: 1578.38
A10: Anytime Fitness Payment | B10: 1st of each month | C10: 38.05 | F10: what we make 2nd half of month | G10: what we owe 2nd half of month | H10: money left over
A11: Tahoe Payment | B11: 4th of each month | C11: 570.92 | F11: =B3+B4 -> 4489.28 | G11: =C23+C24+C25+C26+C27+C28 -> 883.94 | H11: =F11-G11 -> 3605.34
A12: Vivint Payment(automatic) | B12: 3rd of each month | C12: 30
A13: US Bank loan payment | B13: 5th of each month | C13: 411.14
A14: Citi Black Card | B14: 4th of each month | C14: 150
A15: Blizzard Payment (automatic) | B15: 5th of each month | C15: 14.99
A16: Mohela Loan (automatic) | B16: 6th of each month | C16: 542.02
A17: Great Lakes Student Loan(automatic) - Lauren | B17: 9th of each month | C17: 153.66
A18: Direct TV | B18: 11th of each month | C18: 44.27
A19: Nissan Finance | B19: 15th of each month | C19: 299.61
A20: NelNet loan(automatic) - Lauren | B20: 15th of each month | C20: 223.01
A22: 2nd half of month:
A23: Greenbrier Water, trash payment | B23: 18th of each month | C23: 33.4
A24: My Media3 internet | B24: 20th of each month | C24: 86.5
A25: American Express | B25: 21st of each month | C25: 68
A26: At&t Payment (automatic) | B26: 22nd of each month | C26: 227
A27: Entergy Payment (automatic) | B27: 27th of each month | C27: 242
A28: Allstate Payment (automatic) | B28: 28th of each month | C28: 227.04
A31: Citi Card Payoff Schedule: | B31: 10721.16 | C31: 10721.17
A32: 43371 | B32: 9771.16 | C32: Paid
A33: 43385 | B33: 8821.16 | F33: Average for two week span
A34: 43399 | B34: 7871.16 | F34: =(H8+H11)/2 -> 2019.285
A35: 43413 | B35: 6971.16
A36: 43427 | B36: 6021.16
A37: 43441 | B37: 5071.16
A38: 43455 | B38: 4121.16
A39: 43469 | B39: 3171.16
A40: 43483 | B40: 2221.16
A41: 43497 | B41: 1271.16
A42: 43511 | B42: 321.16
A43: 43525 | B43: -628.84
A45: American Express Payoff Schedule: | B45: 5933.76
A46: 43525 | B46: 5304.92
A47: 43539 | B47: 4136.92
A48: 43553 | B48: 2968.92
A49: 43567 | B49: 1800.92
A50: 43581 | B50: 632.92
A51: 43595 | B51: -535.08
A53: US Bank Loan Payoff Schedule: | B53: 11293.76
A54: 43609 | B54: 10129.68
A55: 43623 | B55: 8550.68
A56: 43637 | B56: 6971.68
A57: 43651 | B57: 5392.68
A58: 43665 | B58: 3813.68
A59: 43679 | B59: 2234.69
A60: 43693 | B60: 655.68
A61: 43707 | B61: -923.32
A63: Paid
A64: Paid In Full
A66: Nelnet Student Loan(lauren) | B66: 11513.13
A67: 43721 | B67: 9538.82
A68: 43735 | B68: 7564.51
A69: 43749 | B69: 5590.2
A70: 43763 | B70: 3615.89
A71: 43777 | B71: 1641.58
A72: 43791 | B72: -332.73
A74: Sofi Mohela Student Loan(Brian) | B74: 58185.21
A75: 43805 | B75: 55668.88
A76: 43819 | B76: 53152.55
A77: 43833 | B77: 50636.22
A78: 43847 | B78: 48119.89
A79: 43861 | B79: 45603.56
A80: 43875 | B80: 43087.23
A81: 43889 | B81: 40570.9
A82: 43903 | B82: 38054.57
A83: 43917 | B83: 35538.24
A84: 43931 | B84: 33021.91
A85: 43945 | B85: 30505.58
A86: 43959 | B86: 27989.25
... A98: 44127 | B98: -2206.71

Sheet August 2018
A1: August 2018 Monthly Budget
A2: Income: | B2: 1st half of month | C2: 2nd half of month
A3: Brian | B3: 3188.56 | C3: 3188.56
A4: Lauren | B4: 1300.72 | C4: 1300.72
A7: Expenses: | B7: Due Date: | C7: Expense Cost: | F7: what we make 1st half of month | G7: what we owe 1st half of month | H7: money left over
A8: 1st half of month: | F8: =B3+B4 -> 4489.28 | G8: =C9+C10+C11+C12+C13+C14+C15+C16+C17+C18+C19+C20 -> 4057.95 | H8: =F8-G8 -> 431.33
A9: New House Payment #1 (automatic) | B9: 1st of each month | C9: 1580.28
A10: Anytime Fitness Payment | B10: 1st of each month | C10: 38.05 | F10: what we make 2nd half of month | G10: what we owe 2nd half of month | H10: money left over
A11: Tahoe Payment | B11: 4th of each month | C11: 570.92 | F11: =B3+B4 -> 4489.28 | G11: =C23+C24+C25+C26+C27+C28 -> 891.94 | H11: =F11-G11 -> 3597.34
A12: Vivint Payment(automatic) | B12: 3rd of each month | C12: 30
A13: US Bank loan payment | B13: 5th of each month | C13: 411.14
A14: Citi Black Card | B14: 4th of each month | C14: 150
A15: Blizzard Payment (automatic) | B15: 5th of each month | C15: 14.99
A16: Mohela Loan (automatic) | B16: 6th of each month | C16: 542.02
A17: Great Lakes Student Loan(automatic) - Lauren | B17: 9th of each month | C17: 153.66
A18: Direct TV | B18: 11th of each month | C18: 44.27
A19: Nissan Finance | B19: 15th of each month | C19: 299.61
A20: NelNet loan(automatic) - Lauren | B20: 15th of each month | C20: 223.01
A22: 2nd half of month:
A23: Greenbrier Water, trash payment | B23: 18th of each month | C23: 33.4
A24: My Media3 internet | B24: 20th of each month | C24: 86.5
A25: American Express | B25: 21st of each month | C25: 68
A26: At&t Payment (automatic) | B26: 22nd of each month | C26: 227
A27: Entergy Payment (automatic) | B27: 27th of each month | C27: 250
A28: Allstate Payment (automatic) | B28: 28th of each month | C28: 227.04
F33: Average for two week span
A34: Who We Owe | B34: What We Owe | F34: =(H8+H11)/2 -> 2014.335
A35: Black Card | B35: 12351.43
A36: US Bank Loan | B36: 19298.76
B38: 32050.19
A40: With Family(400.72 & 125,000) = 2984.01 = 574 every 2 weeks
A41: With Family(400.72 & 130,000) = 3098.35 = 685 every 2 weeks
A45: AF, US Bank loan, Black Card, Blizzard, Synchrony, Conway Regional, smaller cars = 1122.10 every 2 weeks

Sheet July 2018
A1: July 2018 Monthly Budget
A2: Income: | B2: 1st half of month | C2: 2nd half of month
A3: Brian | B3: 3190.78 | C3: 3190.78
A4: Lauren | B4: 1264.97 | C4: 1267.97
A7: Expenses: | B7: Due Date: | C7: Expense Cost: | F7: what we make 1st half of month | G7: what we owe 1st half of month | H7: money left over
A8: 1st half of month: | F8: =B3+B4 -> 4455.75 | G8: =C9+C10+C11+C12+C13+C14+C15+C16+C17+C18+C19+C20+C21+C22 -> 4142.54 | H8: =F8-G8 -> 313.21
A9: New House Payment #1 (automatic) | B9: 1st of each month | C9: 1580.28
A10: Anytime Fitness Payment | B10: 1st of each month | C10: 38.05 | F10: what we make 2nd half of month | G10: what we owe 2nd half of month | H10: money left over
A11: Tahoe Payment | B11: 4th of each month | C11: 570.92 | F11: =B3+B4 -> 4455.75 | G11: =C25+C26+C27+C28+C29+C30 -> 901.94 | H11: =F11-G11 -> 3553.81
A12: Vivint Payment(automatic) | B12: 3rd of each month | C12: 30
A13: US Bank loan payment | B13: 5th of each month | C13: 412
A14: Citi Black Card | B14: 4th of each month | C14: 150
A15: Blizzard Payment (automatic) | B15: 5th of each month | C15: 14.99
A16: Mohela Loan (automatic) | B16: 6th of each month | C16: 542.02
A17: Synchrony bank | B17: 7th of each month | C17: 25
A18: Great Lakes Student Loan(automatic) - Lauren | B18: 9th of each month | C18: 153.66
A19: Direct TV | B19: 11th of each month | C19: 35
A20: Conway Regional Bill(automatic) | B20: 13th of each month | C20: 68
A21: Nissan Finance | B21: 15th of each month | C21: 299.61
A22: NelNet loan(automatic) - Lauren | B22: 15th of each month | C22: 223.01
A24: 2nd half of month:
A25: Greenbrier Water, trash payment | B25: 18th of each month | C25: 33.4
A26: My Media3 internet | B26: 20th of each month | C26: 86.5
A27: American Express | B27: 21st of each month | C27: 68
A28: At&t Payment (automatic) | B28: 22nd of each month | C28: 227
A29: Entergy Payment (automatic) | B29: 27th of each month | C29: 260
A30: Allstate Payment (automatic) | B30: 28th of each month | C30: 227.04
F33: Average for two week span
F34: =(H8+H11)/2 -> 1933.51
A36: Who We Owe | B36: What We Owe
A37: Black Card | B37: 12351.43
A38: US Bank Loan | B38: 19298.76
B39: 31650.19
A41: With Family(400.72 & 125,000) = 2984.01 = 574 every 2 weeks
A42: With Family(400.72 & 130,000) = 3098.35 = 685 every 2 weeks
A46: AF, US Bank loan, Black Card, Blizzard, Synchrony, Conway Regional, smaller cars = 1122.10 every 2 weeks

Sheet June 2018
A1: June 2018 Monthly Budget
A2: Income: | B2: 1st half of month | C2: 2nd half of month
A3: Brian | B3: 3153.51 | C3: 3153.51
A4: Lauren | B4: 1264.97 | C4: 1267.97
J5: 2957.69 with me and the boys
J6: 2806.51 with family
A7: Expenses: | B7: Due Date: | C7: Expense Cost: | F7: what we make 1st half of month | G7: what we owe 1st half of month | H7: money left over
A8: 1st half of month: | F8: =B3+B4 -> 4418.48 | G8: =C9+C10+C11+C12+C13+C14+C15+C16+C17+C18+C19+C20+C21 -> 4112.54 | H8: =F8-G8 -> 305.94
A9: New House Payment #1 (automatic) | B9: 1st of each month | C9: 1580.28 | J9: 3153.51 | K9: 391.64 with raise at ABC a month
A10: Anytime Fitness Payment | B10: 1st of each month | C10: 38.05 | F10: what we make 2nd half of month | G10: what we owe 2nd half of month | H10: money left over
A11: Tahoe Payment | B11: 4th of each month | C11: 570.92
A12: US Bank loan payment | B12: 5th of each month | C12: 412 | F12: =B3+B4 -> 4418.48 | G12: =C24+C25+C26+C27+C28 -> 797.52 | H12: =F12-G12 -> 3620.96
A13: Citi Black Card | B13: 4th of each month | C13: 150
A14: Blizzard Payment (automatic) | B14: 5th of each month | C14: 14.99
A15: Mohela Loan (automatic) | B15: 6th of each month | C15: 542.02
A16: Synchrony bank | B16: 7th of each month | C16: 25
A17: Great Lakes Student Loan(automatic) - Lauren | B17: 9th of each month | C17: 153.66
A18: Direct TV | B18: 11th of each month | C18: 35
A19: Conway Regional Bill(automatic) | B19: 13th of each month | C19: 68
A20: Nissan Finance | B20: 15th of each month | C20: 299.61
A21: NelNet loan(automatic) - Lauren | B21: 15th of each month | C21: 223.01 | J21: 80973.6 a year
J22: 3373.9 is what I make at 2 checks a month with 120,000
A23: 2nd half of month:
A24: Greenbrier Water, trash payment | B24: 18th of each month | C24: 33.4 | J24: 76899.94 a year
A25: My Media3 internet | B25: 20th of each month | C25: 86.5 | J25: 3204.16 is what I make at ABC with two checks a month like FO
A26: At&t Payment (automatic) | B26: 22nd of each month | C26: 227
A27: Entergy Payment (automatic) | B27: 27th of each month | C27: 269 | J27: 87034.32 a year
A28: Allstate Payment (automatic) | B28: 28th of each month | C28: 181.62 | J28: 3626.43 is what I make at 2 checks with 130,000
J30: 844.51 more a month at 130,000
J32: 339.48 more a month at 120,000
F33: Average for two week span
A34: Who We Owe | B34: What We Owe | C34: What we pay a month | F34: =(H8+H12)/2 -> 1963.45
A35: Black Card | B35: 12351.43 | C35: 184
A36: US Bank Loan | B36: 19298.76 | C36: 411.14
A37: Amex Card | B37: 0
D39: When comes due
D40: May 14th 2019
D42: 43647

Sheet May 2018
A1: May 2018 Monthly Budget
A2: Income: | B2: 1st half of month | C2: 2nd half of month
A3: Brian | B3: 2957.69 | C3: 2957.69
A4: Lauren | B4: 1264.97 | C4: 1267.97
A7: Expenses: | B7: Due Date: | C7: Expense Cost: | F7: what we make 1st half of month | G7: what we owe 1st half of month | H7: money left over
A8: 1st half of month: | F8: =B3+B4 -> 4222.66 | G8: =C9+C10+C11+C12+C13+C14+C15+C16+C17+C18+C19+C20+C21+C22 -> 3830.43 | H8: =F8-G8 -> 392.23
A9: Rep Daycare #1 (automatic) | B9: each Monday | C9: 45
A10: New House Payment #1 (automatic) | B10: 1st of each month | C10: 1580.28 | F10: what we make 2nd half of month | G10: what we owe 2nd half of month | H10: money left over
A11: Anytime Fitness Payment | B11: 1st of each month | C11: 38.05
A12: Vivint Payment(automatic) | B12: 3rd of each month | C12: 74.89 | F12: =B3+B4 -> 4222.66 | G12: =C25+C26+C27+C28+C29+C30+C31+C32 -> 941.37 | H12: =F12-G12 -> 3281.29
A13: Tahoe Payment | B13: 30th of each month | C13: 570.92
A14: Citi Black Card | B14: 4th of each month | C14: 150
A15: Blizzard Payment (automatic) | B15: 5th of each month | C15: 14.99
A16: Mohela Loan (automatic) | B16: 6th of each month | C16: 542.02
A17: Synchrony bank | B17: 7th of each month | C17: 25
A18: Rep Daycare #2 (automatic) | B18: each Monday | C18: 45
A19: Great Lakes Student Loan(automatic) - Lauren | B19: 9th of each month | C19: 153.66
A20: Conway Regional Bill(automatic) | B20: 13th of each month | C20: 68
A21: Nissan Finance | B21: 15th of each month | C21: 299.61
A22: NelNet loan(automatic) - Lauren | B22: 15th of each month | C22: 223.01
A24: 2nd half of month:
A25: Rep Daycare #3 (automatic) | B25: each Monday | C25: 45
A26: Greenbrier Water, trash payment | B26: 18th of each month | C26: 33.4
A27: My Media3 internet | B27: 20th of each month | C27: 86.5
A28: At&t Payment (automatic) | B28: 22nd of each month | C28: 227
A29: Entergy Payment (automatic) | B29: 27th of each month | C29: 278
A30: Allstate Payment (automatic) | B30: 28th of each month | C30: 181.62
A31: Direct TV Payment (automatic) | B31: 30th of each month | C31: 44.85
A32: Rep Daycare #4 (automatic) | B32: each Monday | C32: 45
F33: Average for two week span
F34: =(H8+H12)/2 -> 1836.76
A38: Loan Payoff Schedule
A39: Lauren | B39: Great Lakes -128.05
B40: Current Balance - 6310.75
B41: Balance as of November 2017 - 5680.75~
B42: Amount to pay each month - 838.40 + 128.05 = 966.45
B43: Months to pay off - ~6 months or November 2017 to April 2018
B45: Nelnet - 171.55 a month
B46: Current Balance - 9797.33
B47: Balance as of April 2018 - 8357.33
B48: Amount to pay each month - 966.45 + 171.55 = 1138.00
B49: Months to pay off - ~8 months April 2018 to December 2018
A53: Credit Card Debt
B54: Lowes - 110.00
B55: Current Balance - 3606.16
B56: Balance as of August 2017 - 3200.00
B57: Amount to pay each month - 800.00 + 110.00 = 910.00
B58: Month to pay off - ~3.5 months August 2017 to October 2017
B60: US Bank - 60.00
B61: Current Balance - 3003.17
B62: Balance as of October 2017 - 2703.17
B63: Amount to pay each month - 910.00 + 60 = 970.00
B64: Month to pay off - ~3 months November 2017 to Januaray 2018
B66: Amazon - 48.00
B67: Current Balance - 1967.36
... B70: Month to pay off - ~2 months Feb 2018 to March 2018

Sheet April 2018
A1: April 2018 Monthly Budget
A2: Income: | B2: 1st half of month | C2: 2nd half of month
A3: Brian | B3: 2957.69 | C3: 2957.69
A4: Lauren | B4: 1264.97 | C4: 1267.97
A7: Expenses: | B7: Due Date: | C7: Expense Cost: | F7: what we make 1st half of month | G7: what we owe 1st half of month | H7: money left over
A8: 1st half of month: | F8: =B3+B4 -> 4222.66 | G8: =C9+C10+C11+C12+C13+C14+C15+C16+C17+C18+C19+C20+C21+C22+C23 -> 3877.52 | H8: =F8-G8 -> 345.14
A9: Rep Daycare #1 (automatic) | B9: each Monday | C9: 50
A10: New House Payment #1 (automatic) | B10: 1st of each month | C10: 1580.28 | F10: what we make 2nd half of month | G10: what we owe 2nd half of month | H10: money left over
A11: Anytime Fitness Payment | B11: 1st of each month | C11: 38.05
A12: Vivint Payment(automatic) | B12: 3rd of each month | C12: 74.9 | F12: =B3+B4 -> 4222.66 | G12: =C26+C27+C28+C29+C30+C31+C32 -> 906.52 | H12: =F12-G12 -> 3316.14
A13: Tahoe Payment | B13: 30th of each month | C13: 573
A14: Citi Black Card | B14: 4th of each month | C14: 150
A15: Blizzard Payment (automatic) | B15: 5th of each month | C15: 14.99
A16: Mohela Loan (automatic) | B16: 6th of each month | C16: 542.02
A17: Synchrony bank | B17: 7th of each month | C17: 25
A18: Rep Daycare #2 (automatic) | B18: each Monday | C18: 50
A19: Great Lakes Student Loan(automatic) - Lauren | B19: 9th of each month | C19: 153.66
A20: Direct TV | B20: 11th of each month | C20: 35
A21: Conway Regional Bill(automatic) | B21: 13th of each month | C21: 68
A22: Nissan Finance | B22: 15th of each month | C22: 299.61
A23: NelNet loan(automatic) - Lauren | B23: 15th of each month | C23: 223.01
A25: 2nd half of month:
A26: Rep Daycare #3 (automatic) | B26: each Monday | C26: 50
A27: Greenbrier Water, trash payment | B27: 18th of each month | C27: 33.4
A28: My Media3 internet | B28: 20th of each month | C28: 86.5
A29: At&t Payment (automatic) | B29: 22nd of each month | C29: 227
A30: Entergy Payment (automatic) | B30: 27th of each month | C30: 278
A31: Allstate Payment (automatic) | B31: 28th of each month | C31: 181.62
A32: Rep Daycare #4 (automatic) | B32: each Monday | C32: 50 | F32: Average for two week span
F33: =(H8+H12)/2 -> 1830.64
F35: 819.6
A38: Loan Payoff Schedule
A39: Lauren | B39: Great Lakes -128.05
B40: Current Balance - 6310.75
B41: Balance as of November 2017 - 5680.75~
B42: Amount to pay each month - 838.40 + 128.05 = 966.45
B43: Months to pay off - ~6 months or November 2017 to April 2018
B45: Nelnet - 171.55 a month
B46: Current Balance - 9797.33
B47: Balance as of April 2018 - 8357.33
B48: Amount to pay each month - 966.45 + 171.55 = 1138.00
B49: Months to pay off - ~8 months April 2018 to December 2018
A53: Credit Card Debt
B54: Lowes - 110.00
B55: Current Balance - 3606.16
B56: Balance as of August 2017 - 3200.00
B57: Amount to pay each month - 800.00 + 110.00 = 910.00
B58: Month to pay off - ~3.5 months August 2017 to October 2017
B60: US Bank - 60.00
B61: Current Balance - 3003.17
B62: Balance as of October 2017 - 2703.17
B63: Amount to pay each month - 910.00 + 60 = 970.00
B64: Month to pay off - ~3 months November 2017 to Januaray 2018
B66: Amazon - 48.00
B67: Current Balance - 1967.36
... B70: Month to pay off - ~2 months Feb 2018 to March 2018

Sheet March 2018
A1: March 2018 Monthly Budget
A2: Income: | B2: 1st half of month | C2: 2nd half of month
A3: Brian | B3: 2957.69 | C3: 2957.69
A4: Lauren | B4: 1264.97 | C4: 1267.97
A7: Expenses: | B7: Due Date: | C7: Expense Cost: | F7: what we make 1st half of month | G7: what we owe 1st half of month | H7: money left over
A8: 1st half of month: | F8: =B3+B4 -> 4222.66 | G8: =C9+C10+C11+C12+C13+C14+C15+C16+C17+C18+C20+C19+C21+C22 -> 3304.52 | H8: =F8-G8 -> 918.14
A9: Rep Daycare #1 (automatic) | B9: each Monday | C9: 50
A10: New House Payment #1 (automatic) | B10: 1st of each month | C10: 1580.28 | F10: what we make 2nd half of month | G10: what we owe 2nd half of month | H10: money left over
A11: Anytime Fitness Payment | B11: 1st of each month | C11: 38.05
A12: Vivint Payment(automatic) | B12: 3rd of each month | C12: 74.9 | F12: =B3+B4 -> 4222.66 | G12: =C25+C26+C27+C28+C29+C30+C31+C32+C33 -> 1558.52 | H12: =F12-G12 -> 2664.14
A13: Citi Black Card | B13: 4th of each month | C13: 150
A14: Blizzard Payment (automatic) | B14: 5th of each month | C14: 14.99
A15: Mohela Loan (automatic) | B15: 6th of each month | C15: 542.02
A16: Synchrony bank | B16: 7th of each month | C16: 25
A17: Rep Daycare #2 (automatic) | B17: each Monday | C17: 50
A18: Great Lakes Student Loan(automatic) - Lauren | B18: 9th of each month | C18: 153.66
A19: Direct TV | B19: 11th of each month | C19: 35
A20: Conway Regional Bill(automatic) | B20: 13th of each month | C20: 68
A21: Nissan Finance | B21: 15th of each month | C21: 299.61
A22: NelNet loan(automatic) - Lauren | B22: 15th of each month | C22: 223.01
A24: 2nd half of month:
A25: Rep Daycare #3 (automatic) | B25: each Monday | C25: 50
A26: Amazon payment | B26: 17th of each month | C26: 91
A27: Greenbrier Water, trash payment | B27: 18th of each month | C27: 33.4
A28: My Media3 internet | B28: 20th of each month | C28: 86.5
A29: At&t Payment (automatic) | B29: 22nd of each month | C29: 227
A30: Entergy Payment (automatic) | B30: 27th of each month | C30: 266
A31: Allstate Payment (automatic) | B31: 28th of each month | C31: 181.62
A32: Tahoe Payment | B32: 30th of each month | C32: 573
A33: Rep Daycare #4 (automatic) | B33: each Monday | C33: 50 | F33: Average for two week span
F34: =(H8+H12)/2 -> 1791.14
A39: Loan Payoff Schedule
A40: Lauren | B40: Great Lakes -128.05
B41: Current Balance - 6310.75
B42: Balance as of November 2017 - 5680.75~
B43: Amount to pay each month - 838.40 + 128.05 = 966.45
B44: Months to pay off - ~6 months or November 2017 to April 2018
B46: Nelnet - 171.55 a month
B47: Current Balance - 9797.33
B48: Balance as of April 2018 - 8357.33
B49: Amount to pay each month - 966.45 + 171.55 = 1138.00
B50: Months to pay off - ~8 months April 2018 to December 2018
A54: Credit Card Debt
B55: Lowes - 110.00
B56: Current Balance - 3606.16
B57: Balance as of August 2017 - 3200.00
B58: Amount to pay each month - 800.00 + 110.00 = 910.00
B59: Month to pay off - ~3.5 months August 2017 to October 2017
B61: US Bank - 60.00
B62: Current Balance - 3003.17
B63: Balance as of October 2017 - 2703.17
B64: Amount to pay each month - 910.00 + 60 = 970.00
B65: Month to pay off - ~3 months November 2017 to Januaray 2018
B67: Amazon - 48.00
B68: Current Balance - 1967.36
... B71: Month to pay off - ~2 months Feb 2018 to March 2018

Sheet February 2018
A1: February 2018 Monthly Budget
A2: Income: | B2: 1st half of month | C2: 2nd half of month
A3: Brian | B3: 2957.69 | C3: 2957.69
A4: Lauren | B4: 1264.97 | C4: 1267.97
A7: Expenses: | B7: Due Date: | C7: Expense Cost: | F7: what we make 1st half of month | G7: what we owe 1st half of month | H7: money left over
A8: 1st half of month: | F8: =B3+B4 -> 4222.66 | G8: =C9+C10+C11+C12+C13+C14+C15+C16+C17+C18+C20+C19+C21+C22 -> 3304.52 | H8: =F8-G8 -> 918.14
A9: Rep Daycare #1 (automatic) | B9: each Monday | C9: 50
A10: New House Payment #1 (automatic) | B10: 1st of each month | C10: 1580.28 | F10: what we make 2nd half of month | G10: what we owe 2nd half of month | H10: money left over
A11: Anytime Fitness Payment | B11: 1st of each month | C11: 38.05
A12: Vivint Payment(automatic) | B12: 3rd of each month | C12: 74.9 | F12: =B3+B4 -> 4222.66 | G12: =C25+C26+C27+C28+C29+C30+C31+C32+C33 -> 1528.52 | H12: =F12-G12 -> 2694.14
A13: Citi Black Card | B13: 4th of each month | C13: 150
A14: Blizzard Payment (automatic) | B14: 5th of each month | C14: 14.99
A15: Mohela Loan (automatic) | B15: 6th of each month | C15: 542.02
A16: Synchrony bank | B16: 7th of each month | C16: 25
A17: Rep Daycare #2 (automatic) | B17: each Monday | C17: 50
A18: Great Lakes Student Loan(automatic) - Lauren | B18: 9th of each month | C18: 153.66
A19: Direct TV | B19: 11th of each month | C19: 35
A20: Conway Regional Bill(automatic) | B20: 13th of each month | C20: 68
A21: Nissan Finance | B21: 15th of each month | C21: 299.61
A22: NelNet loan(automatic) - Lauren | B22: 15th of each month | C22: 223.01
A24: 2nd half of month:
A25: Rep Daycare #3 (automatic) | B25: each Monday | C25: 50
A26: Amazon payment | B26: 17th of each month | C26: 91
A27: Greenbrier Water, trash payment | B27: 18th of each month | C27: 33.4
A28: My Media3 internet | B28: 20th of each month | C28: 86.5
A29: At&t Payment (automatic) | B29: 22nd of each month | C29: 227
A30: Entergy Payment (automatic) | B30: 27th of each month | C30: 236
A31: Allstate Payment (automatic) | B31: 28th of each month | C31: 181.62
A32: Tahoe Payment | B32: 30th of each month | C32: 573
A33: Rep Daycare #4 (automatic) | B33: each Monday | C33: 50 | F33: Average for two week span
F34: =(H8+H12)/2 -> 1806.14
A39: Loan Payoff Schedule
A40: Lauren | B40: Great Lakes -128.05
B41: Current Balance - 6310.75
B42: Balance as of November 2017 - 5680.75~
B43: Amount to pay each month - 838.40 + 128.05 = 966.45
B44: Months to pay off - ~6 months or November 2017 to April 2018
B46: Nelnet - 171.55 a month
B47: Current Balance - 9797.33
B48: Balance as of April 2018 - 8357.33
B49: Amount to pay each month - 966.45 + 171.55 = 1138.00
B50: Months to pay off - ~8 months April 2018 to December 2018
A54: Credit Card Debt
B55: Lowes - 110.00
B56: Current Balance - 3606.16
B57: Balance as of August 2017 - 3200.00
B58: Amount to pay each month - 800.00 + 110.00 = 910.00
B59: Month to pay off - ~3.5 months August 2017 to October 2017
B61: US Bank - 60.00
B62: Current Balance - 3003.17
B63: Balance as of October 2017 - 2703.17
B64: Amount to pay each month - 910.00 + 60 = 970.00
B65: Month to pay off - ~3 months November 2017 to Januaray 2018
B67: Amazon - 48.00
B68: Current Balance - 1967.36
... B71: Month to pay off - ~2 months Feb 2018 to March 2018

Sheet January 2018
A1: January 2018 Monthly Budget
A2: Income: | B2: 1st half of month | C2: 2nd half of month
A3: Brian | B3: 2957.69 | C3: 2957.69
A4: Lauren | B4: 1258.41 | C4: 1258.41
A7: Expenses: | B7: Due Date: | C7: Expense Cost: | F7: what we make 1st half of month | G7: what we owe 1st half of month | H7: money left over
A8: 1st half of month: | F8: =B3+B4 -> 4216.1 | G8: =C9+C10+C11+C12+C13+C14+C15+C16+C17+C18+C20+C19+C21+C22 -> 3304.52 | H8: =F8-G8 -> 911.58
A9: Rep Daycare #1 (automatic) | B9: each Monday | C9: 50
A10: New House Payment #1 (automatic) | B10: 1st of each month | C10: 1580.28 | F10: what we make 2nd half of month | G10: what we owe 2nd half of month | H10: money left over
A11: Anytime Fitness Payment | B11: 1st of each month | C11: 38.05
A12: Vivint Payment(automatic) | B12: 3rd of each month | C12: 74.9 | F12: =B3+B4 -> 4216.1 | G12: =C25+C26+C27+C28+C29+C30+C31+C32+C33 -> 1445 | H12: =F12-G12 -> 2771.1
A13: Citi Black Card | B13: 4th of each month | C13: 150
A14: Blizzard Payment (automatic) | B14: 5th of each month | C14: 14.99
A15: Mohela Loan (automatic) | B15: 6th of each month | C15: 542.02
A16: Synchrony bank | B16: 7th of each month | C16: 25
A17: Rep Daycare #2 (automatic) | B17: each Monday | C17: 50
A18: Great Lakes Student Loan(automatic) - Lauren | B18: 9th of each month | C18: 153.66
A19: Direct TV | B19: 11th of each month | C19: 35
A20: Conway Regional Bill(automatic) | B20: 13th of each month | C20: 68
A21: Nissan Finance | B21: 15th of each month | C21: 299.61
A22: NelNet loan(automatic) - Lauren | B22: 15th of each month | C22: 223.01
A24: 2nd half of month:
A25: Rep Daycare #3 (automatic) | B25: each Monday | C25: 50
A26: Amazon payment | B26: 17th of each month | C26: 91
A27: Greenbrier Water, trash payment | B27: 18th of each month | C27: 33.4
A28: My Media3 internet | B28: 20th of each month | C28: 86.5
A29: At&t Payment (automatic) | B29: 22nd of each month | C29: 174.48
A30: Entergy Payment (automatic) | B30: 27th of each month | C30: 205
A31: Allstate Payment (automatic) | B31: 28th of each month | C31: 181.62
A32: Tahoe Payment | B32: 30th of each month | C32: 573
A33: Rep Daycare #4 (automatic) | B33: each Monday | C33: 50 | F33: Average for two week span
F34: =(H8+H12)/2 -> 1841.34
A39: Loan Payoff Schedule
A40: Lauren | B40: Great Lakes -128.05
B41: Current Balance - 6310.75
B42: Balance as of November 2017 - 5680.75~
B43: Amount to pay each month - 838.40 + 128.05 = 966.45
B44: Months to pay off - ~6 months or November 2017 to April 2018
B46: Nelnet - 171.55 a month
B47: Current Balance - 9797.33
B48: Balance as of April 2018 - 8357.33
B49: Amount to pay each month - 966.45 + 171.55 = 1138.00
B50: Months to pay off - ~8 months April 2018 to December 2018
A54: Credit Card Debt
B55: Lowes - 110.00
B56: Current Balance - 3606.16
B57: Balance as of August 2017 - 3200.00
B58: Amount to pay each month - 800.00 + 110.00 = 910.00
B59: Month to pay off - ~3.5 months August 2017 to October 2017
B61: US Bank - 60.00
B62: Current Balance - 3003.17
B63: Balance as of October 2017 - 2703.17
B64: Amount to pay each month - 910.00 + 60 = 970.00
B65: Month to pay off - ~3 months November 2017 to Januaray 2018
B67: Amazon - 48.00
B68: Current Balance - 1967.36
... B71: Month to pay off - ~2 months Feb 2018 to March 2018

Sheet December 2017
A1: December 2017 Monthly Budget
A2: Income: | B2: 1st half of month | C2: 2nd half of month
A3: Brian | B3: 2356.85 | C3: 2356.85
A4: Lauren | B4: 1258.41 | C4: 1258.41
A7: Expenses: | B7: Due Date: | C7: Expense Cost: | F7: what we make 1st half of month | G7: what we owe 1st half of month | H7: money left over
A8: 1st half of month: | F8: =B3+B4 -> 3615.26 | G8: =C9+C10+C11+C12+C13+C14+C15+C16+C17+C18+C20+C19+C21+C22 -> 3314.54 | H8: =F8-G8 -> 300.72
A9: Rep Daycare #1 (automatic) | B9: each Monday | C9: 50
A10: New House Payment #1 (automatic) | B10: 1st of each month | C10: 1590.3 | F10: what we make 2nd half of month | G10: what we owe 2nd half of month | H10: money left over
A11: Anytime Fitness Payment | B11: 1st of each month | C11: 38.05
A12: Vivint Payment(automatic) | B12: 3rd of each month | C12: 74.9 | F12: =B3+B4 -> 3615.26 | G12: =C25+C26+C27+C28+C29+C30+C31+C32+C33 -> 1389.02 | H12: =F12-G12 -> 2226.24
A13: Citi Black Card | B13: 4th of each month | C13: 150
A14: Blizzard Payment (automatic) | B14: 5th of each month | C14: 14.99
A15: Mohela Loan (automatic) | B15: 6th of each month | C15: 542.02
A16: Synchrony bank | B16: 7th of each month | C16: 25
A17: Evan & Rep Daycare #2 (automatic) | B17: each Monday | C17: 50
A18: Great Lakes Student Loan(automatic) - Lauren | B18: 9th of each month | C18: 153.66
A19: Direct TV | B19: 11th of each month | C19: 35
A20: Conway Regional Bill(automatic) | B20: 13th of each month | C20: 68
A21: Nissan Finance | B21: 15th of each month | C21: 299.61
A22: NelNet loan(automatic) - Lauren | B22: 15th of each month | C22: 223.01
A24: 2nd half of month:
A25: Evan & Rep Daycare #3 (automatic) | B25: each Monday | C25: 50
A26: Amazon payment | B26: 17th of each month | C26: 50
A27: Greenbrier Water, trash payment | B27: 18th of each month | C27: 43.42
A28: My Media3 internet | B28: 20th of each month | C28: 86.5
A29: At&t Payment (automatic) | B29: 22nd of each month | C29: 174.48
A30: Entergy Payment (automatic) | B30: 27th of each month | C30: 230
A31: Allstate Payment (automatic) | B31: 28th of each month | C31: 181.62
A32: Tahoe Payment | B32: 30th of each month | C32: 573
A33: Evan & Rep Daycare #4 (automatic) | B33: each Monday | F33: Average for two week span
F34: =(H8+H12)/2 -> 1263.48
A39: Loan Payoff Schedule
A40: Lauren | B40: Great Lakes -128.05
B41: Current Balance - 6310.75
B42: Balance as of November 2017 - 5680.75~
B43: Amount to pay each month - 838.40 + 128.05 = 966.45
B44: Months to pay off - ~6 months or November 2017 to April 2018
B46: Nelnet - 171.55 a month
B47: Current Balance - 9797.33
B48: Balance as of April 2018 - 8357.33
B49: Amount to pay each month - 966.45 + 171.55 = 1138.00
B50: Months to pay off - ~8 months April 2018 to December 2018
A54: Credit Card Debt
B55: Lowes - 110.00
B56: Current Balance - 3606.16
B57: Balance as of August 2017 - 3200.00
B58: Amount to pay each month - 800.00 + 110.00 = 910.00
B59: Month to pay off - ~3.5 months August 2017 to October 2017
B61: US Bank - 60.00
B62: Current Balance - 3003.17
B63: Balance as of October 2017 - 2703.17
B64: Amount to pay each month - 910.00 + 60 = 970.00
B65: Month to pay off - ~3 months November 2017 to Januaray 2018
B67: Amazon - 48.00
B68: Current Balance - 1967.36
... B71: Month to pay off - ~2 months Feb 2018 to March 2018

Sheet November 2017
A1: November 2017 Monthly Budget
A2: Income: | B2: 1st half of month | C2: 2nd half of month
A3: Brian | B3: 2356.85 | C3: 2356.85
A4: Lauren | B4: 1258.41 | C4: 1258.41
A7: Expenses: | B7: Due Date: | C7: Expense Cost: | F7: what we make 1st half of month | G7: what we owe 1st half of month | H7: money left over
A8: 1st half of month: | F8: =B3+B4 -> 3615.26 | G8: =C9+C10+C11+C12+C13+C14+C15+C16+C17+C19+C18+C20+C21 -> 3356.48 | H8: =F8-G8 -> 258.78
A9: Rep Daycare #1 (automatic) | B9: each Monday | C9: 120
A10: New House Payment #1 (automatic) | B10: 1st of each month | C10: 1590.3 | F10: what we make 2nd half of month | G10: what we owe 2nd half of month | H10: money left over
A11: Vivint Payment(automatic) | B11: 3rd of each month | C11: 74.9 | F11: =B3+B4 -> 3615.26 | G11: =C24+C25+C26+C27+C28+C29+C30+C31+C32 -> 1419.02 | H11: =F11-G11 -> 2196.24
A12: Citi Black Card | B12: 4th of each month | C12: 150
A13: Blizzard Payment (automatic) | B13: 5th of each month | C13: 14.99
A14: Mohela Loan (automatic) | B14: 6th of each month | C14: 542.02
A15: Synchrony bank | B15: 7th of each month | C15: 25
A16: Evan & Rep Daycare #2 (automatic) | B16: each Monday | C16: 50
A17: Great Lakes Student Loan(automatic) - Lauren | B17: 9th of each month | C17: 153.66
A18: PS VUE (automatic) | B18: 11th of each month | C18: 44.99
A19: Conway Regional Bill(automatic) | B19: 13th of each month | C19: 68
A20: Nissan Finance | B20: 15th of each month | C20: 299.61
A21: NelNet loan(automatic) - Lauren | B21: 15th of each month | C21: 223.01
A23: 2nd half of month:
A24: Evan & Rep Daycare #3 (automatic) | B24: each Monday | C24: 50
A25: Amazon payment | B25: 17th of each month | C25: 50
A26: Greenbrier Water, trash payment | B26: 18th of each month | C26: 43.42
A27: My Media3 internet | B27: 20th of each month | C27: 66.5
A28: At&t Payment (automatic) | B28: 22nd of each month | C28: 174.48
A29: Entergy Payment (automatic) | B29: 27th of each month | C29: 230
A30: Allstate Payment (automatic) | B30: 28th of each month | C30: 181.62
A31: Tahoe Payment | B31: 30th of each month | C31: 573
A32: Evan & Rep Daycare #4 (automatic) | B32: each Monday | C32: 50 | F32: Average for two week span
F33: =(H8+H11)/2 -> 1227.51
A38: Loan Payoff Schedule
A39: Lauren | B39: Great Lakes -128.05
B40: Current Balance - 6310.75
B41: Balance as of November 2017 - 5680.75~
B42: Amount to pay each month - 838.40 + 128.05 = 966.45
B43: Months to pay off - ~6 months or November 2017 to April 2018
B45: Nelnet - 171.55 a month
B46: Current Balance - 9797.33
B47: Balance as of April 2018 - 8357.33
B48: Amount to pay each month - 966.45 + 171.55 = 1138.00
B49: Months to pay off - ~8 months April 2018 to December 2018
A53: Credit Card Debt
B54: Lowes - 110.00
B55: Current Balance - 3606.16
B56: Balance as of August 2017 - 3200.00
B57: Amount to pay each month - 800.00 + 110.00 = 910.00
B58: Month to pay off - ~3.5 months August 2017 to October 2017
B60: US Bank - 60.00
B61: Current Balance - 3003.17
B62: Balance as of October 2017 - 2703.17
B63: Amount to pay each month - 910.00 + 60 = 970.00
B64: Month to pay off - ~3 months November 2017 to Januaray 2018
B66: Amazon - 48.00
B67: Current Balance - 1967.36
... B70: Month to pay off - ~2 months Feb 2018 to March 2018

Sheet October 2017
A1: October 2017 Monthly Budget
A2: Income: | B2: 1st half of month | C2: 2nd half of month
A3: Brian | B3: 2356.85 | C3: 2356.85
A4: Lauren | B4: 1258.41 | C4: 1258.41
A7: Expenses: | B7: Due Date: | C7: Expense Cost: | F7: what we make 1st half of month | G7: what we owe 1st half of month | H7: money left over
A8: 1st half of month: | F8: =B3+B4 -> 3615.26 | G8: =C9+C10+C11+C12+C13+C14+C15+C16+C17+C18+C19+C20 -> 3099.81 | H8: =F8-G8 -> 515.45
A9: Rep Daycare #1 (automatic) | B9: each Monday | C9: 120
A10: New House Payment #1 (automatic) | B10: 1st of each month | C10: 1590.3 | F10: what we make 2nd half of month | G10: what we owe 2nd half of month | H10: money left over
A11: Vivint Payment(automatic) | B11: 3rd of each month | C11: 74.9 | F11: =B3+B4 -> 3615.26 | G11: =C23+C24+C25+C26+C27+C28+C29+C30+C31+C32 -> 1741.1 | H11: =F11-G11 -> 1874.16
A12: Citi Black Card | B12: 4th of each month | C12: 150
A13: Blizzard Payment (automatic) | B13: 5th of each month | C13: 14.99
A14: SoFi Load (automatic) | B14: 6th of each month | C14: 542.02
A15: Synchrony bank | B15: 7th of each month | C15: 25
A16: Evan & Rep Daycare #2 (automatic) | B16: each Monday | C16: 120
A17: Great Lakes Student Loan(automatic) - Lauren | B17: 9th of each month | C17: 128.05
A18: Conway Regional Bill(automatic) | B18: 10th of each month | C18: 68
A19: Direct TV (automatic) | B19: 11th of each month | C19: 95
A20: NelNet loan(automatic) - Lauren | B20: 15th of each month | C20: 171.55
A22: 2nd half of month:
A23: Evan & Rep Daycare #3 (automatic) | B23: each Monday | C23: 120
A24: Amazon payment | B24: 17th of each month | C24: 50
A25: Greenbrier Water, trash payment | B25: 18th of each month | C25: 32
A26: My Media3 internet | B26: 20th of each month | C26: 66.5
A27: At&t Payment (automatic) | B27: 22nd of each month | C27: 174.48
A28: Nissan Altima Payment | B28: 23rd of each month | C28: 216.5
A29: Entergy Payment (automatic) | B29: 27th of each month | C29: 207
A30: Allstate Payment (automatic) | B30: 28th of each month | C30: 181.62
A31: Tahoe Payment | B31: 30th of each month | C31: 573
A32: Evan & Rep Daycare #4 (automatic) | B32: each Monday | C32: 120 | F32: Average for two week span
F33: =(H8+H11)/2 -> 1194.805
A38: Loan Payoff Schedule
A39: Lauren | B39: Great Lakes -128.05
B40: Current Balance - 6310.75
B41: Balance as of November 2017 - 5680.75~
B42: Amount to pay each month - 838.40 + 128.05 = 966.45
B43: Months to pay off - ~6 months or November 2017 to April 2018
B45: Nelnet - 171.55 a month
B46: Current Balance - 9797.33
B47: Balance as of April 2018 - 8357.33
B48: Amount to pay each month - 966.45 + 171.55 = 1138.00
B49: Months to pay off - ~8 months April 2018 to December 2018
A53: Credit Card Debt
B54: Lowes - 110.00
B55: Current Balance - 3606.16
B56: Balance as of August 2017 - 3200.00
B57: Amount to pay each month - 800.00 + 110.00 = 910.00
B58: Month to pay off - ~3.5 months August 2017 to October 2017
B60: US Bank - 60.00
B61: Current Balance - 3003.17
B62: Balance as of October 2017 - 2703.17
B63: Amount to pay each month - 910.00 + 60 = 970.00
B64: Month to pay off - ~3 months November 2017 to Januaray 2018
B66: Amazon - 48.00
B67: Current Balance - 1967.36
... B70: Month to pay off - ~2 months Feb 2018 to March 2018

Sheet September 2017
A1: September 2017 Monthly Budget
A2: Income: | B2: 1st half of month | C2: 2nd half of month
A3: Brian | B3: 2440.5 | C3: 2440.5
A4: Lauren | B4: 1258.41 | C4: 1258.41
A7: Expenses: | B7: Due Date: | C7: Expense Cost: | F7: what we make 1st half of month | G7: what we owe 1st half of month | H7: money left over
A8: 1st half of month: | F8: =B3+B4 -> 3698.91 | G8: =C9+C10+C11+C12+C13+C14+C15+C16+C17+C18+C19 -> 2506.79 | H8: =F8-G8 -> 1192.12
A9: Rep Daycare #1 (automatic) | B9: each Monday | C9: 120
A10: New House Payment #1 (automatic) | B10: 1st of each month | C10: 1590.3 | F10: what we make 2nd half of month | G10: what we owe 2nd half of month | H10: money left over
A11: Vivint Payment(automatic) | B11: 3rd of each month | C11: 74.9 | F11: =B3+B4 -> 3698.91 | G11: =C22+C23+C24+C25+C26+C27+C28+C29+C30+C31 -> 1756.77 | H11: =F11-G11 -> 1942.14
A12: Lowes payment | B12: 4th of each month | C12: 99
A13: Blizzard Payment (automatic) | B13: 5th of each month | C13: 14.99
A14: Synchrony bank | B14: 7th of each month | C14: 25
A15: Evan & Rep Daycare #2 (automatic) | B15: each Monday | C15: 120
A16: Great Lakes Student Loan(automatic) - Lauren | B16: 9th of each month | C16: 128.05
A17: Conway Regional Bill(automatic) | B17: 10th of each month | C17: 68
A18: Direct TV (automatic) | B18: 11th of each month | C18: 95
A19: NelNet loan(automatic) - Lauren | B19: 15th of each month | C19: 171.55
A21: 2nd half of month:
A22: Evan & Rep Daycare #3 (automatic) | B22: each Monday | C22: 120
A23: Amazon payment | B23: 17th of each month | C23: 50
A24: Greenbrier Water, trash payment | B24: 18th of each month | C24: 32
A25: My Media3 internet | B25: 20th of each month | C25: 66.5
A26: At&t Payment (automatic) | B26: 22nd of each month | C26: 174.48
A27: Nissan Altima Payment | B27: 23rd of each month | C27: 216.5
A28: Entergy Payment (automatic) | B28: 27th of each month | C28: 207
A29: Allstate Payment (automatic) | B29: 28th of each month | C29: 197.29
A30: Tahoe Payment | B30: 30th of each month | C30: 573
A31: Evan & Rep Daycare #4 (automatic) | B31: each Monday | C31: 120
F32: Average for two week span
F33: =(H8+H11)/2 -> 1567.13
A37: Loan Payoff Schedule
A38: Lauren | B38: Great Lakes -128.05
B39: Current Balance - 6310.75
B40: Balance as of November 2017 - 5680.75~
B41: Amount to pay each month - 838.40 + 128.05 = 966.45
B42: Months to pay off - ~6 months or November 2017 to April 2018
B44: Nelnet - 171.55 a month
B45: Current Balance - 9797.33
B46: Balance as of April 2018 - 8357.33
B47: Amount to pay each month - 966.45 + 171.55 = 1138.00
B48: Months to pay off - ~8 months April 2018 to December 2018
A52: Credit Card Debt
B53: Lowes - 110.00
B54: Current Balance - 3606.16
B55: Balance as of August 2017 - 3200.00
B56: Amount to pay each month - 800.00 + 110.00 = 910.00
B57: Month to pay off - ~3.5 months August 2017 to October 2017
B59: US Bank - 60.00
B60: Current Balance - 3003.17
B61: Balance as of October 2017 - 2703.17
B62: Amount to pay each month - 910.00 + 60 = 970.00
B63: Month to pay off - ~3 months November 2017 to Januaray 2018
B65: Amazon - 48.00
B66: Current Balance - 1967.36
... B69: Month to pay off - ~2 months Feb 2018 to March 2018

Sheet August 2017
A1: August 2017 Monthly Budget
A2: Income: | B2: 1st half of month | C2: 2nd half of month
A3: Brian | B3: 2440.5 | C3: 2440.5
A4: Lauren | B4: 1258.41 | C4: 1258.41
A7: Expenses: | B7: Due Date: | C7: Expense Cost: | F7: what we make 1st half of month | G7: what we owe 1st half of month | H7: money left over
A8: 1st half of month: | F8: =B3+B4 -> 3698.91 | G8: =C9+C10+C11+C12+C13+C14+C15+C16+C17+C18+C19 -> 2506.79 | H8: =F8-G8 -> 1192.12
A9: Rep Daycare #1 (automatic) | B9: each Monday | C9: 120
A10: New House Payment #1 (automatic) | B10: 1st of each month | C10: 1590.3 | F10: what we make 2nd half of month | G10: what we owe 2nd half of month | H10: money left over
A11: Vivint Payment(automatic) | B11: 3rd of each month | C11: 74.9 | F11: =B3+B4 -> 3698.91 | G11: =C22+C23+C24+C25+C26+C27+C28+C29+C30+C31+C32 -> 2288.79 | H11: =F11-G11 -> 1410.12
A12: Lowes payment | B12: 4th of each month | C12: 99
A13: Blizzard Payment (automatic) | B13: 5th of each month | C13: 14.99
A14: Synchrony bank | B14: 7th of each month | C14: 25
A15: Evan & Rep Daycare #2 (automatic) | B15: each Monday | C15: 120
A16: Great Lakes Student Loan(automatic) - Lauren | B16: 9th of each month | C16: 128.05
A17: Conway Regional Bill(automatic) | B17: 10th of each month | C17: 68
A18: Direct TV (automatic) | B18: 11th of each month | C18: 95
A19: NelNet loan(automatic) - Lauren | B19: 15th of each month | C19: 171.55
A21: 2nd half of month:
A22: Evan & Rep Daycare #3 (automatic) | B22: each Monday | C22: 120
A23: Amazon payment | B23: 17th of each month | C23: 50
A24: Greenbrier Water, trash payment | B24: 18th of each month | C24: 32
A25: My Media3 internet | B25: 20th of each month | C25: 66.5
A26: At&t Payment (automatic) | B26: 22nd of each month | C26: 174.48
A27: Nissan Altima Payment | B27: 23rd of each month | C27: 216.5
A28: SoFi Load (automatic) | B28: 25th of each month | C28: 542.02
A29: Entergy Payment (automatic) | B29: 27th of each month | C29: 197
A30: Allstate Payment (automatic) | B30: 28th of each month | C30: 197.29
A31: Tahoe Payment | B31: 30th of each month | C31: 573
A32: Evan & Rep Daycare #4 (automatic) | B32: each Monday | C32: 120 | F32: Average for two week span
F33: =(H8+H11)/2 -> 1301.12
A38: Loan Payoff Schedule
A39: Lauren | B39: Great Lakes -128.05
B40: Current Balance - 6310.75
B41: Balance as of November 2017 - 5680.75~
B42: Amount to pay each month - 838.40 + 128.05 = 966.45
B43: Months to pay off - ~6 months or November 2017 to April 2018
B45: Nelnet - 171.55 a month
B46: Current Balance - 9797.33
B47: Balance as of April 2018 - 8357.33
B48: Amount to pay each month - 966.45 + 171.55 = 1138.00
B49: Months to pay off - ~8 months April 2018 to December 2018
A53: Credit Card Debt
B54: Lowes - 110.00
B55: Current Balance - 3606.16
B56: Balance as of August 2017 - 3200.00
B57: Amount to pay each month - 800.00 + 110.00 = 910.00
B58: Month to pay off - ~3.5 months August 2017 to October 2017
B60: US Bank - 60.00
B61: Current Balance - 3003.17
B62: Balance as of October 2017 - 2703.17
B63: Amount to pay each month - 910.00 + 60 = 970.00
B64: Month to pay off - ~3 months November 2017 to Januaray 2018
B66: Amazon - 48.00
B67: Current Balance - 1967.36
... B70: Month to pay off - ~2 months Feb 2018 to March 2018

Sheet July 2017
A1: July 2017 Monthly Budget
A2: Income: | B2: 1st half of month | C2: 2nd half of month
A3: Brian | B3: 2440.5 | C3: 2440.5
A4: Lauren | B4: 1223.79 | C4: 1223.79
A7: Expenses: | B7: Due Date: | C7: Expense Cost: | F7: what we make 1st half of month | G7: what we owe 1st half of month | H7: money left over
A8: 1st half of month: | F8: =B3+B4 -> 3664.29 | G8: =C9+C10+C11+C12+C13+C14+C15+C16+C17+C18+C19 -> 2266.79 | H8: =F8-G8 -> 1397.5
A9: Evan & Rep Daycare #1 (automatic) | B9: each Monday
A10: New House Payment #1 (automatic) | B10: 1st of each month | C10: 1590.3 | F10: what we make 2nd half of month | G10: what we owe 2nd half of month | H10: money left over
A11: Vivint Payment(automatic) | B11: 3rd of each month | C11: 74.9 | F11: =B3+B4 -> 3664.29 | G11: =C22+C23+C24+C25+C26+C27+C28+C29+C30+C31+C32 -> 2049.79 | H11: =F11-G11 -> 1614.5
A12: Lowes payment | B12: 4th of each month | C12: 99
A13: Blizzard Payment (automatic) | B13: 5th of each month | C13: 14.99
A14: Synchrony bank | B14: 7th of each month | C14: 25
A15: Evan & Rep Daycare #2 (automatic) | B15: each Monday
A16: Great Lakes Student Loan(automatic) - Lauren | B16: 9th of each month | C16: 128.05
A17: Conway Regional Bill(automatic) | B17: 10th of each month | C17: 68
A18: Direct TV (automatic) | B18: 11th of each month | C18: 95
A19: NelNet loan(automatic) - Lauren | B19: 15th of each month | C19: 171.55
A21: 2nd half of month:
A22: Evan & Rep Daycare #3 (automatic) | B22: each Monday
A23: Amazon payment | B23: 17th of each month | C23: 50
A24: Greenbrier Water, trash payment | B24: 18th of each month | C24: 32
A25: My Media3 internet | B25: 20th of each month | C25: 66.5
A26: At&t Payment (automatic) | B26: 22nd of each month | C26: 174.48
A27: Nissan Altima Payment | B27: 23rd of each month | C27: 216.5
A28: SoFi Load (automatic) | B28: 25th of each month | C28: 542.02
A29: Entergy Payment (automatic) | B29: 27th of each month | C29: 198
A30: Allstate Payment (automatic) | B30: 28th of each month | C30: 197.29
A31: Tahoe Payment | B31: 30th of each month | C31: 573
A32: Evan & Rep Daycare #4 (automatic) | B32: each Monday | F32: Average for two week span
F33: =(H8+H11)/2 -> 1506
A38: Loan Payoff Schedule
A39: Lauren | B39: Great Lakes -128.05
B40: Current Balance - 6310.75
B41: Balance as of November 2017 - 5680.75~
B42: Amount to pay each month - 838.40 + 128.05 = 966.45
B43: Months to pay off - ~6 months or November 2017 to April 2018
B45: Nelnet - 171.55 a month
B46: Current Balance - 9797.33
B47: Balance as of April 2018 - 8357.33
B48: Amount to pay each month - 966.45 + 171.55 = 1138.00
B49: Months to pay off - ~8 months April 2018 to December 2018
A53: Credit Card Debt
B54: Lowes - 110.00
B55: Current Balance - 3606.16
B56: Balance as of August 2017 - 3200.00
B57: Amount to pay each month - 800.00 + 110.00 = 910.00
B58: Month to pay off - ~3.5 months August 2017 to October 2017
B60: US Bank - 60.00
B61: Current Balance - 3003.17
B62: Balance as of October 2017 - 2703.17
B63: Amount to pay each month - 910.00 + 60 = 970.00
B64: Month to pay off - ~3 months November 2017 to Januaray 2018
B66: Amazon - 48.00
B67: Current Balance - 1967.36
... B70: Month to pay off - ~2 months Feb 2018 to March 2018

Sheet June 2017
A1: June 2017 Monthly Budget
A2: Income: | B2: 1st half of month | C2: 2nd half of month
A3: Brian | B3: 2440.5 | C3: 2440.5
A4: Lauren | B4: 1223.79 | C4: 1223.79
A7: Expenses: | B7: Due Date: | C7: Expense Cost: | F7: what we make 1st half of month | G7: what we owe 1st half of month | H7: money left over
A8: 1st half of month: | F8: =B3+B4 -> 3664.29 | G8: =C9+C10+C11+C12+C13+C14+C15+C16+C17+C18+C19 -> 2266.79 | H8: =F8-G8 -> 1397.5
A9: Evan & Rep Daycare #1 (automatic) | B9: each Monday
A10: New House Payment #1 (automatic) | B10: 1st of each month | C10: 1590.3 | F10: what we make 2nd half of month | G10: what we owe 2nd half of month | H10: money left over
A11: Vivint Payment(automatic) | B11: 3rd of each month | C11: 74.9 | F11: =B3+B4 -> 3664.29 | G11: =C22+C23+C24+C25+C26+C27+C28+C29+C30+C31+C32 -> 2058.79 | H11: =F11-G11 -> 1605.5
A12: Lowes payment | B12: 4th of each month | C12: 99
A13: Blizzard Payment (automatic) | B13: 5th of each month | C13: 14.99
A14: Synchrony bank | B14: 7th of each month | C14: 25
A15: Evan & Rep Daycare #2 (automatic) | B15: each Monday
A16: Great Lakes Student Loan(automatic) - Lauren | B16: 9th of each month | C16: 128.05
A17: Conway Regional Bill(automatic) | B17: 10th of each month | C17: 68
A18: Direct TV (automatic) | B18: 11th of each month | C18: 95
A19: NelNet loan(automatic) - Lauren | B19: 15th of each month | C19: 171.55
A21: 2nd half of month:
A22: Evan & Rep Daycare #3 (automatic) | B22: each Monday
A23: Amazon payment | B23: 17th of each month | C23: 50
A24: Greenbrier Water, trash payment | B24: 18th of each month | C24: 32
A25: My Media3 internet | B25: 20th of each month | C25: 66.5
A26: At&t Payment (automatic) | B26: 22nd of each month | C26: 174.48
A27: Nissan Altima Payment | B27: 23rd of each month | C27: 216.5
A28: SoFi Load (automatic) | B28: 25th of each month | C28: 542.02
A29: Entergy Payment (automatic) | B29: 27th of each month | C29: 207
A30: Allstate Payment (automatic) | B30: 28th of each month | C30: 197.29
A31: Tahoe Payment | B31: 30th of each month | C31: 573
A32: Evan & Rep Daycare #4 (automatic) | B32: each Monday | F32: Average for two week span
F33: =(H8+H11)/2 -> 1501.5
A38: Loan Payoff Schedule
A39: Lauren | B39: Great Lakes -128.05
B40: Current Balance - 6310.75
B41: Balance as of November 2017 - 5680.75~
B42: Amount to pay each month - 838.40 + 128.05 = 966.45
B43: Months to pay off - ~6 months or November 2017 to April 2018
B45: Nelnet - 171.55 a month
B46: Current Balance - 9797.33
B47: Balance as of April 2018 - 8357.33
B48: Amount to pay each month - 966.45 + 171.55 = 1138.00
B49: Months to pay off - ~8 months April 2018 to December 2018
A53: Credit Card Debt
B54: Lowes - 110.00
B55: Current Balance - 3606.16
B56: Balance as of August 2017 - 3200.00
B57: Amount to pay each month - 800.00 + 110.00 = 910.00
B58: Month to pay off - ~3.5 months August 2017 to October 2017
B60: US Bank - 60.00
B61: Current Balance - 3003.17
B62: Balance as of October 2017 - 2703.17
B63: Amount to pay each month - 910.00 + 60 = 970.00
B64: Month to pay off - ~3 months November 2017 to Januaray 2018
B66: Amazon - 48.00
B67: Current Balance - 1967.36
... B70: Month to pay off - ~2 months Feb 2018 to March 2018

Sheet May 2017
A1: May 2017 Monthly Budget
A2: Income: | B2: 1st half of month | C2: 2nd half of month
A3: Brian | B3: 2322.05 | C3: 2322.05
A4: Lauren | B4: 1223.79 | C4: 1223.79
A7: Expenses: | B7: Due Date: | C7: Expense Cost: | F7: what we make 1st half of month | G7: what we owe 1st half of month | H7: money left over
A8: 1st half of month: | F8: =B3+B4 -> 3545.84 | G8: =C9+C10+C11+C12+C13+C14+C15+C16+C17+C18+C19 -> 2685.99 | H8: =F8-G8 -> 859.85
A9: Evan & Rep Daycare #1 (automatic) | B9: each Monday | C9: 209.6
A10: New House Payment #1 (automatic) | B10: 1st of each month | C10: 1590.3 | F10: what we make 2nd half of month | G10: what we owe 2nd half of month | H10: money left over
A11: Vivint Payment(automatic) | B11: 3rd of each month | C11: 74.9 | F11: =B3+B4 -> 3545.84 | G11: =C22+C23+C24+C25+C26+C27+C28+C29+C30+C31+C32 -> 2450.95 | H11: =F11-G11 -> 1094.89
A12: Lowes payment | B12: 4th of each month | C12: 99
A13: Blizzard Payment (automatic) | B13: 5th of each month | C13: 14.99
A14: Synchrony bank | B14: 7th of each month | C14: 25
A15: Evan & Rep Daycare #2 (automatic) | B15: each Monday | C15: 209.6
A16: Great Lakes Student Loan(automatic) - Lauren | B16: 9th of each month | C16: 128.05
A17: Conway Regional Bill(automatic) | B17: 10th of each month | C17: 68
A18: Direct TV (automatic) | B18: 11th of each month | C18: 95
A19: NelNet loan(automatic) - Lauren | B19: 15th of each month | C19: 171.55
A21: 2nd half of month:
A22: Evan & Rep Daycare #3 (automatic) | B22: each Monday | C22: 209.6
A23: Amazon payment | B23: 17th of each month | C23: 25
A24: Greenbrier Water, trash payment | B24: 18th of each month | C24: 28.13
A25: My Media3 internet | B25: 20th of each month | C25: 61
A26: At&t Payment (automatic) | B26: 22nd of each month | C26: 174.48
A27: Nissan Altima Payment | B27: 23rd of each month | C27: 216.5
A28: SoFi Load (automatic) | B28: 25th of each month | C28: 542.02
A29: Entergy Payment (automatic) | B29: 27th of each month | C29: 214.33
A30: Allstate Payment (automatic) | B30: 28th of each month | C30: 197.29
A31: Tahoe Payment | B31: 30th of each month | C31: 573
A32: Evan & Rep Daycare #4 (automatic) | B32: each Monday | C32: 209.6 | F32: Average for two week span
F33: =(H8+H11)/2 -> 977.37
E35: 172.16
A38: Loan Payoff Schedule
A39: Lauren | B39: Great Lakes -128.05
B40: Current Balance - 6310.75
B41: Balance as of November 2017 - 5680.75~
B42: Amount to pay each month - 838.40 + 128.05 = 966.45
B43: Months to pay off - ~6 months or November 2017 to April 2018
B45: Nelnet - 171.55 a month
B46: Current Balance - 9797.33
B47: Balance as of April 2018 - 8357.33
B48: Amount to pay each month - 966.45 + 171.55 = 1138.00
B49: Months to pay off - ~8 months April 2018 to December 2018
A53: Credit Card Debt
B54: Lowes - 110.00
B55: Current Balance - 3606.16
B56: Balance as of August 2017 - 3200.00
B57: Amount to pay each month - 800.00 + 110.00 = 910.00
B58: Month to pay off - ~3.5 months August 2017 to October 2017
B60: US Bank - 60.00
B61: Current Balance - 3003.17
B62: Balance as of October 2017 - 2703.17
B63: Amount to pay each month - 910.00 + 60 = 970.00
B64: Month to pay off - ~3 months November 2017 to Januaray 2018
B66: Amazon - 48.00
B67: Current Balance - 1967.36
... B70: Month to pay off - ~2 months Feb 2018 to March 2018

Sheet April 2017
A1: April 2017 Monthly Budget
A2: Income: | B2: 1st half of month | C2: 2nd half of month
A3: Brian | B3: 2322.05 | C3: 2322.05
A4: Lauren | B4: 1223.79 | C4: 1223.79
A7: Expenses: | B7: Due Date: | C7: Expense Cost: | F7: what we make 1st half of month | G7: what we owe 1st half of month | H7: money left over
A8: 1st half of month: | F8: =B3+B4 -> 3545.84 | G8: =C9+C10+C11+C12+C13+C14+C15+C16+C17+C18+C19+C20+C21 -> 2817.63 | H8: =F8-G8 -> 728.21
A9: Evan & Rep Daycare #1 (automatic) | B9: each Monday | C9: 209.6
A10: New House Payment #1 (automatic) | B10: 1st of each month | C10: 1590.3 | F10: what we make 2nd half of month | G10: what we owe 2nd half of month | H10: money left over
A11: Vivint Payment(automatic) | B11: 3rd of each month | C11: 74.9 | F11: =B3+B4 -> 3545.84 | G11: =C24+C25+C26+C27+C28+C29+C30+C31+C32+C33+C34+C35+C36 -> 2417.94 | H11: =F11-G11 -> 1127.9
A12: Navient (automatic) | B12: 4th of each month | C12: 152.64
A13: Lowes payment | B13: 4th of each month | C13: 78
A14: Blizzard Payment (automatic) | B14: 5th of each month | C14: 14.99
A15: Synchrony bank | B15: 7th of each month | C15: 25
A16: Evan & Rep Daycare #2 (automatic) | B16: each Monday | C16: 209.6
A17: Great Lakes Student Loan(automatic) - Lauren | B17: 9th of each month | C17: 128.05
A18: Conway Regional Bill(automatic) | B18: 10th of each month | C18: 68
A19: Direct TV (automatic) | B19: 11th of each month | C19: 95
A20: NelNet loan(automatic) - Lauren | B20: 15th of each month | C20: 171.55
A23: 2nd half of month:
A24: Evan & Rep Daycare #3 (automatic) | B24: each Monday | C24: 209.6
A25: Amazon payment | B25: 17th of each month | C25: 25
A26: Greenbrier Water, trash payment | B26: 18th of each month | C26: 28.13
A27: My Media3 internet | B27: 20th of each month | C27: 61
A28: At&t Payment (automatic) | B28: 22nd of each month | C28: 174.48
A29: Nissan Altima Payment | B29: 23rd of each month | C29: 216.5
A30: AES Student Loan Payment (online) | B30: 26th of each month | C30: 244.92
A31: Entergy Payment (automatic) | B31: 27th of each month | C31: 220.18
A32: Allstate Payment (automatic) | B32: 28th of each month | C32: 197.29 | F32: Average for two week span
A33: Firstmark Services loan(automatic) | B33: 28th of each month | C33: 258.24 | F33: =(H8+H11)/2 -> 928.055
A35: Tahoe Payment | B35: 30th of each month | C35: 573
A36: Evan & Rep Daycare #4 (automatic) | B36: each Monday | C36: 209.6
A42: Loan Payoff Schedule
A43: Lauren | B43: Great Lakes -128.05
B44: Current Balance - 6310.75
B45: Balance as of November 2017 - 5680.75~
B46: Amount to pay each month - 838.40 + 128.05 = 966.45
B47: Months to pay off - ~6 months or November 2017 to April 2018
B49: Nelnet - 171.55 a month
B50: Current Balance - 9797.33
B51: Balance as of April 2018 - 8357.33
B52: Amount to pay each month - 966.45 + 171.55 = 1138.00
B53: Months to pay off - ~8 months April 2018 to December 2018
A57: Brian | B57: First Mark Services - 258.24
B58: Current Balance - 9819.47
B59: Balance as of December 2018 - 6014.27
B60: Amount to pay each month - 1138 + 258.24 = 1396.24
B61: Months to pay off - ~4 months December 2018 to April 2019
B63: Navient - 152.66
B64: Current Balance - 10417.53
B65: Balance as of April 2019 - 8377.53
B66: Amount to pay each month - 1396.24 + 152.66 = 1548.90
B67: Months to pay off - ~5 months April 2019 to September 2019
B69: AES - 244.92
B70: Current Balance - 41086.27
B71: Balance as of September 2019 - 39523.17
... B73: Months to pay off - ~22 months September 2019 to July 2021

Sheet March 2017
A1: March 2017 Monthly Budget
A2: Income: | B2: 1st half of month | C2: 2nd half of month
A3: Brian | B3: 2322.05 | C3: 2322.05
A4: Lauren | B4: 1223.79 | C4: 1223.79
A7: Expenses: | B7: Due Date: | C7: Expense Cost: | F7: what we make 1st half of month | G7: what we owe 1st half of month | H7: money left over
A8: 1st half of month: | F8: =B3+B4 -> 3545.84 | G8: =C9+C10+C11+C12+C13+C14+C15+C16+C17+C18+C19+C20+C21 -> 2817.63 | H8: =F8-G8 -> 728.21
A9: Evan & Rep Daycare #1 (automatic) | B9: each Monday | C9: 209.6
A10: New House Payment #1 (automatic) | B10: 1st of each month | C10: 1590.3 | F10: what we make 2nd half of month | G10: what we owe 2nd half of month | H10: money left over
A11: Vivint Payment(automatic) | B11: 3rd of each month | C11: 74.9 | F11: =B3+B4 -> 3545.84 | G11: =C24+C25+C26+C27+C28+C29+C30+C31+C32+C33+C34+C35+C36 -> 2418.91 | H11: =F11-G11 -> 1126.93
A12: Navient (automatic) | B12: 4th of each month | C12: 152.64
A13: Lowes payment | B13: 4th of each month | C13: 78
A14: Blizzard Payment (automatic) | B14: 5th of each month | C14: 14.99
A15: Synchrony bank | B15: 7th of each month | C15: 25
A16: Evan & Rep Daycare #2 (automatic) | B16: each Monday | C16: 209.6
A17: Great Lakes Student Loan(automatic) | B17: 9th of each month | C17: 128.05
A18: Conway Regional Bill(automatic) | B18: 10th of each month | C18: 68
A19: Direct TV (automatic) | B19: 11th of each month | C19: 95
A20: NelNet loan(automatic) | B20: 15th of each month | C20: 171.55
A21: US Bank Loan payment | B21: 16th of each month
A23: 2nd half of month:
A24: Evan & Rep Daycare #3 (automatic) | B24: each Monday | C24: 209.6
A25: Amazon payment | B25: 17th of each month | C25: 25
A26: Greenbrier Water, trash payment | B26: 18th of each month | C26: 28.13
A27: My Media3 internet | B27: 20th of each month | C27: 61
A28: At&t Payment (automatic) | B28: 22nd of each month | C28: 173.63
A29: Nissan Altima Payment | B29: 23rd of each month | C29: 216.5
A30: AES Student Loan Payment (online) | B30: 26th of each month | C30: 244.92
A31: Entergy Payment (automatic) | B31: 27th of each month | C31: 222
A32: Allstate Payment (automatic) | B32: 28th of each month | C32: 197.29 | F32: Average for two week span
A33: Firstmark Services loan(automatic) | B33: 28th of each month | C33: 258.24 | F33: =(H8+H11)/2 -> 927.57
A34: US Bank Loan payment | B34: 28th of each month
A35: Tahoe Payment | B35: 30th of each month | C35: 573
A36: Evan & Rep Daycare #4 (automatic) | B36: each Monday | C36: 209.6
A41: Check Information
A42: February 19th - 1st half of March
A43: March 4th - 2nd half of March
A44: March 18th - 1st half of April
A45: April 1st - Extra check!!!!
A46: April 15th - 2nd half of April
A47: April 29th - 1st half of May
A48: May 13th - 2nd half of May
A49: May 27th - 1st half June
A50: June 10th - 2nd half of June
A51: June 24th - 1st half of July
A52: July 8th - 2nd half of July
... A64: December 23rd - 1st half of January 2017

Sheet February 2017
A1: February 2017 Monthly Budget
A2: Income: | B2: 1st half of month | C2: 2nd half of month
A3: Brian | B3: 2322.05 | C3: 2322.05
A4: Lauren | B4: 1223.79 | C4: 1223.79
A7: Expenses: | B7: Due Date: | C7: Expense Cost: | F7: what we make 1st half of month | G7: what we owe 1st half of month | H7: money left over
A8: 1st half of month: | F8: =B3+B4 -> 3545.84 | G8: =C9+C10+C11+C12+C13+C14+C15+C16+C17+C18+C19+C20+C21 -> 2817.63 | H8: =F8-G8 -> 728.21
A9: Evan & Rep Daycare #1 (automatic) | B9: each Monday | C9: 209.6
A10: New House Payment #1 (automatic) | B10: 1st of each month | C10: 1590.3 | F10: what we make 2nd half of month | G10: what we owe 2nd half of month | H10: money left over
A11: Vivint Payment(automatic) | B11: 3rd of each month | C11: 74.9 | F11: =B3+B4 -> 3545.84 | G11: =C24+C25+C26+C27+C28+C29+C30+C31+C32+C33+C34+C35+C36 -> 2400.14 | H11: =F11-G11 -> 1145.7
A12: Navient (automatic) | B12: 4th of each month | C12: 152.64
A13: Lowes payment | B13: 4th of each month | C13: 78
A14: Blizzard Payment (automatic) | B14: 5th of each month | C14: 14.99
A15: Synchrony bank | B15: 7th of each month | C15: 25
A16: Evan & Rep Daycare #2 (automatic) | B16: each Monday | C16: 209.6
A17: Great Lakes Student Loan(automatic) | B17: 9th of each month | C17: 128.05
A18: Conway Regional Bill(automatic) | B18: 10th of each month | C18: 68
A19: Direct TV (automatic) | B19: 11th of each month | C19: 95
A20: NelNet loan(automatic) | B20: 15th of each month | C20: 171.55
A21: US Bank Loan payment | B21: 16th of each month
A23: 2nd half of month:
A24: Evan & Rep Daycare #3 (automatic) | B24: each Monday | C24: 209.6
A25: Amazon payment | B25: 17th of each month | C25: 25
A26: Greenbrier Water, trash payment | B26: 18th of each month | C26: 28.13
A27: My Media3 internet | B27: 20th of each month | C27: 61
A28: At&t Payment (automatic) | B28: 22nd of each month | C28: 173.63
A29: Nissan Altima Payment | B29: 23rd of each month | C29: 216.5
A30: AES Student Loan Payment (online) | B30: 26th of each month | C30: 244.92
A31: Entergy Payment (automatic) | B31: 27th of each month | C31: 217.07
A32: Allstate Payment (automatic) | B32: 28th of each month | C32: 188.4 | F32: Average for two week span
A33: Firstmark Services loan(automatic) | B33: 28th of each month | C33: 253.29 | F33: =(H8+H11)/2 -> 936.955
A34: US Bank Loan payment | B34: 28th of each month
A35: Tahoe Payment | B35: 30th of each month | C35: 573
A36: Evan & Rep Daycare #4 (automatic) | B36: each Monday | C36: 209.6
A41: Check Information
A42: February 19th - 1st half of March
A43: March 4th - 2nd half of March
A44: March 18th - 1st half of April
A45: April 1st - Extra check!!!!
A46: April 15th - 2nd half of April
A47: April 29th - 1st half of May
A48: May 13th - 2nd half of May
A49: May 27th - 1st half June
A50: June 10th - 2nd half of June
A51: June 24th - 1st half of July
A52: July 8th - 2nd half of July
... A64: December 23rd - 1st half of January 2017

Sheet January 2017
A1: January 2017 Monthly Budget
A2: Income: | B2: 1st half of month | C2: 2nd half of month
A3: Brian | B3: 2322.05 | C3: 2322.05
A4: Lauren | B4: 1223.79 | C4: 1223.79
A7: Expenses: | B7: Due Date: | C7: Expense Cost: | F7: what we make 1st half of month | G7: what we owe 1st half of month | H7: money left over
A8: 1st half of month: | F8: =B3+B4 -> 3545.84 | G8: =C9+C10+C11+C12+C13+C14+C15+C16+C17+C18+C19+C20+C21 -> 2817.63 | H8: =F8-G8 -> 728.21
A9: Evan & Rep Daycare #1 (automatic) | B9: each Monday | C9: 209.6
A10: New House Payment #1 (automatic) | B10: 1st of each month | C10: 1590.3 | F10: what we make 2nd half of month | G10: what we owe 2nd half of month | H10: money left over
A11: Vivint Payment(automatic) | B11: 3rd of each month | C11: 74.9 | F11: =B3+B4 -> 3545.84 | G11: =C24+C25+C26+C27+C28+C29+C30+C31+C32+C33+C34+C35+C36 -> 2314.81 | H11: =F11-G11 -> 1231.03
A12: Navient (automatic) | B12: 4th of each month | C12: 152.64
A13: Lowes payment | B13: 4th of each month | C13: 78
A14: Blizzard Payment (automatic) | B14: 5th of each month | C14: 14.99
A15: Synchrony bank | B15: 7th of each month | C15: 25
A16: Evan & Rep Daycare #2 (automatic) | B16: each Monday | C16: 209.6
A17: Great Lakes Student Loan(automatic) | B17: 9th of each month | C17: 128.05
A18: Conway Regional Bill(automatic) | B18: 10th of each month | C18: 68
A19: Direct TV (automatic) | B19: 11th of each month | C19: 95
A20: NelNet loan(automatic) | B20: 15th of each month | C20: 171.55
A21: US Bank Loan payment | B21: 16th of each month
A23: 2nd half of month:
A24: Evan & Rep Daycare #3 (automatic) | B24: each Monday | C24: 209.6
A25: Amazon payment | B25: 17th of each month | C25: 25
A26: Greenbrier Water, trash payment | B26: 18th of each month | C26: 28.13
A27: My Media3 internet | B27: 20th of each month | C27: 61
A28: At&t Payment (automatic) | B28: 22nd of each month | C28: 144.82
A29: Nissan Altima Payment | B29: 23rd of each month | C29: 216.5
A30: AES Student Loan Payment (online) | B30: 26th of each month | C30: 244.92
A31: Entergy Payment (automatic) | B31: 27th of each month | C31: 213.9
A32: Allstate Payment (automatic) | B32: 28th of each month | C32: 175.1 | F32: Average for two week span
A33: Firstmark Services loan(automatic) | B33: 28th of each month | C33: 258.24 | F33: =(H8+H11)/2 -> 979.62
A34: US Bank Loan payment | B34: 28th of each month
A35: Tahoe Payment | B35: 30th of each month | C35: 528
A36: Evan & Rep Daycare #4 (automatic) | B36: each Monday | C36: 209.6
A41: Check Information
A42: February 19th - 1st half of March
A43: March 4th - 2nd half of March
A44: March 18th - 1st half of April
A45: April 1st - Extra check!!!!
A46: April 15th - 2nd half of April
A47: April 29th - 1st half of May
A48: May 13th - 2nd half of May
A49: May 27th - 1st half June
A50: June 10th - 2nd half of June
A51: June 24th - 1st half of July
A52: July 8th - 2nd half of July
... A64: December 23rd - 1st half of January 2017

Sheet December 2016
A1: December 2016 Monthly Budget
A2: Income: | B2: 1st half of month | C2: 2nd half of month
A3: Brian | B3: 2383.66 | C3: 2383.66
A4: Lauren | B4: 1223.79 | C4: 1223.79
A7: Expenses: | B7: Due Date: | C7: Expense Cost: | F7: what we make 1st half of month | G7: what we owe 1st half of month | H7: money left over
A8: 1st half of month: | F8: =B3+B4 -> 3607.45 | G8: =C9+C10+C11+C12+C13+C14+C15+C16+C17+C18+C19+C20+C21 -> 2817.63 | H8: =F8-G8 -> 789.82
A9: Evan & Rep Daycare #1 (automatic) | B9: each Monday | C9: 209.6
A10: New House Payment #1 (automatic) | B10: 1st of each month | C10: 1590.3 | F10: what we make 2nd half of month | G10: what we owe 2nd half of month | H10: money left over
A11: Vivint Payment(automatic) | B11: 3rd of each month | C11: 74.9 | F11: =B3+B4 -> 3607.45 | G11: =C24+C25+C26+C27+C28+C29+C30+C31+C32+C33+C34+C35+C36 -> 2308.42 | H11: =F11-G11 -> 1299.03
A12: Navient (automatic) | B12: 4th of each month | C12: 152.64
A13: Lowes payment | B13: 4th of each month | C13: 78
A14: Blizzard Payment (automatic) | B14: 5th of each month | C14: 14.99
A15: Synchrony bank | B15: 7th of each month | C15: 25
A16: Evan & Rep Daycare #2 (automatic) | B16: each Monday | C16: 209.6
A17: Great Lakes Student Loan(automatic) | B17: 9th of each month | C17: 128.05
A18: Conway Regional Bill(automatic) | B18: 10th of each month | C18: 68
A19: Direct TV (automatic) | B19: 11th of each month | C19: 95
A20: NelNet loan(automatic) | B20: 15th of each month | C20: 171.55
A21: US Bank Loan payment | B21: 16th of each month
A23: 2nd half of month:
A24: Evan & Rep Daycare #3 (automatic) | B24: each Monday | C24: 209.6
A25: Amazon payment | B25: 17th of each month | C25: 25
A26: Greenbrier Water, trash payment | B26: 18th of each month | C26: 28.13
A27: My Media3 internet | B27: 20th of each month | C27: 61
A28: At&t Payment (automatic) | B28: 22nd of each month | C28: 144.82
A29: Nissan Altima Payment | B29: 23rd of each month | C29: 216.5
A30: AES Student Loan Payment (online) | B30: 26th of each month | C30: 244.92
A31: Entergy Payment (automatic) | B31: 27th of each month | C31: 212.53
A32: Allstate Payment (automatic) | B32: 28th of each month | C32: 175.1 | F32: Average for two week span
A33: FirstMark Loan Payment (automatic) | B33: 28th of each month | C33: 256.22 | F33: =(H8+H11)/2 -> 1044.425
A34: US Bank Loan payment | B34: 28th of each month
A35: Tahoe Payment | B35: 30th of each month | C35: 525
A36: Evan & Rep Daycare #4 (automatic) | B36: each Monday | C36: 209.6
A41: Check Information
A42: February 19th - 1st half of March
A43: March 4th - 2nd half of March
A44: March 18th - 1st half of April
A45: April 1st - Extra check!!!!
A46: April 15th - 2nd half of April
A47: April 29th - 1st half of May
A48: May 13th - 2nd half of May
A49: May 27th - 1st half June
A50: June 10th - 2nd half of June
A51: June 24th - 1st half of July
A52: July 8th - 2nd half of July
... A64: December 23rd - 1st half of January 2017

Sheet November 2016
A1: November 2016 Monthly Budget
A2: Income: | B2: 1st half of month | C2: 2nd half of month
A3: Brian | B3: 2383.66 | C3: 2383.66
A4: Lauren | B4: 1223.79 | C4: 1223.79
A7: Expenses: | B7: Due Date: | C7: Expense Cost: | F7: what we make 1st half of month | G7: what we owe 1st half of month | H7: money left over
A8: 1st half of month: | F8: =B3+B4 -> 3607.45 | G8: =C9+C10+C11+C12+C13+C14+C15+C16+C17+C18+C19+C20+C21 -> 2817.63 | H8: =F8-G8 -> 789.82
A9: Evan & Rep Daycare #1 (automatic) | B9: each Monday | C9: 209.6
A10: New House Payment #1 (automatic) | B10: 1st of each month | C10: 1590.3 | F10: what we make 2nd half of month | G10: what we owe 2nd half of month | H10: money left over
A11: Vivint Payment(automatic) | B11: 3rd of each month | C11: 74.9 | F11: =B3+B4 -> 3607.45 | G11: =C24+C25+C26+C27+C28+C29+C30+C31+C32+C33+C34+C35+C36 -> 2308.42 | H11: =F11-G11 -> 1299.03
A12: Navient (automatic) | B12: 4th of each month | C12: 152.64
A13: Lowes payment | B13: 4th of each month | C13: 78
A14: Blizzard Payment (automatic) | B14: 5th of each month | C14: 14.99
A15: Synchrony bank | B15: 7th of each month | C15: 25
A16: Evan & Rep Daycare #2 (automatic) | B16: each Monday | C16: 209.6
A17: Great Lakes Student Loan(automatic) | B17: 9th of each month | C17: 128.05
A18: Conway Regional Bill(automatic) | B18: 10th of each month | C18: 68
A19: Direct TV (automatic) | B19: 11th of each month | C19: 95
A20: US Bank Loan payment | B20: 16th of each month
A21: NelNet loan(automatic) | B21: 15th of each month | C21: 171.55
A23: 2nd half of month:
A24: Evan & Rep Daycare #3 (automatic) | B24: each Monday | C24: 209.6
A25: Tahoe Payment | B25: 30th of each month | C25: 525
A26: Nissan Altima Payment | B26: 23rd of each month | C26: 216.5
A27: Amazon payment | B27: 17th of each month | C27: 25
A28: Allstate Payment (automatic) | B28: 28th of each month | C28: 175.1
A29: Evan & Rep Daycare #4 (automatic) | B29: each Monday | C29: 209.6
A30: AES Student Loan Payment (online) | B30: 26th of each month | C30: 244.92 | F30: Average for two week span
A31: At&t Payment (automatic) | B31: 22nd of each month | C31: 144.82 | F31: =(H8+H11)/2 -> 1044.425
A32: Citi Student Loan Payment (automatic) | B32: 28th of each month | C32: 256.22
A33: Greenbrier Water, trash payment | B33: 18th of each month | C33: 28.13
A34: US Bank Loan payment | B34: 28th of each month
A35: My Media3 internet | B35: 20th of each month | C35: 61
A36: Entergy Payment (automatic) | B36: 27th of each month | C36: 212.53
A41: Check Information
A42: February 19th - 1st half of March
A43: March 4th - 2nd half of March
A44: March 18th - 1st half of April
A45: April 1st - Extra check!!!!
A46: April 15th - 2nd half of April
A47: April 29th - 1st half of May
A48: May 13th - 2nd half of May
A49: May 27th - 1st half June
A50: June 10th - 2nd half of June
A51: June 24th - 1st half of July
A52: July 8th - 2nd half of July
... A64: December 23rd - 1st half of January 2017

Sheet October 2016
A1: October 2016 Monthly Budget
A2: Income: | B2: 1st half of month | C2: 2nd half of month
A3: Brian | B3: 2383.66 | C3: 2383.66
A4: Lauren | B4: 1223.79 | C4: 1223.79
A7: Expenses: | B7: Due Date: | C7: Expense Cost: | F7: what we make 1st half of month | G7: what we owe 1st half of month | H7: money left over
A8: 1st half of month: | F8: =B3+B4 -> 3607.45 | G8: =C9+C10+C11+C12+C13+C14+C15+C16+C17+C18+C19+C20+C21 -> 2778.5 | H8: =F8-G8 -> 828.95
A9: Evan & Rep Daycare #1 (automatic) | B9: each Monday | C9: 209.6
A10: New House Payment #1 (automatic) | B10: 1st of each month | C10: 1551.17 | F10: what we make 2nd half of month | G10: what we owe 2nd half of month | H10: money left over
A11: Vivint Payment(automatic) | B11: 3rd of each month | C11: 74.9 | F11: =B3+B4 -> 3607.45 | G11: =C24+C25+C26+C27+C28+C29+C30+C31+C32+C33+C34+C35+C36 -> 2375.96 | H11: =F11-G11 -> 1231.49
A12: Navient (automatic) | B12: 4th of each month | C12: 152.64
A13: Lowes payment | B13: 4th of each month | C13: 78
A14: Blizzard Payment (automatic) | B14: 5th of each month | C14: 14.99
A15: Synchrony bank | B15: 7th of each month | C15: 25
A16: Evan & Rep Daycare #2 (automatic) | B16: each Monday | C16: 209.6
A17: Great Lakes Student Loan(automatic) | B17: 9th of each month | C17: 128.05
A18: Conway Regional Bill(automatic) | B18: 10th of each month | C18: 68
A19: Direct TV (automatic) | B19: 11th of each month | C19: 95
A20: US Bank Loan payment | B20: 16th of each month
A21: NelNet loan(automatic) | B21: 15th of each month | C21: 171.55
A23: 2nd half of month:
A24: Evan & Rep Daycare #3 (automatic) | B24: each Monday | C24: 209.6
A25: Tahoe Payment | B25: 30th of each month | C25: 525
A26: Nissan Altima Payment | B26: 23rd of each month | C26: 216.5
A27: Amazon payment | B27: 17th of each month | C27: 25
A28: Allstate Payment (automatic) | B28: 28th of each month | C28: 175.1
A29: Evan & Rep Daycare #4 (automatic) | B29: each Monday | C29: 209.6
A30: AES Student Loan Payment (online) | B30: 26th of each month | C30: 311.55 | F30: Average for two week span
A31: At&t Payment (automatic) | B31: 22nd of each month | C31: 144.82 | F31: =(H8+H11)/2 -> 1030.22
A32: Student Loan Payment (automatic) | B32: 28th of each month | C32: 256.22
A33: Greenbrier Water, trash payment | B33: 18th of each month | C33: 28.13
A34: US Bank Loan payment | B34: 28th of each month
A35: My Media3 internet | B35: 20th of each month | C35: 61
A36: Entergy Payment (automatic) | B36: 27th of each month | C36: 213.44
A41: Check Information
A42: February 19th - 1st half of March
A43: March 4th - 2nd half of March
A44: March 18th - 1st half of April
A45: April 1st - Extra check!!!!
A46: April 15th - 2nd half of April
A47: April 29th - 1st half of May
A48: May 13th - 2nd half of May
A49: May 27th - 1st half June
A50: June 10th - 2nd half of June
A51: June 24th - 1st half of July
A52: July 8th - 2nd half of July
... A64: December 23rd - 1st half of January 2017

Sheet September 2016
A1: September 2016 Monthly Budget
A2: Income: | B2: 1st half of month | C2: 2nd half of month
A3: Brian | B3: 2383.66 | C3: 2383.66
A4: Lauren | B4: 1223.79 | C4: 1223.79
A7: Expenses: | B7: Due Date: | C7: Expense Cost: | F7: what we make 1st half of month | G7: what we owe 1st half of month | H7: money left over
A8: 1st half of month: | F8: =B3+B4 -> 3607.45 | G8: =C9+C10+C11+C12+C13+C14+C15+C16+C17+C18+C19 -> 2848.26 | H8: =F8-G8 -> 759.19
A9: Evan & Rep Daycare #1 (automatic) | B9: each Monday | C9: 209.6
A10: New House Payment #1 (automatic) | B10: 1st of each month | C10: 1551.17 | F10: what we make 2nd half of month | G10: what we owe 2nd half of month | H10: money left over
A11: Vivint Payment(automatic) | B11: 3rd of each month | C11: 74.9 | F11: =B3+B4 -> 3607.45 | G11: =C22+C23+C24+C25+C26+C27+C28+C29+C30+C31+C32+C33 -> 2413.91 | H11: =F11-G11 -> 1193.54
A12: Navient (automatic) | B12: 4th of each month | C12: 152.64
A13: Blizzard Payment (automatic) | B13: 5th of each month | C13: 14.99
A14: Evan & Rep Daycare #2 (automatic) | B14: each Monday | C14: 209.6
A15: Great Lakes Student Loan(automatic) | B15: 9th of each month | C15: 128.05
A16: Conway Regional Bill(automatic) | B16: 10th of each month | C16: 68
A17: Direct TV (automatic) | B17: 11th of each month | C17: 87.76
A18: US Bank Loan payment | B18: 16th of each month | C18: 180
A19: NelNet loan(automatic) | B19: 15th of each month | C19: 171.55
A21: 2nd half of month:
A22: Evan & Rep Daycare #3 (automatic) | B22: each Monday | C22: 209.6
A23: Tahoe Payment | B23: 30th of each month | C23: 525
A24: Nissan Altima Payment | B24: 23rd of each month | C24: 216.5
A25: Allstate Payment (automatic) | B25: 28th of each month | C25: 71
A26: Evan & Rep Daycare #4 (automatic) | B26: each Monday | C26: 209.6
A27: AES Student Loan Payment (online) | B27: 26th of each month | C27: 311.55 | F27: Average for two week span
A28: At&t Payment (automatic) | B28: 22nd of each month | C28: 142 | F28: =(H8+H11)/2 -> 976.365
A29: Student Loan Payment (automatic) | B29: 28th of each month | C29: 256.22
A30: Greenbrier Water, trash payment | B30: 18th of each month | C30: 28.13
A31: US Bank Loan payment | B31: 28th of each month | C31: 180
A32: My Media3 internet | B32: 20th of each month | C32: 55.9
A33: Entergy Payment (automatic) | B33: 27th of each month | C33: 208.41
A38: Check Information
A39: February 19th - 1st half of March
A40: March 4th - 2nd half of March
A41: March 18th - 1st half of April
A42: April 1st - Extra check!!!!
A43: April 15th - 2nd half of April
A44: April 29th - 1st half of May
A45: May 13th - 2nd half of May
A46: May 27th - 1st half June
A47: June 10th - 2nd half of June
A48: June 24th - 1st half of July
A49: July 8th - 2nd half of July
... A61: December 23rd - 1st half of January 2017

Sheet August 2016
A1: August 2016 Monthly Budget
A2: Income: | B2: 1st half of month | C2: 2nd half of month
A3: Brian | B3: 2383.66 | C3: 2383.66
A4: Lauren | B4: 1223.79 | C4: 1223.79
A7: Expenses: | B7: Due Date: | C7: Expense Cost: | F7: what we make 1st half of month | G7: what we owe 1st half of month | H7: money left over
A8: 1st half of month: | F8: =B3+B4 -> 3607.45 | G8: =C9+C10+C11+C12+C13+C14+C15+C16+C17+C18+C19 -> 2581.75 | H8: =F8-G8 -> 1025.7
A9: Evan & Rep Daycare #1 (automatic) | B9: each Monday | C9: 209.6
A10: New House Payment #1 (automatic) | B10: 1st of each month | C10: 1215.17 | F10: what we make 2nd half of month | G10: what we owe 2nd half of month | H10: money left over
A11: Vivint Payment(automatic) | B11: 3rd of each month | C11: 74.9 | F11: =B3+B4 -> 3607.45 | G11: =C22+C23+C24+C25+C26+C27+C28+C29+C30+C31+C32+C33+C34 -> 2749.9 | H11: =F11-G11 -> 857.55
A12: Sallie Mae Payment (automatic) | B12: 4th of each month | C12: 151.23
A13: Blizzard Payment (automatic) | B13: 5th of each month | C13: 14.99
A14: Evan & Rep Daycare #2 (automatic) | B14: each Monday | C14: 209.6
A15: Great Lakes Student Loan(automatic) | B15: 9th of each month | C15: 128.05
A16: Conway Regional Bill(automatic) | B16: 10th of each month | C16: 68
A17: Direct TV (automatic) | B17: 11th of each month | C17: 158.66
A18: US Bank Loan payment | B18: 16th of each month | C18: 180
A19: NelNet loan(automatic) | B19: 15th of each month | C19: 171.55
A21: 2nd half of month:
A22: Evan & Rep Daycare #3 (automatic) | B22: each Monday | C22: 209.6
A23: New House Payment #2 (automatic) | B23: Used to break up house payment | C23: 336
A24: Tahoe Payment | B24: 30th of each month | C24: 525
A25: Nissan Altima Payment | B25: 23rd of each month | C25: 216.5
A26: Allstate Payment (automatic) | B26: 28th of each month | C26: 70.99
A27: Evan & Rep Daycare #4 (automatic) | B27: each Monday | C27: 209.6
A28: AES Student Loan Payment (online) | B28: 26th of each month | C28: 311.55 | F28: Average for two week span
A29: At&t Payment (automatic) | B29: 22nd of each month | C29: 142 | F29: =(H8+H11)/2 -> 941.625
A30: Student Loan Payment (automatic) | B30: 28th of each month | C30: 256.22
A31: Greenbrier Water, trash payment | B31: 18th of each month | C31: 28.13
A32: US Bank Loan payment | B32: 28th of each month | C32: 180
A33: My Media3 internet | B33: 20th of each month | C33: 55.9
A34: Entergy Payment (automatic) | B34: 27th of each month | C34: 208.41
A39: Check Information
A40: February 19th - 1st half of March
A41: March 4th - 2nd half of March
A42: March 18th - 1st half of April
A43: April 1st - Extra check!!!!
A44: April 15th - 2nd half of April
A45: April 29th - 1st half of May
A46: May 13th - 2nd half of May
A47: May 27th - 1st half June
A48: June 10th - 2nd half of June
A49: June 24th - 1st half of July
A50: July 8th - 2nd half of July
... A62: December 23rd - 1st half of January 2017

Sheet July 2016
A1: July 2016 Monthly Budget
A2: Income: | B2: 1st half of month | C2: 2nd half of month
A3: Brian | B3: 2383.66 | C3: 2383.66
A4: Lauren | B4: 1188.71 | C4: 1188.71
A7: Expenses: | B7: Due Date: | C7: Expense Cost: | F7: what we make 1st half of month | G7: what we owe 1st half of month | H7: money left over
A8: 1st half of month: | F8: =B3+B4 -> 3572.37 | G8: =C9+C10+C11+C12+C13+C14+C15+C16+C17+C18 -> 1982.55 | H8: =F8-G8 -> 1589.82
A9: Evan & Rep Daycare #1 (automatic) | B9: each Monday
A10: New House Payment #1 (automatic) | B10: 1st of each month | C10: 1215.17 | F10: what we make 2nd half of month | G10: what we owe 2nd half of month | H10: money left over
A11: Vivint Payment(automatic) | B11: 3rd of each month | C11: 74.9 | F11: =B3+B4 -> 3572.37 | G11: =C21+C22+C23+C24+C25+C26+C27+C28+C29+C30+C31+C32 -> 2231.69 | H11: =F11-G11 -> 1340.68
A12: Sallie Mae Payment (automatic) | B12: 4th of each month | C12: 151.23
A13: Blizzard Payment (automatic) | B13: 5th of each month | C13: 14.99
A14: Evan & Rep Daycare #2 (automatic) | B14: each Monday
A15: Great Lakes Student Loan(automatic) | B15: 9th of each month | C15: 128.05
A16: Conway Regional Bill(automatic) | B16: 10th of each month | C16: 68
A17: Direct TV (automatic) | B17: 11th of each month | C17: 158.66
A18: NelNet loan(automatic) | B18: 15th of each month | C18: 171.55
A20: 2nd half of month:
A21: Evan & Rep Daycare #3 (automatic) | B21: each Monday
A22: New House Payment #2 (automatic) | B22: Used to break up house payment | C22: 336
A23: Tahoe Payment | B23: 30th of each month | C23: 525
A24: Nissan Altima Payment | B24: 23rd of each month | C24: 216.5
A25: Allstate Car insurance | B25: 28th of each month | C25: 155.83
A26: Evan & Rep Daycare #4 (automatic) | B26: each Monday
A27: AES Student Loan Payment (online) | B27: 26th of each month | C27: 311.55 | F27: Average for two week span | H27: Money for Savings each check
A28: At&t Payment (automatic) | B28: 22nd of each month | C28: 142 | F28: =(H8+H11)/2 -> 1465.25 | H28: =F28-900 -> 565.25
A29: Student Loan Payment (automatic) | B29: 28th of each month | C29: 256.22
A30: Greenbrier Water, trash payment | B30: 18th of each month | C30: 28.13
A31: My Media3 internet | B31: 20th of each month | C31: 55.9
A32: Entergy Payment (automatic) | B32: 27th of each month | C32: 204.56
A37: Check Information
A38: February 19th - 1st half of March
A39: March 4th - 2nd half of March
A40: March 18th - 1st half of April
A41: April 1st - Extra check!!!!
A42: April 15th - 2nd half of April
A43: April 29th - 1st half of May
A44: May 13th - 2nd half of May
A45: May 27th - 1st half June
A46: June 10th - 2nd half of June
A47: June 24th - 1st half of July
A48: July 8th - 2nd half of July
... A60: December 23rd - 1st half of January 2017

Sheet June 2016
A1: June 2016 Monthly Budget
A2: Income: | B2: 1st half of month | C2: 2nd half of month
A3: Brian | B3: 2383.66 | C3: 2383.66
A4: Lauren | B4: 1188.71 | C4: 1188.71
A7: Expenses: | B7: Due Date: | C7: Expense Cost: | F7: what we make 1st half of month | G7: what we owe 1st half of month | H7: money left over
A8: 1st half of month: | F8: =B3+B4 -> 3572.37 | G8: =C9+C10+C11 -> 1514.77 | H8: =F8-G8 -> 2057.6
A9: New House Payment #1 (automatic) | B9: 1st of each month | C9: 1215.17
A10: Great Lakes Student Loan(automatic) | B10: 9th of each month | C10: 128.05 | F10: what we make 2nd half of month | G10: what we owe 2nd half of month | H10: money left over
A11: NelNet loan(automatic) | B11: 15th of each month | C11: 171.55 | F11: =B3+B4 -> 3572.37 | G11: =C14+C15+C16+C17+C18+C19+C20+C21+C22+C23+C24+C25+C26 -> 2325.53 | H11: =F11-G11 -> 1246.84
A13: 2nd half of month:
A14: New House Payment #2 (automatic) | B14: 1st of each month | C14: 336
A15: Tahoe Payment | B15: 30th of each month | C15: 525
A16: Nissan Altima Payment | B16: 23rd of each month | C16: 216.5
A17: Esurance Payment (automatic) | B17: 28th of each month | C17: 155.83
A18: Blizzard Payment (automatic) | B18: 5th of each month | C18: 14.99
A19: Vivint Payment(automatic) | B19: 3rd of each month | C19: 74.9
A20: At&t Payment (automatic) | B20: 22nd of each month | C20: 142
A21: Student Loan Payment (automatic) | B21: 28th of each month | C21: 256.22
A22: Sallie Mae Payment (automatic) | B22: 4th of each month | C22: 151.23
A23: Greenbrier Water, trash payment | B23: 18th of each month | C23: 28.13
A24: Direct TV (automatic) | B24: 11th of each month | C24: 158.66
A25: My Media3 internet | B25: 20th of each month | C25: 55.9 | F25: Average for two week span | H25: Money for Savings each check
A26: Entergy Payment (automatic) | B26: 27th of each month | C26: 210.17 | F26: =(H8+H11)/2 -> 1652.22 | H26: =F26-800 -> 852.22
A31: Check Information
A32: February 19th - 1st half of March
A33: March 4th - 2nd half of March
A34: March 18th - 1st half of April
A35: April 1st - Extra check!!!!
A36: April 15th - 2nd half of April
A37: April 29th - 1st half of May
A38: May 13th - 2nd half of May
A39: May 27th - 1st half June
A40: June 10th - 2nd half of June
A41: June 24th - 1st half of July
A42: July 8th - 2nd half of July
... A54: December 23rd - 1st half of January 2017

Sheet May 2016
A1: May 2016 Monthly Budget
A2: Income: | B2: 1st half of month | C2: 2nd half of month
A3: Brian | B3: 2383.66 | C3: 2383.66
A4: Lauren | B4: 1188.71 | C4: 1188.71
A7: Expenses: | B7: Due Date: | C7: Expense Cost: | F7: what we make 1st half of month | G7: what we owe 1st half of month | H7: money left over
A8: 1st half of month: | F8: =B3+B4 -> 3572.37 | G8: =C9+C10+C11+C12+C13 -> 1933.97 | H8: =F8-G8 -> 1638.4
A9: New House Payment #1 (automatic) | B9: 1st of each month | C9: 1215.17
A10: Evan & Rep Daycare #1 (automatic) | B10: each Monday | C10: 209.6 | F10: what we make 2nd half of month | G10: what we owe 2nd half of month | H10: money left over
A11: Edfinancial Loan(automatic) | B11: 9th of each month | C11: 128.05 | F11: =B3+B4 -> 3572.37 | G11: =C16+C17+C18+C19+C20+C21+C22+C23+C24+C25+C26+C27+C28+C29+C30 -> 2701.13 | H11: =F11-G11 -> 871.24
A12: NelNet loan(automatic) | B12: 15th of each month | C12: 171.55
A13: Evan & Rep Daycare #2 (automatic) | B13: each Monday | C13: 209.6
A15: 2nd half of month:
A16: New House Payment #2 (automatic) | B16: 1st of each month | C16: 336
A17: Tahoe Payment | B17: 30th of each month | C17: 525
A18: Nissan Altima Payment | B18: 23rd of each month | C18: 216.5
A19: Esurance Payment (automatic) | B19: 28th of each month | C19: 107.81
A20: Evan & Rep Daycare #3 (automatic) | B20: each Monday | C20: 209.6
A21: Blizzard Payment (automatic) | B21: 5th of each month | C21: 14.99
A22: Vivint Payment(automatic) | B22: 3rd of each month | C22: 74.9
A23: At&t Payment (automatic) | B23: 22nd of each month | C23: 142
A24: Evan & Rep Daycare #4 (automatic) | B24: each Monday | C24: 209.6
A25: Student Loan Payment (automatic) | B25: 28th of each month | C25: 256.22 | F25: Average for two week span | H25: Money for Savings each check
A26: Sallie Mae Payment (automatic) | B26: 4th of each month | C26: 151.23 | F26: =(H8+H11)/2 -> 1254.82 | H26: =F26-800 -> 454.82
A27: Greenbrier Water, trash payment | B27: 18th of each month | C27: 28.13
A28: Direct TV (automatic) | B28: 11th of each month | C28: 158.66
A29: Alliance Cable Company | B29: 20th of each month | C29: 55.9
A30: Entergy Payment (automatic) | B30: 27th of each month | C30: 214.59
A35: Check Information
A36: February 19th - 1st half of March
A37: March 4th - 2nd half of March
A38: March 18th - 1st half of April
A39: April 1st - Extra check!!!!
A40: April 15th - 2nd half of April
A41: April 29th - 1st half of May
A42: May 13th - 2nd half of May
A43: May 27th - 1st half June
A44: June 10th - 2nd half of June
A45: June 24th - 1st half of July
A46: July 8th - 2nd half of July
... A58: December 23rd - 1st half of January 2017

Sheet April 2016
A1: April 2016 Monthly Budget
A2: Income: | B2: 1st half of month | C2: 2nd half of month
A3: Brian | B3: 2293.6 | C3: 2293.61
A4: Lauren | B4: 1188.71 | C4: 1188.71
A7: Expenses: | B7: Due Date: | C7: Expense Cost: | F7: what we make 1st half of month | G7: what we owe 1st half of month | H7: money left over
A8: 1st half of month: | F8: =B3+B4 -> 3482.31 | G8: =C9+C10+C11+C12+C13 -> 1933.97 | H8: =F8-G8 -> 1548.34
A9: New House Payment #1 (automatic) | B9: 1st of each month | C9: 1215.17
